Workbook

Sheet Start Here
B2: Small Business Bookkeeping 2027
B3: Read me first - 3 minutes
B5: 1. SETUP: type your business name, tax set-aside %, mileage rate and your income / expense categories (blue cells).
B6: 2. INCOME: log every payment you receive. Category and payment method are drop-downs. The month fills in by itself.
B7: 3. EXPENSES: log every business purchase with its category. Mark it deductible (Y/N).
B8: 4. MILEAGE: log business trips. The deduction is calculated with your rate.
B9: 5. PROFIT & LOSS: your monthly and yearly profit and loss statement, by category - automatic.
B10: 6. DASHBOARD: income, expenses, net profit, margin, tax to set aside, charts - automatic.
B11: 7. QUARTERLY TAX: estimated tax to set aside each quarter, with typical US due dates.
B13: Only type in blue-shaded cells. White cells contain formulas.
B14: Works in Google Sheets (upload to Drive, then Open with Google Sheets) and Excel 2016 / Microsoft 365.
B15: Sample data is included so you can see it working. Select the blue cells and press Delete when you are ready.
B17: This is a general bookkeeping tool, not tax or legal advice. Check rates and deadlines with your accountant.

Sheet Setup
B2: Setup
B3: Your business details and categories
B5: Business name | C5: Bright Home Services LLC
B6: Year | C6: 2027
B7: Tax set-aside % | C7: 0.25
B8: Mileage rate ($/mile) | C8: 0.7
B10: Income categories | E10: Expense categories
B11: Services | E11: Advertising
B12: Products | E12: Car & truck
B13: Subscriptions | E13: Contract labor
B14: Other income | E14: Insurance
E15: Legal & professional
E16: Office supplies
E17: Rent
E18: Repairs
E19: Supplies
E20: Software
E21: Phone & internet
E22: Travel
E23: Meals (50%)
E24: Bank & payment fees
E25: Education
E26: Other

Sheet Income
B2: Income
B3: Every payment you receive
B5: Date | C5: Client | D5: Category | E5: Reference | F5: Amount | G5: Payment method | H5: Month
B6: 46388 | C6: Miller family | D6: Services | E6: Invoice #1050 | F6: 125.28 | G6: Cash | H6: =IF(B6="","",TEXT(B6,"mmm"))
B7: 46390 | C7: Oak Street Dental | D7: Services | E7: Invoice #1049 | F7: 483.93 | G7: Bank transfer | H7: =IF(B7="","",TEXT(B7,"mmm"))
B8: 46392 | C8: J. Patel | D8: Products | E8: Invoice #1053 | F8: 115.44 | G8: Cash | H8: =IF(B8="","",TEXT(B8,"mmm"))
B9: 46393 | C9: J. Patel | D9: Services | E9: Invoice #1054 | F9: 172.06 | G9: Card | H9: =IF(B9="","",TEXT(B9,"mmm"))
B10: 46395 | C10: Miller family | D10: Products | E10: Invoice #1045 | F10: 186.86 | G10: Card | H10: =IF(B10="","",TEXT(B10,"mmm"))
B11: 46396 | C11: Greenway Offices | D11: Other income | E11: Invoice #1056 | F11: 119.06 | G11: Cash | H11: =IF(B11="","",TEXT(B11,"mmm"))
B12: 46397 | C12: Sunrise Realty | D12: Services | E12: Invoice #1042 | F12: 541.48 | G12: Bank transfer | H12: =IF(B12="","",TEXT(B12,"mmm"))
B13: 46398 | C13: Oak Street Dental | D13: Services | E13: Invoice #1052 | F13: 137.14 | G13: Bank transfer | H13: =IF(B13="","",TEXT(B13,"mmm"))
B14: 46401 | C14: Harbor Cafe | D14: Services | E14: Invoice #1055 | F14: 252.56 | G14: Bank transfer | H14: =IF(B14="","",TEXT(B14,"mmm"))
B15: 46401 | C15: Oak Street Dental | D15: Services | E15: Invoice #1051 | F15: 165.86 | G15: Check | H15: =IF(B15="","",TEXT(B15,"mmm"))
B16: 46402 | C16: Greenway Offices | D16: Services | E16: Invoice #1047 | F16: 298.78 | G16: Bank transfer | H16: =IF(B16="","",TEXT(B16,"mmm"))
B17: 46404 | C17: J. Patel | D17: Products | E17: Invoice #1046 | F17: 209.2 | G17: Bank transfer | H17: =IF(B17="","",TEXT(B17,"mmm"))
... B155: 46658 | C155: Miller family | D155: Subscriptions | E155: Invoice #1372 | F155: 464.57 | G155: Cash | H155: =IF(B155="","",TEXT(B155,"mmm"))
H156: =IF(B156="","",TEXT(B156,"mmm"))
H157: =IF(B157="","",TEXT(B157,"mmm"))
H158: =IF(B158="","",TEXT(B158,"mmm"))
H159: =IF(B159="","",TEXT(B159,"mmm"))
H160: =IF(B160="","",TEXT(B160,"mmm"))
H161: =IF(B161="","",TEXT(B161,"mmm"))
H162: =IF(B162="","",TEXT(B162,"mmm"))
H163: =IF(B163="","",TEXT(B163,"mmm"))
H164: =IF(B164="","",TEXT(B164,"mmm"))
H165: =IF(B165="","",TEXT(B165,"mmm"))
H166: =IF(B166="","",TEXT(B166,"mmm"))
H167: =IF(B167="","",TEXT(B167,"mmm"))
... H1500: =IF(B1500="","",TEXT(B1500,"mmm"))

Sheet Expenses
B2: Expenses
B3: Every business purchase
B5: Date | C5: Vendor | D5: Category | E5: Note | F5: Amount | G5: Deductible | H5: Month
B6: 46388 | C6: Liability insurance | D6: Insurance | E6: Monthly | F6: 145 | G6: Y | H6: =IF(B6="","",TEXT(B6,"mmm"))
B7: 46388 | C7: Mobile carrier | D7: Phone & internet | E7: Monthly | F7: 85 | G7: Y | H7: =IF(B7="","",TEXT(B7,"mmm"))
B8: 46388 | C8: Scheduling app | D8: Software | E8: Monthly | F8: 39 | G8: Y | H8: =IF(B8="","",TEXT(B8,"mmm"))
B9: 46389 | C9: Helper - weekend | D9: Contract labor | F9: 301.67 | G9: Y | H9: =IF(B9="","",TEXT(B9,"mmm"))
B10: 46392 | C10: Office store | D10: Office supplies | F10: 44.28 | G10: Y | H10: =IF(B10="","",TEXT(B10,"mmm"))
B11: 46394 | C11: Cleaning supply co | D11: Supplies | F11: 83.12 | G11: Y | H11: =IF(B11="","",TEXT(B11,"mmm"))
B12: 46395 | C12: Card processor | D12: Bank & payment fees | F12: 41.74 | G12: Y | H12: =IF(B12="","",TEXT(B12,"mmm"))
B13: 46396 | C13: Auto repair | D13: Car & truck | F13: 41.04 | G13: Y | H13: =IF(B13="","",TEXT(B13,"mmm"))
B14: 46398 | C14: Facebook Ads | D14: Advertising | F14: 58.96 | G14: Y | H14: =IF(B14="","",TEXT(B14,"mmm"))
B15: 46403 | C15: Gas station | D15: Car & truck | F15: 50.47 | G15: Y | H15: =IF(B15="","",TEXT(B15,"mmm"))
B16: 46403 | C16: Local paper | D16: Advertising | F16: 84.86 | G16: Y | H16: =IF(B16="","",TEXT(B16,"mmm"))
B17: 46406 | C17: Cleaning supply co | D17: Supplies | F17: 112 | G17: Y | H17: =IF(B17="","",TEXT(B17,"mmm"))
B18: 46412 | C18: Auto repair | D18: Car & truck | F18: 56.94 | G18: Y | H18: =IF(B18="","",TEXT(B18,"mmm"))
B19: 46413 | C19: Cleaning supply co | D19: Supplies | F19: 77.51 | G19: Y | H19: =IF(B19="","",TEXT(B19,"mmm"))
B20: 46413 | C20: Client lunch | D20: Meals (50%) | F20: 52.57 | G20: Y | H20: =IF(B20="","",TEXT(B20,"mmm"))
B21: 46414 | C21: Auto repair | D21: Car & truck | F21: 64.87 | G21: Y | H21: =IF(B21="","",TEXT(B21,"mmm"))
B22: 46419 | C22: Liability insurance | D22: Insurance | E22: Monthly | F22: 145 | G22: Y | H22: =IF(B22="","",TEXT(B22,"mmm"))
B23: 46419 | C23: Mobile carrier | D23: Phone & internet | E23: Monthly | F23: 85 | G23: Y | H23: =IF(B23="","",TEXT(B23,"mmm"))
B24: 46419 | C24: Scheduling app | D24: Software | E24: Monthly | F24: 39 | G24: Y | H24: =IF(B24="","",TEXT(B24,"mmm"))
B25: 46420 | C25: Gas station | D25: Car & truck | F25: 55.02 | G25: Y | H25: =IF(B25="","",TEXT(B25,"mmm"))
B26: 46421 | C26: Card processor | D26: Bank & payment fees | F26: 49.45 | G26: Y | H26: =IF(B26="","",TEXT(B26,"mmm"))
B27: 46424 | C27: Facebook Ads | D27: Advertising | F27: 42.26 | G27: Y | H27: =IF(B27="","",TEXT(B27,"mmm"))
B28: 46433 | C28: Cleaning supply co | D28: Supplies | F28: 125.59 | G28: Y | H28: =IF(B28="","",TEXT(B28,"mmm"))
B29: 46438 | C29: Auto repair | D29: Car & truck | F29: 53.06 | G29: Y | H29: =IF(B29="","",TEXT(B29,"mmm"))
B30: 46438 | C30: Cleaning supply co | D30: Supplies | F30: 89.89 | G30: Y | H30: =IF(B30="","",TEXT(B30,"mmm"))
B31: 46441 | C31: Client lunch | D31: Meals (50%) | F31: 27.9 | G31: Y | H31: =IF(B31="","",TEXT(B31,"mmm"))
B32: 46441 | C32: Office store | D32: Office supplies | F32: 41.69 | G32: Y | H32: =IF(B32="","",TEXT(B32,"mmm"))
B33: 46442 | C33: Helper - weekend | D33: Contract labor | F33: 153.24 | G33: Y | H33: =IF(B33="","",TEXT(B33,"mmm"))
B34: 46443 | C34: Auto repair | D34: Car & truck | F34: 40.07 | G34: Y | H34: =IF(B34="","",TEXT(B34,"mmm"))
B35: 46446 | C35: Facebook Ads | D35: Advertising | F35: 79.33 | G35: Y | H35: =IF(B35="","",TEXT(B35,"mmm"))
B36: 46446 | C36: Gas station | D36: Car & truck | F36: 57.29 | G36: Y | H36: =IF(B36="","",TEXT(B36,"mmm"))
B37: 46446 | C37: Wholesale club | D37: Supplies | F37: 148.63 | G37: Y | H37: =IF(B37="","",TEXT(B37,"mmm"))
B38: 46447 | C38: CPA quarterly | D38: Legal & professional | E38: Monthly | F38: 120 | G38: Y | H38: =IF(B38="","",TEXT(B38,"mmm"))
B39: 46447 | C39: Liability insurance | D39: Insurance | E39: Monthly | F39: 145 | G39: Y | H39: =IF(B39="","",TEXT(B39,"mmm"))
B40: 46447 | C40: Mobile carrier | D40: Phone & internet | E40: Monthly | F40: 85 | G40: Y | H40: =IF(B40="","",TEXT(B40,"mmm"))
B41: 46447 | C41: Office store | D41: Office supplies | F41: 36.35 | G41: Y | H41: =IF(B41="","",TEXT(B41,"mmm"))
B42: 46447 | C42: Scheduling app | D42: Software | E42: Monthly | F42: 39 | G42: Y | H42: =IF(B42="","",TEXT(B42,"mmm"))
B43: 46450 | C43: Helper - weekend | D43: Contract labor | F43: 281.21 | G43: Y | H43: =IF(B43="","",TEXT(B43,"mmm"))
B44: 46453 | C44: Wholesale club | D44: Supplies | F44: 63.17 | G44: Y | H44: =IF(B44="","",TEXT(B44,"mmm"))
B45: 46459 | C45: Gas station | D45: Car & truck | F45: 54.47 | G45: Y | H45: =IF(B45="","",TEXT(B45,"mmm"))
B46: 46459 | C46: Local paper | D46: Advertising | F46: 74.8 | G46: Y | H46: =IF(B46="","",TEXT(B46,"mmm"))
B47: 46460 | C47: Auto repair | D47: Car & truck | F47: 40.51 | G47: Y | H47: =IF(B47="","",TEXT(B47,"mmm"))
B48: 46461 | C48: Cleaning supply co | D48: Supplies | F48: 44.47 | G48: Y | H48: =IF(B48="","",TEXT(B48,"mmm"))
B49: 46461 | C49: Gas station | D49: Car & truck | F49: 47.59 | G49: Y | H49: =IF(B49="","",TEXT(B49,"mmm"))
B50: 46462 | C50: Client lunch | D50: Meals (50%) | F50: 35.27 | G50: Y | H50: =IF(B50="","",TEXT(B50,"mmm"))
B51: 46468 | C51: Cleaning supply co | D51: Supplies | F51: 133.77 | G51: Y | H51: =IF(B51="","",TEXT(B51,"mmm"))
B52: 46468 | C52: Facebook Ads | D52: Advertising | F52: 36.35 | G52: Y | H52: =IF(B52="","",TEXT(B52,"mmm"))
B53: 46472 | C53: Card processor | D53: Bank & payment fees | F53: 62.89 | G53: Y | H53: =IF(B53="","",TEXT(B53,"mmm"))
B54: 46473 | C54: Auto repair | D54: Car & truck | F54: 46.06 | G54: Y | H54: =IF(B54="","",TEXT(B54,"mmm"))
B55: 46478 | C55: Liability insurance | D55: Insurance | E55: Monthly | F55: 145 | G55: Y | H55: =IF(B55="","",TEXT(B55,"mmm"))
B56: 46478 | C56: Mobile carrier | D56: Phone & internet | E56: Monthly | F56: 85 | G56: Y | H56: =IF(B56="","",TEXT(B56,"mmm"))
B57: 46478 | C57: Scheduling app | D57: Software | E57: Monthly | F57: 39 | G57: Y | H57: =IF(B57="","",TEXT(B57,"mmm"))
B58: 46480 | C58: Auto repair | D58: Car & truck | F58: 41.6 | G58: Y | H58: =IF(B58="","",TEXT(B58,"mmm"))
B59: 46480 | C59: Facebook Ads | D59: Advertising | F59: 38.45 | G59: Y | H59: =IF(B59="","",TEXT(B59,"mmm"))
B60: 46481 | C60: Card processor | D60: Bank & payment fees | F60: 63.72 | G60: Y | H60: =IF(B60="","",TEXT(B60,"mmm"))
B61: 46482 | C61: Wholesale club | D61: Supplies | F61: 115.33 | G61: Y | H61: =IF(B61="","",TEXT(B61,"mmm"))
B62: 46486 | C62: Auto repair | D62: Car & truck | F62: 60.33 | G62: Y | H62: =IF(B62="","",TEXT(B62,"mmm"))
B63: 46488 | C63: Local paper | D63: Advertising | F63: 79.61 | G63: Y | H63: =IF(B63="","",TEXT(B63,"mmm"))
B64: 46490 | C64: Client lunch | D64: Meals (50%) | F64: 54.29 | G64: Y | H64: =IF(B64="","",TEXT(B64,"mmm"))
B65: 46490 | C65: Gas station | D65: Car & truck | F65: 46.53 | G65: Y | H65: =IF(B65="","",TEXT(B65,"mmm"))
B66: 46495 | C66: Wholesale club | D66: Supplies | F66: 154.49 | G66: Y | H66: =IF(B66="","",TEXT(B66,"mmm"))
B67: 46496 | C67: Helper - weekend | D67: Contract labor | F67: 167.07 | G67: Y | H67: =IF(B67="","",TEXT(B67,"mmm"))
B68: 46500 | C68: Office store | D68: Office supplies | F68: 20.4 | G68: Y | H68: =IF(B68="","",TEXT(B68,"mmm"))
B69: 46502 | C69: Auto repair | D69: Car & truck | F69: 54.45 | G69: Y | H69: =IF(B69="","",TEXT(B69,"mmm"))
B70: 46505 | C70: Cleaning supply co | D70: Supplies | F70: 148.18 | G70: Y | H70: =IF(B70="","",TEXT(B70,"mmm"))
B71: 46508 | C71: Liability insurance | D71: Insurance | E71: Monthly | F71: 145 | G71: Y | H71: =IF(B71="","",TEXT(B71,"mmm"))
B72: 46508 | C72: Mobile carrier | D72: Phone & internet | E72: Monthly | F72: 85 | G72: Y | H72: =IF(B72="","",TEXT(B72,"mmm"))
B73: 46508 | C73: Scheduling app | D73: Software | E73: Monthly | F73: 39 | G73: Y | H73: =IF(B73="","",TEXT(B73,"mmm"))
B74: 46509 | C74: Cleaning supply co | D74: Supplies | F74: 158.49 | G74: Y | H74: =IF(B74="","",TEXT(B74,"mmm"))
B75: 46512 | C75: Gas station | D75: Car & truck | F75: 61.84 | G75: Y | H75: =IF(B75="","",TEXT(B75,"mmm"))
B76: 46514 | C76: Card processor | D76: Bank & payment fees | F76: 50.74 | G76: Y | H76: =IF(B76="","",TEXT(B76,"mmm"))
B77: 46514 | C77: Client lunch | D77: Meals (50%) | F77: 52.6 | G77: Y | H77: =IF(B77="","",TEXT(B77,"mmm"))
B78: 46518 | C78: Wholesale club | D78: Supplies | F78: 151.23 | G78: Y | H78: =IF(B78="","",TEXT(B78,"mmm"))
B79: 46521 | C79: Gas station | D79: Car & truck | F79: 60.44 | G79: Y | H79: =IF(B79="","",TEXT(B79,"mmm"))
B80: 46521 | C80: Wholesale club | D80: Supplies | F80: 132.54 | G80: Y | H80: =IF(B80="","",TEXT(B80,"mmm"))
B81: 46522 | C81: Office store | D81: Office supplies | F81: 31.72 | G81: Y | H81: =IF(B81="","",TEXT(B81,"mmm"))
B82: 46527 | C82: Auto repair | D82: Car & truck | F82: 69.37 | G82: Y | H82: =IF(B82="","",TEXT(B82,"mmm"))
B83: 46527 | C83: Facebook Ads | D83: Advertising | F83: 45.64 | G83: Y | H83: =IF(B83="","",TEXT(B83,"mmm"))
B84: 46533 | C84: Facebook Ads | D84: Advertising | F84: 69.61 | G84: Y | H84: =IF(B84="","",TEXT(B84,"mmm"))
B85: 46534 | C85: Auto repair | D85: Car & truck | F85: 51.9 | G85: Y | H85: =IF(B85="","",TEXT(B85,"mmm"))
B86: 46534 | C86: Helper - weekend | D86: Contract labor | F86: 253.94 | G86: Y | H86: =IF(B86="","",TEXT(B86,"mmm"))
B87: 46539 | C87: CPA quarterly | D87: Legal & professional | E87: Monthly | F87: 120 | G87: Y | H87: =IF(B87="","",TEXT(B87,"mmm"))
B88: 46539 | C88: Gas station | D88: Car & truck | F88: 62.18 | G88: Y | H88: =IF(B88="","",TEXT(B88,"mmm"))
B89: 46539 | C89: Liability insurance | D89: Insurance | E89: Monthly | F89: 145 | G89: Y | H89: =IF(B89="","",TEXT(B89,"mmm"))
B90: 46539 | C90: Mobile carrier | D90: Phone & internet | E90: Monthly | F90: 85 | G90: Y | H90: =IF(B90="","",TEXT(B90,"mmm"))
B91: 46539 | C91: Scheduling app | D91: Software | E91: Monthly | F91: 39 | G91: Y | H91: =IF(B91="","",TEXT(B91,"mmm"))
B92: 46542 | C92: Local paper | D92: Advertising | F92: 88.41 | G92: Y | H92: =IF(B92="","",TEXT(B92,"mmm"))
B93: 46543 | C93: Card processor | D93: Bank & payment fees | F93: 71.64 | G93: Y | H93: =IF(B93="","",TEXT(B93,"mmm"))
B94: 46543 | C94: Gas station | D94: Car & truck | F94: 51.73 | G94: Y | H94: =IF(B94="","",TEXT(B94,"mmm"))
B95: 46544 | C95: Wholesale club | D95: Supplies | F95: 131.98 | G95: Y | H95: =IF(B95="","",TEXT(B95,"mmm"))
B96: 46545 | C96: Gas station | D96: Car & truck | F96: 54.86 | G96: Y | H96: =IF(B96="","",TEXT(B96,"mmm"))
B97: 46547 | C97: Client lunch | D97: Meals (50%) | F97: 56.83 | G97: Y | H97: =IF(B97="","",TEXT(B97,"mmm"))
B98: 46548 | C98: Cleaning supply co | D98: Supplies | F98: 82.31 | G98: Y | H98: =IF(B98="","",TEXT(B98,"mmm"))
B99: 46552 | C99: Auto repair | D99: Car & truck | F99: 46.52 | G99: Y | H99: =IF(B99="","",TEXT(B99,"mmm"))
B100: 46555 | C100: Cleaning supply co | D100: Supplies | F100: 108.9 | G100: Y | H100: =IF(B100="","",TEXT(B100,"mmm"))
B101: 46556 | C101: Office store | D101: Office supplies | F101: 31.81 | G101: Y | H101: =IF(B101="","",TEXT(B101,"mmm"))
B102: 46565 | C102: Helper - weekend | D102: Contract labor | F102: 252.26 | G102: Y | H102: =IF(B102="","",TEXT(B102,"mmm"))
...

Sheet Mileage
B2: Mileage Log
B3: Business trips and deduction
B5: Date | C5: Purpose | D5: Client / place | E5: Miles | F5: Deduction | G5: Month | I5: Total miles | J5: Total deduction
B6: 46388 | C6: Supply run | D6: L. Thompson | E6: 15.9 | F6: =IF(E6="","",E6*Setup!$C$8) | G6: =IF(B6="","",TEXT(B6,"mmm")) | I6: =SUM(E6:E599) | J6: =SUM(F6:F599)
B7: 46394 | C7: Supply run | D7: Miller family | E7: 12.3 | F7: =IF(E7="","",E7*Setup!$C$8) | G7: =IF(B7="","",TEXT(B7,"mmm"))
B8: 46395 | C8: Client job | D8: Miller family | E8: 26.8 | F8: =IF(E8="","",E8*Setup!$C$8) | G8: =IF(B8="","",TEXT(B8,"mmm"))
B9: 46397 | C9: Estimate visit | D9: L. Thompson | E9: 36.8 | F9: =IF(E9="","",E9*Setup!$C$8) | G9: =IF(B9="","",TEXT(B9,"mmm"))
B10: 46403 | C10: Client job | D10: R. Nguyen | E10: 34.1 | F10: =IF(E10="","",E10*Setup!$C$8) | G10: =IF(B10="","",TEXT(B10,"mmm"))
B11: 46408 | C11: Estimate visit | D11: J. Patel | E11: 23.1 | F11: =IF(E11="","",E11*Setup!$C$8) | G11: =IF(B11="","",TEXT(B11,"mmm"))
B12: 46410 | C12: Estimate visit | D12: J. Patel | E12: 7.5 | F12: =IF(E12="","",E12*Setup!$C$8) | G12: =IF(B12="","",TEXT(B12,"mmm"))
B13: 46414 | C13: Supply run | D13: R. Nguyen | E13: 6.5 | F13: =IF(E13="","",E13*Setup!$C$8) | G13: =IF(B13="","",TEXT(B13,"mmm"))
B14: 46425 | C14: Supply run | D14: Sunrise Realty | E14: 29 | F14: =IF(E14="","",E14*Setup!$C$8) | G14: =IF(B14="","",TEXT(B14,"mmm"))
B15: 46426 | C15: Supply run | D15: Oak Street Dental | E15: 28.7 | F15: =IF(E15="","",E15*Setup!$C$8) | G15: =IF(B15="","",TEXT(B15,"mmm"))
B16: 46426 | C16: Supply run | D16: Sunrise Realty | E16: 27.3 | F16: =IF(E16="","",E16*Setup!$C$8) | G16: =IF(B16="","",TEXT(B16,"mmm"))
B17: 46427 | C17: Client job | D17: Oak Street Dental | E17: 20.8 | F17: =IF(E17="","",E17*Setup!$C$8) | G17: =IF(B17="","",TEXT(B17,"mmm"))
B18: 46427 | C18: Supply run | D18: Sunrise Realty | E18: 16.7 | F18: =IF(E18="","",E18*Setup!$C$8) | G18: =IF(B18="","",TEXT(B18,"mmm"))
... B77: 46657 | C77: Supply run | D77: R. Nguyen | E77: 8.7 | F77: =IF(E77="","",E77*Setup!$C$8) | G77: =IF(B77="","",TEXT(B77,"mmm"))
F78: =IF(E78="","",E78*Setup!$C$8) | G78: =IF(B78="","",TEXT(B78,"mmm"))
F79: =IF(E79="","",E79*Setup!$C$8) | G79: =IF(B79="","",TEXT(B79,"mmm"))
F80: =IF(E80="","",E80*Setup!$C$8) | G80: =IF(B80="","",TEXT(B80,"mmm"))
F81: =IF(E81="","",E81*Setup!$C$8) | G81: =IF(B81="","",TEXT(B81,"mmm"))
F82: =IF(E82="","",E82*Setup!$C$8) | G82: =IF(B82="","",TEXT(B82,"mmm"))
F83: =IF(E83="","",E83*Setup!$C$8) | G83: =IF(B83="","",TEXT(B83,"mmm"))
F84: =IF(E84="","",E84*Setup!$C$8) | G84: =IF(B84="","",TEXT(B84,"mmm"))
F85: =IF(E85="","",E85*Setup!$C$8) | G85: =IF(B85="","",TEXT(B85,"mmm"))
F86: =IF(E86="","",E86*Setup!$C$8) | G86: =IF(B86="","",TEXT(B86,"mmm"))
F87: =IF(E87="","",E87*Setup!$C$8) | G87: =IF(B87="","",TEXT(B87,"mmm"))
F88: =IF(E88="","",E88*Setup!$C$8) | G88: =IF(B88="","",TEXT(B88,"mmm"))
F89: =IF(E89="","",E89*Setup!$C$8) | G89: =IF(B89="","",TEXT(B89,"mmm"))
... F599: =IF(E599="","",E599*Setup!$C$8) | G599: =IF(B599="","",TEXT(B599,"mmm"))

Sheet Profit & Loss
B2: Profit & Loss Statement
B3: Monthly and year to date
B5: Category | C5: Jan | D5: Feb | E5: Mar | F5: Apr | G5: May | H5: Jun | I5: Jul | J5: Aug | K5: Sep | L5: Oct | M5: Nov | N5: Dec | O5: Year total
B6: INCOME
B7: =IF(Setup!B11="","",Setup!B11) | C7: =IF($B7="","",SUMIFS(Income!$F$6:$F$1500,Income!$D$6:$D$1500,$B7,Income!$H$6:$H$1500,C$5)) | D7: =IF($B7="","",SUMIFS(Income!$F$6:$F$1500,Income!$D$6:$D$1500,$B7,Income!$H$6:$H$1500,D$5)) | E7: =IF($B7="","",SUMIFS(Income!$F$6:$F$1500,Income!$D$6:$D$1500,$B7,Income!$H$6:$H$1500,E$5)) | F7: =IF($B7="","",SUMIFS(Income!$F$6:$F$1500,Income!$D$6:$D$1500,$B7,Income!$H$6:$H$1500,F$5)) | G7: =IF($B7="","",SUMIFS(Income!$F$6:$F$1500,Income!$D$6:$D$1500,$B7,Income!$H$6:$H$1500,G$5)) | H7: =IF($B7="","",SUMIFS(Income!$F$6:$F$1500,Income!$D$6:$D$1500,$B7,Income!$H$6:$H$1500,H$5)) | I7: =IF($B7="","",SUMIFS(Income!$F$6:$F$1500,Income!$D$6:$D$1500,$B7,Income!$H$6:$H$1500,I$5)) | J7: =IF($B7="","",SUMIFS(Income!$F$6:$F$1500,Income!$D$6:$D$1500,$B7,Income!$H$6:$H$1500,J$5)) | ... N7: =IF($B7="","",SUMIFS(Income!$F$6:$F$1500,Income!$D$6:$D$1500,$B7,Income!$H$6:$H$1500,N$5)) | O7: =IF(B7="","",SUM(C7:N7))
B8: =IF(Setup!B12="","",Setup!B12) | C8: =IF($B8="","",SUMIFS(Income!$F$6:$F$1500,Income!$D$6:$D$1500,$B8,Income!$H$6:$H$1500,C$5)) | D8: =IF($B8="","",SUMIFS(Income!$F$6:$F$1500,Income!$D$6:$D$1500,$B8,Income!$H$6:$H$1500,D$5)) | E8: =IF($B8="","",SUMIFS(Income!$F$6:$F$1500,Income!$D$6:$D$1500,$B8,Income!$H$6:$H$1500,E$5)) | F8: =IF($B8="","",SUMIFS(Income!$F$6:$F$1500,Income!$D$6:$D$1500,$B8,Income!$H$6:$H$1500,F$5)) | G8: =IF($B8="","",SUMIFS(Income!$F$6:$F$1500,Income!$D$6:$D$1500,$B8,Income!$H$6:$H$1500,G$5)) | H8: =IF($B8="","",SUMIFS(Income!$F$6:$F$1500,Income!$D$6:$D$1500,$B8,Income!$H$6:$H$1500,H$5)) | I8: =IF($B8="","",SUMIFS(Income!$F$6:$F$1500,Income!$D$6:$D$1500,$B8,Income!$H$6:$H$1500,I$5)) | J8: =IF($B8="","",SUMIFS(Income!$F$6:$F$1500,Income!$D$6:$D$1500,$B8,Income!$H$6:$H$1500,J$5)) | ... N8: =IF($B8="","",SUMIFS(Income!$F$6:$F$1500,Income!$D$6:$D$1500,$B8,Income!$H$6:$H$1500,N$5)) | O8: =IF(B8="","",SUM(C8:N8))
B9: =IF(Setup!B13="","",Setup!B13) | C9: =IF($B9="","",SUMIFS(Income!$F$6:$F$1500,Income!$D$6:$D$1500,$B9,Income!$H$6:$H$1500,C$5)) | D9: =IF($B9="","",SUMIFS(Income!$F$6:$F$1500,Income!$D$6:$D$1500,$B9,Income!$H$6:$H$1500,D$5)) | E9: =IF($B9="","",SUMIFS(Income!$F$6:$F$1500,Income!$D$6:$D$1500,$B9,Income!$H$6:$H$1500,E$5)) | F9: =IF($B9="","",SUMIFS(Income!$F$6:$F$1500,Income!$D$6:$D$1500,$B9,Income!$H$6:$H$1500,F$5)) | G9: =IF($B9="","",SUMIFS(Income!$F$6:$F$1500,Income!$D$6:$D$1500,$B9,Income!$H$6:$H$1500,G$5)) | H9: =IF($B9="","",SUMIFS(Income!$F$6:$F$1500,Income!$D$6:$D$1500,$B9,Income!$H$6:$H$1500,H$5)) | I9: =IF($B9="","",SUMIFS(Income!$F$6:$F$1500,Income!$D$6:$D$1500,$B9,Income!$H$6:$H$1500,I$5)) | J9: =IF($B9="","",SUMIFS(Income!$F$6:$F$1500,Income!$D$6:$D$1500,$B9,Income!$H$6:$H$1500,J$5)) | ... N9: =IF($B9="","",SUMIFS(Income!$F$6:$F$1500,Income!$D$6:$D$1500,$B9,Income!$H$6:$H$1500,N$5)) | O9: =IF(B9="","",SUM(C9:N9))
B10: =IF(Setup!B14="","",Setup!B14) | C10: =IF($B10="","",SUMIFS(Income!$F$6:$F$1500,Income!$D$6:$D$1500,$B10,Income!$H$6:$H$1500,C$5)) | D10: =IF($B10="","",SUMIFS(Income!$F$6:$F$1500,Income!$D$6:$D$1500,$B10,Income!$H$6:$H$1500,D$5)) | E10: =IF($B10="","",SUMIFS(Income!$F$6:$F$1500,Income!$D$6:$D$1500,$B10,Income!$H$6:$H$1500,E$5)) | F10: =IF($B10="","",SUMIFS(Income!$F$6:$F$1500,Income!$D$6:$D$1500,$B10,Income!$H$6:$H$1500,F$5)) | G10: =IF($B10="","",SUMIFS(Income!$F$6:$F$1500,Income!$D$6:$D$1500,$B10,Income!$H$6:$H$1500,G$5)) | H10: =IF($B10="","",SUMIFS(Income!$F$6:$F$1500,Income!$D$6:$D$1500,$B10,Income!$H$6:$H$1500,H$5)) | I10: =IF($B10="","",SUMIFS(Income!$F$6:$F$1500,Income!$D$6:$D$1500,$B10,Income!$H$6:$H$1500,I$5)) | J10: =IF($B10="","",SUMIFS(Income!$F$6:$F$1500,Income!$D$6:$D$1500,$B10,Income!$H$6:$H$1500,J$5)) | ... N10: =IF($B10="","",SUMIFS(Income!$F$6:$F$1500,Income!$D$6:$D$1500,$B10,Income!$H$6:$H$1500,N$5)) | O10: =IF(B10="","",SUM(C10:N10))
B11: =IF(Setup!B15="","",Setup!B15) | C11: =IF($B11="","",SUMIFS(Income!$F$6:$F$1500,Income!$D$6:$D$1500,$B11,Income!$H$6:$H$1500,C$5)) | D11: =IF($B11="","",SUMIFS(Income!$F$6:$F$1500,Income!$D$6:$D$1500,$B11,Income!$H$6:$H$1500,D$5)) | E11: =IF($B11="","",SUMIFS(Income!$F$6:$F$1500,Income!$D$6:$D$1500,$B11,Income!$H$6:$H$1500,E$5)) | F11: =IF($B11="","",SUMIFS(Income!$F$6:$F$1500,Income!$D$6:$D$1500,$B11,Income!$H$6:$H$1500,F$5)) | G11: =IF($B11="","",SUMIFS(Income!$F$6:$F$1500,Income!$D$6:$D$1500,$B11,Income!$H$6:$H$1500,G$5)) | H11: =IF($B11="","",SUMIFS(Income!$F$6:$F$1500,Income!$D$6:$D$1500,$B11,Income!$H$6:$H$1500,H$5)) | I11: =IF($B11="","",SUMIFS(Income!$F$6:$F$1500,Income!$D$6:$D$1500,$B11,Income!$H$6:$H$1500,I$5)) | J11: =IF($B11="","",SUMIFS(Income!$F$6:$F$1500,Income!$D$6:$D$1500,$B11,Income!$H$6:$H$1500,J$5)) | ... N11: =IF($B11="","",SUMIFS(Income!$F$6:$F$1500,Income!$D$6:$D$1500,$B11,Income!$H$6:$H$1500,N$5)) | O11: =IF(B11="","",SUM(C11:N11))
B12: =IF(Setup!B16="","",Setup!B16) | C12: =IF($B12="","",SUMIFS(Income!$F$6:$F$1500,Income!$D$6:$D$1500,$B12,Income!$H$6:$H$1500,C$5)) | D12: =IF($B12="","",SUMIFS(Income!$F$6:$F$1500,Income!$D$6:$D$1500,$B12,Income!$H$6:$H$1500,D$5)) | E12: =IF($B12="","",SUMIFS(Income!$F$6:$F$1500,Income!$D$6:$D$1500,$B12,Income!$H$6:$H$1500,E$5)) | F12: =IF($B12="","",SUMIFS(Income!$F$6:$F$1500,Income!$D$6:$D$1500,$B12,Income!$H$6:$H$1500,F$5)) | G12: =IF($B12="","",SUMIFS(Income!$F$6:$F$1500,Income!$D$6:$D$1500,$B12,Income!$H$6:$H$1500,G$5)) | H12: =IF($B12="","",SUMIFS(Income!$F$6:$F$1500,Income!$D$6:$D$1500,$B12,Income!$H$6:$H$1500,H$5)) | I12: =IF($B12="","",SUMIFS(Income!$F$6:$F$1500,Income!$D$6:$D$1500,$B12,Income!$H$6:$H$1500,I$5)) | J12: =IF($B12="","",SUMIFS(Income!$F$6:$F$1500,Income!$D$6:$D$1500,$B12,Income!$H$6:$H$1500,J$5)) | ... N12: =IF($B12="","",SUMIFS(Income!$F$6:$F$1500,Income!$D$6:$D$1500,$B12,Income!$H$6:$H$1500,N$5)) | O12: =IF(B12="","",SUM(C12:N12))
B13: =IF(Setup!B17="","",Setup!B17) | C13: =IF($B13="","",SUMIFS(Income!$F$6:$F$1500,Income!$D$6:$D$1500,$B13,Income!$H$6:$H$1500,C$5)) | D13: =IF($B13="","",SUMIFS(Income!$F$6:$F$1500,Income!$D$6:$D$1500,$B13,Income!$H$6:$H$1500,D$5)) | E13: =IF($B13="","",SUMIFS(Income!$F$6:$F$1500,Income!$D$6:$D$1500,$B13,Income!$H$6:$H$1500,E$5)) | F13: =IF($B13="","",SUMIFS(Income!$F$6:$F$1500,Income!$D$6:$D$1500,$B13,Income!$H$6:$H$1500,F$5)) | G13: =IF($B13="","",SUMIFS(Income!$F$6:$F$1500,Income!$D$6:$D$1500,$B13,Income!$H$6:$H$1500,G$5)) | H13: =IF($B13="","",SUMIFS(Income!$F$6:$F$1500,Income!$D$6:$D$1500,$B13,Income!$H$6:$H$1500,H$5)) | I13: =IF($B13="","",SUMIFS(Income!$F$6:$F$1500,Income!$D$6:$D$1500,$B13,Income!$H$6:$H$1500,I$5)) | J13: =IF($B13="","",SUMIFS(Income!$F$6:$F$1500,Income!$D$6:$D$1500,$B13,Income!$H$6:$H$1500,J$5)) | ... N13: =IF($B13="","",SUMIFS(Income!$F$6:$F$1500,Income!$D$6:$D$1500,$B13,Income!$H$6:$H$1500,N$5)) | O13: =IF(B13="","",SUM(C13:N13))
B14: =IF(Setup!B18="","",Setup!B18) | C14: =IF($B14="","",SUMIFS(Income!$F$6:$F$1500,Income!$D$6:$D$1500,$B14,Income!$H$6:$H$1500,C$5)) | D14: =IF($B14="","",SUMIFS(Income!$F$6:$F$1500,Income!$D$6:$D$1500,$B14,Income!$H$6:$H$1500,D$5)) | E14: =IF($B14="","",SUMIFS(Income!$F$6:$F$1500,Income!$D$6:$D$1500,$B14,Income!$H$6:$H$1500,E$5)) | F14: =IF($B14="","",SUMIFS(Income!$F$6:$F$1500,Income!$D$6:$D$1500,$B14,Income!$H$6:$H$1500,F$5)) | G14: =IF($B14="","",SUMIFS(Income!$F$6:$F$1500,Income!$D$6:$D$1500,$B14,Income!$H$6:$H$1500,G$5)) | H14: =IF($B14="","",SUMIFS(Income!$F$6:$F$1500,Income!$D$6:$D$1500,$B14,Income!$H$6:$H$1500,H$5)) | I14: =IF($B14="","",SUMIFS(Income!$F$6:$F$1500,Income!$D$6:$D$1500,$B14,Income!$H$6:$H$1500,I$5)) | J14: =IF($B14="","",SUMIFS(Income!$F$6:$F$1500,Income!$D$6:$D$1500,$B14,Income!$H$6:$H$1500,J$5)) | ... N14: =IF($B14="","",SUMIFS(Income!$F$6:$F$1500,Income!$D$6:$D$1500,$B14,Income!$H$6:$H$1500,N$5)) | O14: =IF(B14="","",SUM(C14:N14))
B15: =IF(Setup!B19="","",Setup!B19) | C15: =IF($B15="","",SUMIFS(Income!$F$6:$F$1500,Income!$D$6:$D$1500,$B15,Income!$H$6:$H$1500,C$5)) | D15: =IF($B15="","",SUMIFS(Income!$F$6:$F$1500,Income!$D$6:$D$1500,$B15,Income!$H$6:$H$1500,D$5)) | E15: =IF($B15="","",SUMIFS(Income!$F$6:$F$1500,Income!$D$6:$D$1500,$B15,Income!$H$6:$H$1500,E$5)) | F15: =IF($B15="","",SUMIFS(Income!$F$6:$F$1500,Income!$D$6:$D$1500,$B15,Income!$H$6:$H$1500,F$5)) | G15: =IF($B15="","",SUMIFS(Income!$F$6:$F$1500,Income!$D$6:$D$1500,$B15,Income!$H$6:$H$1500,G$5)) | H15: =IF($B15="","",SUMIFS(Income!$F$6:$F$1500,Income!$D$6:$D$1500,$B15,Income!$H$6:$H$1500,H$5)) | I15: =IF($B15="","",SUMIFS(Income!$F$6:$F$1500,Income!$D$6:$D$1500,$B15,Income!$H$6:$H$1500,I$5)) | J15: =IF($B15="","",SUMIFS(Income!$F$6:$F$1500,Income!$D$6:$D$1500,$B15,Income!$H$6:$H$1500,J$5)) | ... N15: =IF($B15="","",SUMIFS(Income!$F$6:$F$1500,Income!$D$6:$D$1500,$B15,Income!$H$6:$H$1500,N$5)) | O15: =IF(B15="","",SUM(C15:N15))
B16: =IF(Setup!B20="","",Setup!B20) | C16: =IF($B16="","",SUMIFS(Income!$F$6:$F$1500,Income!$D$6:$D$1500,$B16,Income!$H$6:$H$1500,C$5)) | D16: =IF($B16="","",SUMIFS(Income!$F$6:$F$1500,Income!$D$6:$D$1500,$B16,Income!$H$6:$H$1500,D$5)) | E16: =IF($B16="","",SUMIFS(Income!$F$6:$F$1500,Income!$D$6:$D$1500,$B16,Income!$H$6:$H$1500,E$5)) | F16: =IF($B16="","",SUMIFS(Income!$F$6:$F$1500,Income!$D$6:$D$1500,$B16,Income!$H$6:$H$1500,F$5)) | G16: =IF($B16="","",SUMIFS(Income!$F$6:$F$1500,Income!$D$6:$D$1500,$B16,Income!$H$6:$H$1500,G$5)) | H16: =IF($B16="","",SUMIFS(Income!$F$6:$F$1500,Income!$D$6:$D$1500,$B16,Income!$H$6:$H$1500,H$5)) | I16: =IF($B16="","",SUMIFS(Income!$F$6:$F$1500,Income!$D$6:$D$1500,$B16,Income!$H$6:$H$1500,I$5)) | J16: =IF($B16="","",SUMIFS(Income!$F$6:$F$1500,Income!$D$6:$D$1500,$B16,Income!$H$6:$H$1500,J$5)) | ... N16: =IF($B16="","",SUMIFS(Income!$F$6:$F$1500,Income!$D$6:$D$1500,$B16,Income!$H$6:$H$1500,N$5)) | O16: =IF(B16="","",SUM(C16:N16))
B17: Total income | C17: =SUM(C7:C16) | D17: =SUM(D7:D16) | E17: =SUM(E7:E16) | F17: =SUM(F7:F16) | G17: =SUM(G7:G16) | H17: =SUM(H7:H16) | I17: =SUM(I7:I16) | J17: =SUM(J7:J16) | ... O17: =SUM(O7:O16)
B19: EXPENSES
B20: =IF(Setup!E11="","",Setup!E11) | C20: =IF($B20="","",SUMIFS(Expenses!$F$6:$F$1500,Expenses!$D$6:$D$1500,$B20,Expenses!$H$6:$H$1500,C$5)) | D20: =IF($B20="","",SUMIFS(Expenses!$F$6:$F$1500,Expenses!$D$6:$D$1500,$B20,Expenses!$H$6:$H$1500,D$5)) | E20: =IF($B20="","",SUMIFS(Expenses!$F$6:$F$1500,Expenses!$D$6:$D$1500,$B20,Expenses!$H$6:$H$1500,E$5)) | F20: =IF($B20="","",SUMIFS(Expenses!$F$6:$F$1500,Expenses!$D$6:$D$1500,$B20,Expenses!$H$6:$H$1500,F$5)) | G20: =IF($B20="","",SUMIFS(Expenses!$F$6:$F$1500,Expenses!$D$6:$D$1500,$B20,Expenses!$H$6:$H$1500,G$5)) | H20: =IF($B20="","",SUMIFS(Expenses!$F$6:$F$1500,Expenses!$D$6:$D$1500,$B20,Expenses!$H$6:$H$1500,H$5)) | I20: =IF($B20="","",SUMIFS(Expenses!$F$6:$F$1500,Expenses!$D$6:$D$1500,$B20,Expenses!$H$6:$H$1500,I$5)) | J20: =IF($B20="","",SUMIFS(Expenses!$F$6:$F$1500,Expenses!$D$6:$D$1500,$B20,Expenses!$H$6:$H$1500,J$5)) | ... N20: =IF($B20="","",SUMIFS(Expenses!$F$6:$F$1500,Expenses!$D$6:$D$1500,$B20,Expenses!$H$6:$H$1500,N$5)) | O20: =IF(B20="","",SUM(C20:N20))
B21: =IF(Setup!E12="","",Setup!E12) | C21: =IF($B21="","",SUMIFS(Expenses!$F$6:$F$1500,Expenses!$D$6:$D$1500,$B21,Expenses!$H$6:$H$1500,C$5)) | D21: =IF($B21="","",SUMIFS(Expenses!$F$6:$F$1500,Expenses!$D$6:$D$1500,$B21,Expenses!$H$6:$H$1500,D$5)) | E21: =IF($B21="","",SUMIFS(Expenses!$F$6:$F$1500,Expenses!$D$6:$D$1500,$B21,Expenses!$H$6:$H$1500,E$5)) | F21: =IF($B21="","",SUMIFS(Expenses!$F$6:$F$1500,Expenses!$D$6:$D$1500,$B21,Expenses!$H$6:$H$1500,F$5)) | G21: =IF($B21="","",SUMIFS(Expenses!$F$6:$F$1500,Expenses!$D$6:$D$1500,$B21,Expenses!$H$6:$H$1500,G$5)) | H21: =IF($B21="","",SUMIFS(Expenses!$F$6:$F$1500,Expenses!$D$6:$D$1500,$B21,Expenses!$H$6:$H$1500,H$5)) | I21: =IF($B21="","",SUMIFS(Expenses!$F$6:$F$1500,Expenses!$D$6:$D$1500,$B21,Expenses!$H$6:$H$1500,I$5)) | J21: =IF($B21="","",SUMIFS(Expenses!$F$6:$F$1500,Expenses!$D$6:$D$1500,$B21,Expenses!$H$6:$H$1500,J$5)) | ... N21: =IF($B21="","",SUMIFS(Expenses!$F$6:$F$1500,Expenses!$D$6:$D$1500,$B21,Expenses!$H$6:$H$1500,N$5)) | O21: =IF(B21="","",SUM(C21:N21))
B22: =IF(Setup!E13="","",Setup!E13) | C22: =IF($B22="","",SUMIFS(Expenses!$F$6:$F$1500,Expenses!$D$6:$D$1500,$B22,Expenses!$H$6:$H$1500,C$5)) | D22: =IF($B22="","",SUMIFS(Expenses!$F$6:$F$1500,Expenses!$D$6:$D$1500,$B22,Expenses!$H$6:$H$1500,D$5)) | E22: =IF($B22="","",SUMIFS(Expenses!$F$6:$F$1500,Expenses!$D$6:$D$1500,$B22,Expenses!$H$6:$H$1500,E$5)) | F22: =IF($B22="","",SUMIFS(Expenses!$F$6:$F$1500,Expenses!$D$6:$D$1500,$B22,Expenses!$H$6:$H$1500,F$5)) | G22: =IF($B22="","",SUMIFS(Expenses!$F$6:$F$1500,Expenses!$D$6:$D$1500,$B22,Expenses!$H$6:$H$1500,G$5)) | H22: =IF($B22="","",SUMIFS(Expenses!$F$6:$F$1500,Expenses!$D$6:$D$1500,$B22,Expenses!$H$6:$H$1500,H$5)) | I22: =IF($B22="","",SUMIFS(Expenses!$F$6:$F$1500,Expenses!$D$6:$D$1500,$B22,Expenses!$H$6:$H$1500,I$5)) | J22: =IF($B22="","",SUMIFS(Expenses!$F$6:$F$1500,Expenses!$D$6:$D$1500,$B22,Expenses!$H$6:$H$1500,J$5)) | ... N22: =IF($B22="","",SUMIFS(Expenses!$F$6:$F$1500,Expenses!$D$6:$D$1500,$B22,Expenses!$H$6:$H$1500,N$5)) | O22: =IF(B22="","",SUM(C22:N22))
B23: =IF(Setup!E14="","",Setup!E14) | C23: =IF($B23="","",SUMIFS(Expenses!$F$6:$F$1500,Expenses!$D$6:$D$1500,$B23,Expenses!$H$6:$H$1500,C$5)) | D23: =IF($B23="","",SUMIFS(Expenses!$F$6:$F$1500,Expenses!$D$6:$D$1500,$B23,Expenses!$H$6:$H$1500,D$5)) | E23: =IF($B23="","",SUMIFS(Expenses!$F$6:$F$1500,Expenses!$D$6:$D$1500,$B23,Expenses!$H$6:$H$1500,E$5)) | F23: =IF($B23="","",SUMIFS(Expenses!$F$6:$F$1500,Expenses!$D$6:$D$1500,$B23,Expenses!$H$6:$H$1500,F$5)) | G23: =IF($B23="","",SUMIFS(Expenses!$F$6:$F$1500,Expenses!$D$6:$D$1500,$B23,Expenses!$H$6:$H$1500,G$5)) | H23: =IF($B23="","",SUMIFS(Expenses!$F$6:$F$1500,Expenses!$D$6:$D$1500,$B23,Expenses!$H$6:$H$1500,H$5)) | I23: =IF($B23="","",SUMIFS(Expenses!$F$6:$F$1500,Expenses!$D$6:$D$1500,$B23,Expenses!$H$6:$H$1500,I$5)) | J23: =IF($B23="","",SUMIFS(Expenses!$F$6:$F$1500,Expenses!$D$6:$D$1500,$B23,Expenses!$H$6:$H$1500,J$5)) | ... N23: =IF($B23="","",SUMIFS(Expenses!$F$6:$F$1500,Expenses!$D$6:$D$1500,$B23,Expenses!$H$6:$H$1500,N$5)) | O23: =IF(B23="","",SUM(C23:N23))
B24: =IF(Setup!E15="","",Setup!E15) | C24: =IF($B24="","",SUMIFS(Expenses!$F$6:$F$1500,Expenses!$D$6:$D$1500,$B24,Expenses!$H$6:$H$1500,C$5)) | D24: =IF($B24="","",SUMIFS(Expenses!$F$6:$F$1500,Expenses!$D$6:$D$1500,$B24,Expenses!$H$6:$H$1500,D$5)) | E24: =IF($B24="","",SUMIFS(Expenses!$F$6:$F$1500,Expenses!$D$6:$D$1500,$B24,Expenses!$H$6:$H$1500,E$5)) | F24: =IF($B24="","",SUMIFS(Expenses!$F$6:$F$1500,Expenses!$D$6:$D$1500,$B24,Expenses!$H$6:$H$1500,F$5)) | G24: =IF($B24="","",SUMIFS(Expenses!$F$6:$F$1500,Expenses!$D$6:$D$1500,$B24,Expenses!$H$6:$H$1500,G$5)) | H24: =IF($B24="","",SUMIFS(Expenses!$F$6:$F$1500,Expenses!$D$6:$D$1500,$B24,Expenses!$H$6:$H$1500,H$5)) | I24: =IF($B24="","",SUMIFS(Expenses!$F$6:$F$1500,Expenses!$D$6:$D$1500,$B24,Expenses!$H$6:$H$1500,I$5)) | J24: =IF($B24="","",SUMIFS(Expenses!$F$6:$F$1500,Expenses!$D$6:$D$1500,$B24,Expenses!$H$6:$H$1500,J$5)) | ... N24: =IF($B24="","",SUMIFS(Expenses!$F$6:$F$1500,Expenses!$D$6:$D$1500,$B24,Expenses!$H$6:$H$1500,N$5)) | O24: =IF(B24="","",SUM(C24:N24))
B25: =IF(Setup!E16="","",Setup!E16) | C25: =IF($B25="","",SUMIFS(Expenses!$F$6:$F$1500,Expenses!$D$6:$D$1500,$B25,Expenses!$H$6:$H$1500,C$5)) | D25: =IF($B25="","",SUMIFS(Expenses!$F$6:$F$1500,Expenses!$D$6:$D$1500,$B25,Expenses!$H$6:$H$1500,D$5)) | E25: =IF($B25="","",SUMIFS(Expenses!$F$6:$F$1500,Expenses!$D$6:$D$1500,$B25,Expenses!$H$6:$H$1500,E$5)) | F25: =IF($B25="","",SUMIFS(Expenses!$F$6:$F$1500,Expenses!$D$6:$D$1500,$B25,Expenses!$H$6:$H$1500,F$5)) | G25: =IF($B25="","",SUMIFS(Expenses!$F$6:$F$1500,Expenses!$D$6:$D$1500,$B25,Expenses!$H$6:$H$1500,G$5)) | H25: =IF($B25="","",SUMIFS(Expenses!$F$6:$F$1500,Expenses!$D$6:$D$1500,$B25,Expenses!$H$6:$H$1500,H$5)) | I25: =IF($B25="","",SUMIFS(Expenses!$F$6:$F$1500,Expenses!$D$6:$D$1500,$B25,Expenses!$H$6:$H$1500,I$5)) | J25: =IF($B25="","",SUMIFS(Expenses!$F$6:$F$1500,Expenses!$D$6:$D$1500,$B25,Expenses!$H$6:$H$1500,J$5)) | ... N25: =IF($B25="","",SUMIFS(Expenses!$F$6:$F$1500,Expenses!$D$6:$D$1500,$B25,Expenses!$H$6:$H$1500,N$5)) | O25: =IF(B25="","",SUM(C25:N25))
B26: =IF(Setup!E17="","",Setup!E17) | C26: =IF($B26="","",SUMIFS(Expenses!$F$6:$F$1500,Expenses!$D$6:$D$1500,$B26,Expenses!$H$6:$H$1500,C$5)) | D26: =IF($B26="","",SUMIFS(Expenses!$F$6:$F$1500,Expenses!$D$6:$D$1500,$B26,Expenses!$H$6:$H$1500,D$5)) | E26: =IF($B26="","",SUMIFS(Expenses!$F$6:$F$1500,Expenses!$D$6:$D$1500,$B26,Expenses!$H$6:$H$1500,E$5)) | F26: =IF($B26="","",SUMIFS(Expenses!$F$6:$F$1500,Expenses!$D$6:$D$1500,$B26,Expenses!$H$6:$H$1500,F$5)) | G26: =IF($B26="","",SUMIFS(Expenses!$F$6:$F$1500,Expenses!$D$6:$D$1500,$B26,Expenses!$H$6:$H$1500,G$5)) | H26: =IF($B26="","",SUMIFS(Expenses!$F$6:$F$1500,Expenses!$D$6:$D$1500,$B26,Expenses!$H$6:$H$1500,H$5)) | I26: =IF($B26="","",SUMIFS(Expenses!$F$6:$F$1500,Expenses!$D$6:$D$1500,$B26,Expenses!$H$6:$H$1500,I$5)) | J26: =IF($B26="","",SUMIFS(Expenses!$F$6:$F$1500,Expenses!$D$6:$D$1500,$B26,Expenses!$H$6:$H$1500,J$5)) | ... N26: =IF($B26="","",SUMIFS(Expenses!$F$6:$F$1500,Expenses!$D$6:$D$1500,$B26,Expenses!$H$6:$H$1500,N$5)) | O26: =IF(B26="","",SUM(C26:N26))
B27: =IF(Setup!E18="","",Setup!E18) | C27: =IF($B27="","",SUMIFS(Expenses!$F$6:$F$1500,Expenses!$D$6:$D$1500,$B27,Expenses!$H$6:$H$1500,C$5)) | D27: =IF($B27="","",SUMIFS(Expenses!$F$6:$F$1500,Expenses!$D$6:$D$1500,$B27,Expenses!$H$6:$H$1500,D$5)) | E27: =IF($B27="","",SUMIFS(Expenses!$F$6:$F$1500,Expenses!$D$6:$D$1500,$B27,Expenses!$H$6:$H$1500,E$5)) | F27: =IF($B27="","",SUMIFS(Expenses!$F$6:$F$1500,Expenses!$D$6:$D$1500,$B27,Expenses!$H$6:$H$1500,F$5)) | G27: =IF($B27="","",SUMIFS(Expenses!$F$6:$F$1500,Expenses!$D$6:$D$1500,$B27,Expenses!$H$6:$H$1500,G$5)) | H27: =IF($B27="","",SUMIFS(Expenses!$F$6:$F$1500,Expenses!$D$6:$D$1500,$B27,Expenses!$H$6:$H$1500,H$5)) | I27: =IF($B27="","",SUMIFS(Expenses!$F$6:$F$1500,Expenses!$D$6:$D$1500,$B27,Expenses!$H$6:$H$1500,I$5)) | J27: =IF($B27="","",SUMIFS(Expenses!$F$6:$F$1500,Expenses!$D$6:$D$1500,$B27,Expenses!$H$6:$H$1500,J$5)) | ... N27: =IF($B27="","",SUMIFS(Expenses!$F$6:$F$1500,Expenses!$D$6:$D$1500,$B27,Expenses!$H$6:$H$1500,N$5)) | O27: =IF(B27="","",SUM(C27:N27))
B28: =IF(Setup!E19="","",Setup!E19) | C28: =IF($B28="","",SUMIFS(Expenses!$F$6:$F$1500,Expenses!$D$6:$D$1500,$B28,Expenses!$H$6:$H$1500,C$5)) | D28: =IF($B28="","",SUMIFS(Expenses!$F$6:$F$1500,Expenses!$D$6:$D$1500,$B28,Expenses!$H$6:$H$1500,D$5)) | E28: =IF($B28="","",SUMIFS(Expenses!$F$6:$F$1500,Expenses!$D$6:$D$1500,$B28,Expenses!$H$6:$H$1500,E$5)) | F28: =IF($B28="","",SUMIFS(Expenses!$F$6:$F$1500,Expenses!$D$6:$D$1500,$B28,Expenses!$H$6:$H$1500,F$5)) | G28: =IF($B28="","",SUMIFS(Expenses!$F$6:$F$1500,Expenses!$D$6:$D$1500,$B28,Expenses!$H$6:$H$1500,G$5)) | H28: =IF($B28="","",SUMIFS(Expenses!$F$6:$F$1500,Expenses!$D$6:$D$1500,$B28,Expenses!$H$6:$H$1500,H$5)) | I28: =IF($B28="","",SUMIFS(Expenses!$F$6:$F$1500,Expenses!$D$6:$D$1500,$B28,Expenses!$H$6:$H$1500,I$5)) | J28: =IF($B28="","",SUMIFS(Expenses!$F$6:$F$1500,Expenses!$D$6:$D$1500,$B28,Expenses!$H$6:$H$1500,J$5)) | ... N28: =IF($B28="","",SUMIFS(Expenses!$F$6:$F$1500,Expenses!$D$6:$D$1500,$B28,Expenses!$H$6:$H$1500,N$5)) | O28: =IF(B28="","",SUM(C28:N28))
B29: =IF(Setup!E20="","",Setup!E20) | C29: =IF($B29="","",SUMIFS(Expenses!$F$6:$F$1500,Expenses!$D$6:$D$1500,$B29,Expenses!$H$6:$H$1500,C$5)) | D29: =IF($B29="","",SUMIFS(Expenses!$F$6:$F$1500,Expenses!$D$6:$D$1500,$B29,Expenses!$H$6:$H$1500,D$5)) | E29: =IF($B29="","",SUMIFS(Expenses!$F$6:$F$1500,Expenses!$D$6:$D$1500,$B29,Expenses!$H$6:$H$1500,E$5)) | F29: =IF($B29="","",SUMIFS(Expenses!$F$6:$F$1500,Expenses!$D$6:$D$1500,$B29,Expenses!$H$6:$H$1500,F$5)) | G29: =IF($B29="","",SUMIFS(Expenses!$F$6:$F$1500,Expenses!$D$6:$D$1500,$B29,Expenses!$H$6:$H$1500,G$5)) | H29: =IF($B29="","",SUMIFS(Expenses!$F$6:$F$1500,Expenses!$D$6:$D$1500,$B29,Expenses!$H$6:$H$1500,H$5)) | I29: =IF($B29="","",SUMIFS(Expenses!$F$6:$F$1500,Expenses!$D$6:$D$1500,$B29,Expenses!$H$6:$H$1500,I$5)) | J29: =IF($B29="","",SUMIFS(Expenses!$F$6:$F$1500,Expenses!$D$6:$D$1500,$B29,Expenses!$H$6:$H$1500,J$5)) | ... N29: =IF($B29="","",SUMIFS(Expenses!$F$6:$F$1500,Expenses!$D$6:$D$1500,$B29,Expenses!$H$6:$H$1500,N$5)) | O29: =IF(B29="","",SUM(C29:N29))
B30: =IF(Setup!E21="","",Setup!E21) | C30: =IF($B30="","",SUMIFS(Expenses!$F$6:$F$1500,Expenses!$D$6:$D$1500,$B30,Expenses!$H$6:$H$1500,C$5)) | D30: =IF($B30="","",SUMIFS(Expenses!$F$6:$F$1500,Expenses!$D$6:$D$1500,$B30,Expenses!$H$6:$H$1500,D$5)) | E30: =IF($B30="","",SUMIFS(Expenses!$F$6:$F$1500,Expenses!$D$6:$D$1500,$B30,Expenses!$H$6:$H$1500,E$5)) | F30: =IF($B30="","",SUMIFS(Expenses!$F$6:$F$1500,Expenses!$D$6:$D$1500,$B30,Expenses!$H$6:$H$1500,F$5)) | G30: =IF($B30="","",SUMIFS(Expenses!$F$6:$F$1500,Expenses!$D$6:$D$1500,$B30,Expenses!$H$6:$H$1500,G$5)) | H30: =IF($B30="","",SUMIFS(Expenses!$F$6:$F$1500,Expenses!$D$6:$D$1500,$B30,Expenses!$H$6:$H$1500,H$5)) | I30: =IF($B30="","",SUMIFS(Expenses!$F$6:$F$1500,Expenses!$D$6:$D$1500,$B30,Expenses!$H$6:$H$1500,I$5)) | J30: =IF($B30="","",SUMIFS(Expenses!$F$6:$F$1500,Expenses!$D$6:$D$1500,$B30,Expenses!$H$6:$H$1500,J$5)) | ... N30: =IF($B30="","",SUMIFS(Expenses!$F$6:$F$1500,Expenses!$D$6:$D$1500,$B30,Expenses!$H$6:$H$1500,N$5)) | O30: =IF(B30="","",SUM(C30:N30))
B31: =IF(Setup!E22="","",Setup!E22) | C31: =IF($B31="","",SUMIFS(Expenses!$F$6:$F$1500,Expenses!$D$6:$D$1500,$B31,Expenses!$H$6:$H$1500,C$5)) | D31: =IF($B31="","",SUMIFS(Expenses!$F$6:$F$1500,Expenses!$D$6:$D$1500,$B31,Expenses!$H$6:$H$1500,D$5)) | E31: =IF($B31="","",SUMIFS(Expenses!$F$6:$F$1500,Expenses!$D$6:$D$1500,$B31,Expenses!$H$6:$H$1500,E$5)) | F31: =IF($B31="","",SUMIFS(Expenses!$F$6:$F$1500,Expenses!$D$6:$D$1500,$B31,Expenses!$H$6:$H$1500,F$5)) | G31: =IF($B31="","",SUMIFS(Expenses!$F$6:$F$1500,Expenses!$D$6:$D$1500,$B31,Expenses!$H$6:$H$1500,G$5)) | H31: =IF($B31="","",SUMIFS(Expenses!$F$6:$F$1500,Expenses!$D$6:$D$1500,$B31,Expenses!$H$6:$H$1500,H$5)) | I31: =IF($B31="","",SUMIFS(Expenses!$F$6:$F$1500,Expenses!$D$6:$D$1500,$B31,Expenses!$H$6:$H$1500,I$5)) | J31: =IF($B31="","",SUMIFS(Expenses!$F$6:$F$1500,Expenses!$D$6:$D$1500,$B31,Expenses!$H$6:$H$1500,J$5)) | ... N31: =IF($B31="","",SUMIFS(Expenses!$F$6:$F$1500,Expenses!$D$6:$D$1500,$B31,Expenses!$H$6:$H$1500,N$5)) | O31: =IF(B31="","",SUM(C31:N31))
... B44: =IF(Setup!E35="","",Setup!E35) | C44: =IF($B44="","",SUMIFS(Expenses!$F$6:$F$1500,Expenses!$D$6:$D$1500,$B44,Expenses!$H$6:$H$1500,C$5)) | D44: =IF($B44="","",SUMIFS(Expenses!$F$6:$F$1500,Expenses!$D$6:$D$1500,$B44,Expenses!$H$6:$H$1500,D$5)) | E44: =IF($B44="","",SUMIFS(Expenses!$F$6:$F$1500,Expenses!$D$6:$D$1500,$B44,Expenses!$H$6:$H$1500,E$5)) | F44: =IF($B44="","",SUMIFS(Expenses!$F$6:$F$1500,Expenses!$D$6:$D$1500,$B44,Expenses!$H$6:$H$1500,F$5)) | G44: =IF($B44="","",SUMIFS(Expenses!$F$6:$F$1500,Expenses!$D$6:$D$1500,$B44,Expenses!$H$6:$H$1500,G$5)) | H44: =IF($B44="","",SUMIFS(Expenses!$F$6:$F$1500,Expenses!$D$6:$D$1500,$B44,Expenses!$H$6:$H$1500,H$5)) | I44: =IF($B44="","",SUMIFS(Expenses!$F$6:$F$1500,Expenses!$D$6:$D$1500,$B44,Expenses!$H$6:$H$1500,I$5)) | J44: =IF($B44="","",SUMIFS(Expenses!$F$6:$F$1500,Expenses!$D$6:$D$1500,$B44,Expenses!$H$6:$H$1500,J$5)) | ... N44: =IF($B44="","",SUMIFS(Expenses!$F$6:$F$1500,Expenses!$D$6:$D$1500,$B44,Expenses!$H$6:$H$1500,N$5)) | O44: =IF(B44="","",SUM(C44:N44))
B45: Mileage deduction | C45: =SUMIFS(Mileage!$F$6:$F$599,Mileage!$G$6:$G$599,C$5) | D45: =SUMIFS(Mileage!$F$6:$F$599,Mileage!$G$6:$G$599,D$5) | E45: =SUMIFS(Mileage!$F$6:$F$599,Mileage!$G$6:$G$599,E$5) | F45: =SUMIFS(Mileage!$F$6:$F$599,Mileage!$G$6:$G$599,F$5) | G45: =SUMIFS(Mileage!$F$6:$F$599,Mileage!$G$6:$G$599,G$5) | H45: =SUMIFS(Mileage!$F$6:$F$599,Mileage!$G$6:$G$599,H$5) | I45: =SUMIFS(Mileage!$F$6:$F$599,Mileage!$G$6:$G$599,I$5) | J45: =SUMIFS(Mileage!$F$6:$F$599,Mileage!$G$6:$G$599,J$5) | ... N45: =SUMIFS(Mileage!$F$6:$F$599,Mileage!$G$6:$G$599,N$5) | O45: =SUM(C45:N45)
B46: Total expenses | C46: =SUM(C20:C45) | D46: =SUM(D20:D45) | E46: =SUM(E20:E45) | F46: =SUM(F20:F45) | G46: =SUM(G20:G45) | H46: =SUM(H20:H45) | I46: =SUM(I20:I45) | J46: =SUM(J20:J45) | ... O46: =SUM(O20:O45)
B48: NET PROFIT | C48: =C17-C46 | D48: =D17-D46 | E48: =E17-E46 | F48: =F17-F46 | G48: =G17-G46 | H48: =H17-H46 | I48: =I17-I46 | J48: =J17-J46 | ... O48: =O17-O46
B49: Profit margin | C49: =IFERROR(C48/C17,"") | D49: =IFERROR(D48/D17,"") | E49: =IFERROR(E48/E17,"") | F49: =IFERROR(F48/F17,"") | G49: =IFERROR(G48/G17,"") | H49: =IFERROR(H48/H17,"") | I49: =IFERROR(I48/I17,"") | J49: =IFERROR(J48/J17,"") | ... O49: =IFERROR(O48/O17,"")

Sheet Dashboard
B2: Business Dashboard
B3: Year to date - updates automatically
B5: =Setup!C5
B7: INCOME | C7: EXPENSES | D7: NET PROFIT | E7: TAX TO SET ASIDE
B8: ='Profit & Loss'!O17 | C8: ='Profit & Loss'!O46 | D8: ='Profit & Loss'!O48 | E8: =MAX(0,'Profit & Loss'!O48)*Setup!C7
B10: Profit margin | C10: ='Profit & Loss'!O49
B11: Miles driven | C11: =Mileage!I6
B13: Month | C13: Income | D13: Expenses | E13: Net profit | G13: Top expense categories | H13: Year total
B14: Jan | C14: ='Profit & Loss'!C17 | D14: ='Profit & Loss'!C46 | E14: ='Profit & Loss'!C48 | G14: ='Profit & Loss'!B20 | H14: ='Profit & Loss'!O20
B15: Feb | C15: ='Profit & Loss'!D17 | D15: ='Profit & Loss'!D46 | E15: ='Profit & Loss'!D48 | G15: ='Profit & Loss'!B21 | H15: ='Profit & Loss'!O21
B16: Mar | C16: ='Profit & Loss'!E17 | D16: ='Profit & Loss'!E46 | E16: ='Profit & Loss'!E48 | G16: ='Profit & Loss'!B22 | H16: ='Profit & Loss'!O22
B17: Apr | C17: ='Profit & Loss'!F17 | D17: ='Profit & Loss'!F46 | E17: ='Profit & Loss'!F48 | G17: ='Profit & Loss'!B23 | H17: ='Profit & Loss'!O23
B18: May | C18: ='Profit & Loss'!G17 | D18: ='Profit & Loss'!G46 | E18: ='Profit & Loss'!G48 | G18: ='Profit & Loss'!B24 | H18: ='Profit & Loss'!O24
B19: Jun | C19: ='Profit & Loss'!H17 | D19: ='Profit & Loss'!H46 | E19: ='Profit & Loss'!H48 | G19: ='Profit & Loss'!B25 | H19: ='Profit & Loss'!O25
B20: Jul | C20: ='Profit & Loss'!I17 | D20: ='Profit & Loss'!I46 | E20: ='Profit & Loss'!I48 | G20: ='Profit & Loss'!B26 | H20: ='Profit & Loss'!O26
B21: Aug | C21: ='Profit & Loss'!J17 | D21: ='Profit & Loss'!J46 | E21: ='Profit & Loss'!J48 | G21: ='Profit & Loss'!B27 | H21: ='Profit & Loss'!O27
B22: Sep | C22: ='Profit & Loss'!K17 | D22: ='Profit & Loss'!K46 | E22: ='Profit & Loss'!K48 | G22: ='Profit & Loss'!B28 | H22: ='Profit & Loss'!O28
B23: Oct | C23: ='Profit & Loss'!L17 | D23: ='Profit & Loss'!L46 | E23: ='Profit & Loss'!L48 | G23: ='Profit & Loss'!B29 | H23: ='Profit & Loss'!O29
B24: Nov | C24: ='Profit & Loss'!M17 | D24: ='Profit & Loss'!M46 | E24: ='Profit & Loss'!M48 | G24: ='Profit & Loss'!B30 | H24: ='Profit & Loss'!O30
B25: Dec | C25: ='Profit & Loss'!N17 | D25: ='Profit & Loss'!N46 | E25: ='Profit & Loss'!N48 | G25: ='Profit & Loss'!B31 | H25: ='Profit & Loss'!O31
G26: ='Profit & Loss'!B32 | H26: ='Profit & Loss'!O32
G27: ='Profit & Loss'!B33 | H27: ='Profit & Loss'!O33
G28: ='Profit & Loss'!B34 | H28: ='Profit & Loss'!O34
G29: ='Profit & Loss'!B35 | H29: ='Profit & Loss'!O35

Sheet Quarterly Tax
B2: Quarterly Estimated Tax
B3: How much to set aside each quarter
B5: Quarter | C5: Months | D5: Net profit | E5: Set aside | F5: Typical US due date | G5: Paid | H5: Status
B6: Q1 | C6: Jan-Mar | D6: =SUM('Profit & Loss'!C48:E48) | E6: =MAX(0,D6)*Setup!$C$7 | F6: Apr 15 | G6: 1200 | H6: =IF(G6>=E6,"Covered",IF(G6>0,"Partly paid","To pay"))
B7: Q2 | C7: Apr-May | D7: =SUM('Profit & Loss'!F48:G48) | E7: =MAX(0,D7)*Setup!$C$7 | F7: Jun 15 | G7: 1450 | H7: =IF(G7>=E7,"Covered",IF(G7>0,"Partly paid","To pay"))
B8: Q3 | C8: Jun-Aug | D8: =SUM('Profit & Loss'!H48:J48) | E8: =MAX(0,D8)*Setup!$C$7 | F8: Sep 15 | G8: 0 | H8: =IF(G8>=E8,"Covered",IF(G8>0,"Partly paid","To pay"))
B9: Q4 | C9: Sep-Dec | D9: =SUM('Profit & Loss'!K48:N48) | E9: =MAX(0,D9)*Setup!$C$7 | F9: Jan 15 (next year) | G9: 0 | H9: =IF(G9>=E9,"Covered",IF(G9>0,"Partly paid","To pay"))
B11: Total | D11: =SUM(D6:D9) | E11: =SUM(E6:E9) | G11: =SUM(G6:G9)
B13: Due dates shown are the usual US federal estimated-tax dates. Confirm yours with your accountant.
