Workbook

Sheet Start Here
B2: Annual Budget Planner 2027
B3: Read me first - 2 minutes
B5: 1. SETUP tab: type your income sources and your budget categories (green cells). Categories feed every other tab.
B6: 2. TRANSACTIONS tab: log each expense - date, category (drop-down), description, amount. The month fills in by itself.
B7: 3. DASHBOARD tab: pick a month in the yellow cell. Totals, budget vs actual and the chart update automatically.
B8: 4. ANNUAL tab: your whole year at a glance, month by month and category by category.
B9: 5. DEBT PAYOFF and SAVINGS GOALS: enter balances and targets, progress bars fill in as you go.
B11: Only type in green-shaded cells. White cells contain formulas - leave them as they are.
B12: Works in Google Sheets (File > Import, or open from Drive) and Microsoft Excel 2016 or newer.
B13: Sample data is included so you can see it working. Clear it from the green cells when you are ready.
B15: This is a personal budgeting tool, not financial advice.

Sheet Setup
B2: Setup
B3: Your income and budget categories
B5: INCOME (monthly)
B6: Source | D6: Amount
B7: Paycheck - Main job | D7: 3200
B8: Paycheck - Partner | D8: 2450
B9: Side hustle | D9: 380
B12: Total income | D12: =SUM(D7:D11)
B14: BUDGET CATEGORIES
B15: Category | C15: Group | D15: Monthly budget
B16: Rent / Mortgage | C16: Bills | D16: 1650
B17: Utilities | C17: Bills | D17: 210
B18: Phone & Internet | C18: Bills | D18: 120
B19: Insurance | C19: Bills | D19: 185
B20: Subscriptions | C20: Bills | D20: 48
B21: Groceries | C21: Living | D21: 620
B22: Dining Out | C22: Living | D22: 180
B23: Transportation | C23: Living | D23: 260
B24: Health | C24: Living | D24: 90
B25: Personal Care | C25: Living | D25: 70
B26: Shopping | C26: Living | D26: 150
B27: Entertainment | C27: Living | D27: 110
... B33: Car Loan | C33: Debt | D33: 285
B46: Total budget | D46: =SUM(D16:D45)

Sheet Transactions
B2: Transactions
B3: Log every expense here
B5: Date | C5: Category | D5: Description | E5: Amount | F5: Month
B6: 46388 | C6: Rent / Mortgage | D6: Rent / Mortgage | E6: 1650 | F6: =IF(B6="","",TEXT(B6,"mmm"))
B7: 46389 | C7: Dining Out | D7: Taco place | E7: 38.71 | F7: =IF(B7="","",TEXT(B7,"mmm"))
B8: 46389 | C8: Transportation | D8: Gas station | E8: 41.07 | F8: =IF(B8="","",TEXT(B8,"mmm"))
B9: 46390 | C9: Groceries | D9: Corner Store | E9: 103.21 | F9: =IF(B9="","",TEXT(B9,"mmm"))
B10: 46390 | C10: Utilities | D10: Electric & water | E10: 194.32 | F10: =IF(B10="","",TEXT(B10,"mmm"))
B11: 46392 | C11: Groceries | D11: Green Grocer | E11: 129.26 | F11: =IF(B11="","",TEXT(B11,"mmm"))
B12: 46392 | C12: Phone & Internet | D12: Phone & Internet | E12: 120 | F12: =IF(B12="","",TEXT(B12,"mmm"))
B13: 46392 | C13: Transportation | D13: Parking | E13: 43.44 | F13: =IF(B13="","",TEXT(B13,"mmm"))
B14: 46393 | C14: Shopping | D14: Clothing store | E14: 63.62 | F14: =IF(B14="","",TEXT(B14,"mmm"))
B15: 46394 | C15: Groceries | D15: Fresh Market | E15: 102.82 | F15: =IF(B15="","",TEXT(B15,"mmm"))
B16: 46394 | C16: Insurance | D16: Insurance | E16: 185 | F16: =IF(B16="","",TEXT(B16,"mmm"))
B17: 46395 | C17: Gifts | D17: Birthday gift | E17: 49.37 | F17: =IF(B17="","",TEXT(B17,"mmm"))
... B185: 46565 | C185: Groceries | D185: Fresh Market | E185: 97.74 | F185: =IF(B185="","",TEXT(B185,"mmm"))
F186: =IF(B186="","",TEXT(B186,"mmm"))
F187: =IF(B187="","",TEXT(B187,"mmm"))
F188: =IF(B188="","",TEXT(B188,"mmm"))
F189: =IF(B189="","",TEXT(B189,"mmm"))
F190: =IF(B190="","",TEXT(B190,"mmm"))
F191: =IF(B191="","",TEXT(B191,"mmm"))
F192: =IF(B192="","",TEXT(B192,"mmm"))
F193: =IF(B193="","",TEXT(B193,"mmm"))
F194: =IF(B194="","",TEXT(B194,"mmm"))
F195: =IF(B195="","",TEXT(B195,"mmm"))
F196: =IF(B196="","",TEXT(B196,"mmm"))
F197: =IF(B197="","",TEXT(B197,"mmm"))
... F1000: =IF(B1000="","",TEXT(B1000,"mmm"))

Sheet Dashboard
B2: Budget Dashboard
B3: Pick a month - everything updates
B5: Month | C5: Jan
C6: Income | D6: Spent | E6: Budgeted | F6: Left
B7: This month | C7: =Setup!D12 | D7: =SUMIFS(Transactions!$E$6:$E$1000,Transactions!$F$6:$F$1000,C5) | E7: =Setup!D46 | F7: =C7-D7
B8: Savings rate | C8: =IFERROR(SUMIFS(Transactions!$E$6:$E$1000,Transactions!$F$6:$F$1000,C5,Transactions!$C$6:$C$1000,"*Fund")+SUMIFS(Transactions!$E$6:$E$1000,Transactions!$F$6:$F$1000,C5,Transactions!$C$6:$C$1000,"Retirement"),0)/C7
B10: Category | C10: Budget | D10: Actual | E10: Difference | F10: % used
B11: =IF(Setup!B16="","",Setup!B16) | C11: =IF(B11="","",Setup!D16) | D11: =IF(B11="","",SUMIFS(Transactions!$E$6:$E$1000,Transactions!$C$6:$C$1000,B11,Transactions!$F$6:$F$1000,$C$5)) | E11: =IF(B11="","",C11-D11) | F11: =IF(OR(B11="",C11=0),"",D11/C11)
B12: =IF(Setup!B17="","",Setup!B17) | C12: =IF(B12="","",Setup!D17) | D12: =IF(B12="","",SUMIFS(Transactions!$E$6:$E$1000,Transactions!$C$6:$C$1000,B12,Transactions!$F$6:$F$1000,$C$5)) | E12: =IF(B12="","",C12-D12) | F12: =IF(OR(B12="",C12=0),"",D12/C12)
B13: =IF(Setup!B18="","",Setup!B18) | C13: =IF(B13="","",Setup!D18) | D13: =IF(B13="","",SUMIFS(Transactions!$E$6:$E$1000,Transactions!$C$6:$C$1000,B13,Transactions!$F$6:$F$1000,$C$5)) | E13: =IF(B13="","",C13-D13) | F13: =IF(OR(B13="",C13=0),"",D13/C13)
B14: =IF(Setup!B19="","",Setup!B19) | C14: =IF(B14="","",Setup!D19) | D14: =IF(B14="","",SUMIFS(Transactions!$E$6:$E$1000,Transactions!$C$6:$C$1000,B14,Transactions!$F$6:$F$1000,$C$5)) | E14: =IF(B14="","",C14-D14) | F14: =IF(OR(B14="",C14=0),"",D14/C14)
B15: =IF(Setup!B20="","",Setup!B20) | C15: =IF(B15="","",Setup!D20) | D15: =IF(B15="","",SUMIFS(Transactions!$E$6:$E$1000,Transactions!$C$6:$C$1000,B15,Transactions!$F$6:$F$1000,$C$5)) | E15: =IF(B15="","",C15-D15) | F15: =IF(OR(B15="",C15=0),"",D15/C15)
B16: =IF(Setup!B21="","",Setup!B21) | C16: =IF(B16="","",Setup!D21) | D16: =IF(B16="","",SUMIFS(Transactions!$E$6:$E$1000,Transactions!$C$6:$C$1000,B16,Transactions!$F$6:$F$1000,$C$5)) | E16: =IF(B16="","",C16-D16) | F16: =IF(OR(B16="",C16=0),"",D16/C16)
B17: =IF(Setup!B22="","",Setup!B22) | C17: =IF(B17="","",Setup!D22) | D17: =IF(B17="","",SUMIFS(Transactions!$E$6:$E$1000,Transactions!$C$6:$C$1000,B17,Transactions!$F$6:$F$1000,$C$5)) | E17: =IF(B17="","",C17-D17) | F17: =IF(OR(B17="",C17=0),"",D17/C17)
B18: =IF(Setup!B23="","",Setup!B23) | C18: =IF(B18="","",Setup!D23) | D18: =IF(B18="","",SUMIFS(Transactions!$E$6:$E$1000,Transactions!$C$6:$C$1000,B18,Transactions!$F$6:$F$1000,$C$5)) | E18: =IF(B18="","",C18-D18) | F18: =IF(OR(B18="",C18=0),"",D18/C18)
B19: =IF(Setup!B24="","",Setup!B24) | C19: =IF(B19="","",Setup!D24) | D19: =IF(B19="","",SUMIFS(Transactions!$E$6:$E$1000,Transactions!$C$6:$C$1000,B19,Transactions!$F$6:$F$1000,$C$5)) | E19: =IF(B19="","",C19-D19) | F19: =IF(OR(B19="",C19=0),"",D19/C19)
B20: =IF(Setup!B25="","",Setup!B25) | C20: =IF(B20="","",Setup!D25) | D20: =IF(B20="","",SUMIFS(Transactions!$E$6:$E$1000,Transactions!$C$6:$C$1000,B20,Transactions!$F$6:$F$1000,$C$5)) | E20: =IF(B20="","",C20-D20) | F20: =IF(OR(B20="",C20=0),"",D20/C20)
B21: =IF(Setup!B26="","",Setup!B26) | C21: =IF(B21="","",Setup!D26) | D21: =IF(B21="","",SUMIFS(Transactions!$E$6:$E$1000,Transactions!$C$6:$C$1000,B21,Transactions!$F$6:$F$1000,$C$5)) | E21: =IF(B21="","",C21-D21) | F21: =IF(OR(B21="",C21=0),"",D21/C21)
B22: =IF(Setup!B27="","",Setup!B27) | C22: =IF(B22="","",Setup!D27) | D22: =IF(B22="","",SUMIFS(Transactions!$E$6:$E$1000,Transactions!$C$6:$C$1000,B22,Transactions!$F$6:$F$1000,$C$5)) | E22: =IF(B22="","",C22-D22) | F22: =IF(OR(B22="",C22=0),"",D22/C22)
... B40: =IF(Setup!B45="","",Setup!B45) | C40: =IF(B40="","",Setup!D45) | D40: =IF(B40="","",SUMIFS(Transactions!$E$6:$E$1000,Transactions!$C$6:$C$1000,B40,Transactions!$F$6:$F$1000,$C$5)) | E40: =IF(B40="","",C40-D40) | F40: =IF(OR(B40="",C40=0),"",D40/C40)

Sheet Annual
B2: Annual Overview
B3: 2027 month by month
B5: Category | C5: Jan | D5: Feb | E5: Mar | F5: Apr | G5: May | H5: Jun | I5: Jul | J5: Aug | K5: Sep | L5: Oct | M5: Nov | N5: Dec | O5: Total
B6: =IF(Setup!B16="","",Setup!B16) | C6: =IF($B6="","",SUMIFS(Transactions!$E$6:$E$1000,Transactions!$C$6:$C$1000,$B6,Transactions!$F$6:$F$1000,C$5)) | D6: =IF($B6="","",SUMIFS(Transactions!$E$6:$E$1000,Transactions!$C$6:$C$1000,$B6,Transactions!$F$6:$F$1000,D$5)) | E6: =IF($B6="","",SUMIFS(Transactions!$E$6:$E$1000,Transactions!$C$6:$C$1000,$B6,Transactions!$F$6:$F$1000,E$5)) | F6: =IF($B6="","",SUMIFS(Transactions!$E$6:$E$1000,Transactions!$C$6:$C$1000,$B6,Transactions!$F$6:$F$1000,F$5)) | G6: =IF($B6="","",SUMIFS(Transactions!$E$6:$E$1000,Transactions!$C$6:$C$1000,$B6,Transactions!$F$6:$F$1000,G$5)) | H6: =IF($B6="","",SUMIFS(Transactions!$E$6:$E$1000,Transactions!$C$6:$C$1000,$B6,Transactions!$F$6:$F$1000,H$5)) | I6: =IF($B6="","",SUMIFS(Transactions!$E$6:$E$1000,Transactions!$C$6:$C$1000,$B6,Transactions!$F$6:$F$1000,I$5)) | J6: =IF($B6="","",SUMIFS(Transactions!$E$6:$E$1000,Transactions!$C$6:$C$1000,$B6,Transactions!$F$6:$F$1000,J$5)) | ... N6: =IF($B6="","",SUMIFS(Transactions!$E$6:$E$1000,Transactions!$C$6:$C$1000,$B6,Transactions!$F$6:$F$1000,N$5)) | O6: =IF(B6="","",SUM(C6:N6))
B7: =IF(Setup!B17="","",Setup!B17) | C7: =IF($B7="","",SUMIFS(Transactions!$E$6:$E$1000,Transactions!$C$6:$C$1000,$B7,Transactions!$F$6:$F$1000,C$5)) | D7: =IF($B7="","",SUMIFS(Transactions!$E$6:$E$1000,Transactions!$C$6:$C$1000,$B7,Transactions!$F$6:$F$1000,D$5)) | E7: =IF($B7="","",SUMIFS(Transactions!$E$6:$E$1000,Transactions!$C$6:$C$1000,$B7,Transactions!$F$6:$F$1000,E$5)) | F7: =IF($B7="","",SUMIFS(Transactions!$E$6:$E$1000,Transactions!$C$6:$C$1000,$B7,Transactions!$F$6:$F$1000,F$5)) | G7: =IF($B7="","",SUMIFS(Transactions!$E$6:$E$1000,Transactions!$C$6:$C$1000,$B7,Transactions!$F$6:$F$1000,G$5)) | H7: =IF($B7="","",SUMIFS(Transactions!$E$6:$E$1000,Transactions!$C$6:$C$1000,$B7,Transactions!$F$6:$F$1000,H$5)) | I7: =IF($B7="","",SUMIFS(Transactions!$E$6:$E$1000,Transactions!$C$6:$C$1000,$B7,Transactions!$F$6:$F$1000,I$5)) | J7: =IF($B7="","",SUMIFS(Transactions!$E$6:$E$1000,Transactions!$C$6:$C$1000,$B7,Transactions!$F$6:$F$1000,J$5)) | ... N7: =IF($B7="","",SUMIFS(Transactions!$E$6:$E$1000,Transactions!$C$6:$C$1000,$B7,Transactions!$F$6:$F$1000,N$5)) | O7: =IF(B7="","",SUM(C7:N7))
B8: =IF(Setup!B18="","",Setup!B18) | C8: =IF($B8="","",SUMIFS(Transactions!$E$6:$E$1000,Transactions!$C$6:$C$1000,$B8,Transactions!$F$6:$F$1000,C$5)) | D8: =IF($B8="","",SUMIFS(Transactions!$E$6:$E$1000,Transactions!$C$6:$C$1000,$B8,Transactions!$F$6:$F$1000,D$5)) | E8: =IF($B8="","",SUMIFS(Transactions!$E$6:$E$1000,Transactions!$C$6:$C$1000,$B8,Transactions!$F$6:$F$1000,E$5)) | F8: =IF($B8="","",SUMIFS(Transactions!$E$6:$E$1000,Transactions!$C$6:$C$1000,$B8,Transactions!$F$6:$F$1000,F$5)) | G8: =IF($B8="","",SUMIFS(Transactions!$E$6:$E$1000,Transactions!$C$6:$C$1000,$B8,Transactions!$F$6:$F$1000,G$5)) | H8: =IF($B8="","",SUMIFS(Transactions!$E$6:$E$1000,Transactions!$C$6:$C$1000,$B8,Transactions!$F$6:$F$1000,H$5)) | I8: =IF($B8="","",SUMIFS(Transactions!$E$6:$E$1000,Transactions!$C$6:$C$1000,$B8,Transactions!$F$6:$F$1000,I$5)) | J8: =IF($B8="","",SUMIFS(Transactions!$E$6:$E$1000,Transactions!$C$6:$C$1000,$B8,Transactions!$F$6:$F$1000,J$5)) | ... N8: =IF($B8="","",SUMIFS(Transactions!$E$6:$E$1000,Transactions!$C$6:$C$1000,$B8,Transactions!$F$6:$F$1000,N$5)) | O8: =IF(B8="","",SUM(C8:N8))
B9: =IF(Setup!B19="","",Setup!B19) | C9: =IF($B9="","",SUMIFS(Transactions!$E$6:$E$1000,Transactions!$C$6:$C$1000,$B9,Transactions!$F$6:$F$1000,C$5)) | D9: =IF($B9="","",SUMIFS(Transactions!$E$6:$E$1000,Transactions!$C$6:$C$1000,$B9,Transactions!$F$6:$F$1000,D$5)) | E9: =IF($B9="","",SUMIFS(Transactions!$E$6:$E$1000,Transactions!$C$6:$C$1000,$B9,Transactions!$F$6:$F$1000,E$5)) | F9: =IF($B9="","",SUMIFS(Transactions!$E$6:$E$1000,Transactions!$C$6:$C$1000,$B9,Transactions!$F$6:$F$1000,F$5)) | G9: =IF($B9="","",SUMIFS(Transactions!$E$6:$E$1000,Transactions!$C$6:$C$1000,$B9,Transactions!$F$6:$F$1000,G$5)) | H9: =IF($B9="","",SUMIFS(Transactions!$E$6:$E$1000,Transactions!$C$6:$C$1000,$B9,Transactions!$F$6:$F$1000,H$5)) | I9: =IF($B9="","",SUMIFS(Transactions!$E$6:$E$1000,Transactions!$C$6:$C$1000,$B9,Transactions!$F$6:$F$1000,I$5)) | J9: =IF($B9="","",SUMIFS(Transactions!$E$6:$E$1000,Transactions!$C$6:$C$1000,$B9,Transactions!$F$6:$F$1000,J$5)) | ... N9: =IF($B9="","",SUMIFS(Transactions!$E$6:$E$1000,Transactions!$C$6:$C$1000,$B9,Transactions!$F$6:$F$1000,N$5)) | O9: =IF(B9="","",SUM(C9:N9))
B10: =IF(Setup!B20="","",Setup!B20) | C10: =IF($B10="","",SUMIFS(Transactions!$E$6:$E$1000,Transactions!$C$6:$C$1000,$B10,Transactions!$F$6:$F$1000,C$5)) | D10: =IF($B10="","",SUMIFS(Transactions!$E$6:$E$1000,Transactions!$C$6:$C$1000,$B10,Transactions!$F$6:$F$1000,D$5)) | E10: =IF($B10="","",SUMIFS(Transactions!$E$6:$E$1000,Transactions!$C$6:$C$1000,$B10,Transactions!$F$6:$F$1000,E$5)) | F10: =IF($B10="","",SUMIFS(Transactions!$E$6:$E$1000,Transactions!$C$6:$C$1000,$B10,Transactions!$F$6:$F$1000,F$5)) | G10: =IF($B10="","",SUMIFS(Transactions!$E$6:$E$1000,Transactions!$C$6:$C$1000,$B10,Transactions!$F$6:$F$1000,G$5)) | H10: =IF($B10="","",SUMIFS(Transactions!$E$6:$E$1000,Transactions!$C$6:$C$1000,$B10,Transactions!$F$6:$F$1000,H$5)) | I10: =IF($B10="","",SUMIFS(Transactions!$E$6:$E$1000,Transactions!$C$6:$C$1000,$B10,Transactions!$F$6:$F$1000,I$5)) | J10: =IF($B10="","",SUMIFS(Transactions!$E$6:$E$1000,Transactions!$C$6:$C$1000,$B10,Transactions!$F$6:$F$1000,J$5)) | ... N10: =IF($B10="","",SUMIFS(Transactions!$E$6:$E$1000,Transactions!$C$6:$C$1000,$B10,Transactions!$F$6:$F$1000,N$5)) | O10: =IF(B10="","",SUM(C10:N10))
B11: =IF(Setup!B21="","",Setup!B21) | C11: =IF($B11="","",SUMIFS(Transactions!$E$6:$E$1000,Transactions!$C$6:$C$1000,$B11,Transactions!$F$6:$F$1000,C$5)) | D11: =IF($B11="","",SUMIFS(Transactions!$E$6:$E$1000,Transactions!$C$6:$C$1000,$B11,Transactions!$F$6:$F$1000,D$5)) | E11: =IF($B11="","",SUMIFS(Transactions!$E$6:$E$1000,Transactions!$C$6:$C$1000,$B11,Transactions!$F$6:$F$1000,E$5)) | F11: =IF($B11="","",SUMIFS(Transactions!$E$6:$E$1000,Transactions!$C$6:$C$1000,$B11,Transactions!$F$6:$F$1000,F$5)) | G11: =IF($B11="","",SUMIFS(Transactions!$E$6:$E$1000,Transactions!$C$6:$C$1000,$B11,Transactions!$F$6:$F$1000,G$5)) | H11: =IF($B11="","",SUMIFS(Transactions!$E$6:$E$1000,Transactions!$C$6:$C$1000,$B11,Transactions!$F$6:$F$1000,H$5)) | I11: =IF($B11="","",SUMIFS(Transactions!$E$6:$E$1000,Transactions!$C$6:$C$1000,$B11,Transactions!$F$6:$F$1000,I$5)) | J11: =IF($B11="","",SUMIFS(Transactions!$E$6:$E$1000,Transactions!$C$6:$C$1000,$B11,Transactions!$F$6:$F$1000,J$5)) | ... N11: =IF($B11="","",SUMIFS(Transactions!$E$6:$E$1000,Transactions!$C$6:$C$1000,$B11,Transactions!$F$6:$F$1000,N$5)) | O11: =IF(B11="","",SUM(C11:N11))
B12: =IF(Setup!B22="","",Setup!B22) | C12: =IF($B12="","",SUMIFS(Transactions!$E$6:$E$1000,Transactions!$C$6:$C$1000,$B12,Transactions!$F$6:$F$1000,C$5)) | D12: =IF($B12="","",SUMIFS(Transactions!$E$6:$E$1000,Transactions!$C$6:$C$1000,$B12,Transactions!$F$6:$F$1000,D$5)) | E12: =IF($B12="","",SUMIFS(Transactions!$E$6:$E$1000,Transactions!$C$6:$C$1000,$B12,Transactions!$F$6:$F$1000,E$5)) | F12: =IF($B12="","",SUMIFS(Transactions!$E$6:$E$1000,Transactions!$C$6:$C$1000,$B12,Transactions!$F$6:$F$1000,F$5)) | G12: =IF($B12="","",SUMIFS(Transactions!$E$6:$E$1000,Transactions!$C$6:$C$1000,$B12,Transactions!$F$6:$F$1000,G$5)) | H12: =IF($B12="","",SUMIFS(Transactions!$E$6:$E$1000,Transactions!$C$6:$C$1000,$B12,Transactions!$F$6:$F$1000,H$5)) | I12: =IF($B12="","",SUMIFS(Transactions!$E$6:$E$1000,Transactions!$C$6:$C$1000,$B12,Transactions!$F$6:$F$1000,I$5)) | J12: =IF($B12="","",SUMIFS(Transactions!$E$6:$E$1000,Transactions!$C$6:$C$1000,$B12,Transactions!$F$6:$F$1000,J$5)) | ... N12: =IF($B12="","",SUMIFS(Transactions!$E$6:$E$1000,Transactions!$C$6:$C$1000,$B12,Transactions!$F$6:$F$1000,N$5)) | O12: =IF(B12="","",SUM(C12:N12))
B13: =IF(Setup!B23="","",Setup!B23) | C13: =IF($B13="","",SUMIFS(Transactions!$E$6:$E$1000,Transactions!$C$6:$C$1000,$B13,Transactions!$F$6:$F$1000,C$5)) | D13: =IF($B13="","",SUMIFS(Transactions!$E$6:$E$1000,Transactions!$C$6:$C$1000,$B13,Transactions!$F$6:$F$1000,D$5)) | E13: =IF($B13="","",SUMIFS(Transactions!$E$6:$E$1000,Transactions!$C$6:$C$1000,$B13,Transactions!$F$6:$F$1000,E$5)) | F13: =IF($B13="","",SUMIFS(Transactions!$E$6:$E$1000,Transactions!$C$6:$C$1000,$B13,Transactions!$F$6:$F$1000,F$5)) | G13: =IF($B13="","",SUMIFS(Transactions!$E$6:$E$1000,Transactions!$C$6:$C$1000,$B13,Transactions!$F$6:$F$1000,G$5)) | H13: =IF($B13="","",SUMIFS(Transactions!$E$6:$E$1000,Transactions!$C$6:$C$1000,$B13,Transactions!$F$6:$F$1000,H$5)) | I13: =IF($B13="","",SUMIFS(Transactions!$E$6:$E$1000,Transactions!$C$6:$C$1000,$B13,Transactions!$F$6:$F$1000,I$5)) | J13: =IF($B13="","",SUMIFS(Transactions!$E$6:$E$1000,Transactions!$C$6:$C$1000,$B13,Transactions!$F$6:$F$1000,J$5)) | ... N13: =IF($B13="","",SUMIFS(Transactions!$E$6:$E$1000,Transactions!$C$6:$C$1000,$B13,Transactions!$F$6:$F$1000,N$5)) | O13: =IF(B13="","",SUM(C13:N13))
B14: =IF(Setup!B24="","",Setup!B24) | C14: =IF($B14="","",SUMIFS(Transactions!$E$6:$E$1000,Transactions!$C$6:$C$1000,$B14,Transactions!$F$6:$F$1000,C$5)) | D14: =IF($B14="","",SUMIFS(Transactions!$E$6:$E$1000,Transactions!$C$6:$C$1000,$B14,Transactions!$F$6:$F$1000,D$5)) | E14: =IF($B14="","",SUMIFS(Transactions!$E$6:$E$1000,Transactions!$C$6:$C$1000,$B14,Transactions!$F$6:$F$1000,E$5)) | F14: =IF($B14="","",SUMIFS(Transactions!$E$6:$E$1000,Transactions!$C$6:$C$1000,$B14,Transactions!$F$6:$F$1000,F$5)) | G14: =IF($B14="","",SUMIFS(Transactions!$E$6:$E$1000,Transactions!$C$6:$C$1000,$B14,Transactions!$F$6:$F$1000,G$5)) | H14: =IF($B14="","",SUMIFS(Transactions!$E$6:$E$1000,Transactions!$C$6:$C$1000,$B14,Transactions!$F$6:$F$1000,H$5)) | I14: =IF($B14="","",SUMIFS(Transactions!$E$6:$E$1000,Transactions!$C$6:$C$1000,$B14,Transactions!$F$6:$F$1000,I$5)) | J14: =IF($B14="","",SUMIFS(Transactions!$E$6:$E$1000,Transactions!$C$6:$C$1000,$B14,Transactions!$F$6:$F$1000,J$5)) | ... N14: =IF($B14="","",SUMIFS(Transactions!$E$6:$E$1000,Transactions!$C$6:$C$1000,$B14,Transactions!$F$6:$F$1000,N$5)) | O14: =IF(B14="","",SUM(C14:N14))
B15: =IF(Setup!B25="","",Setup!B25) | C15: =IF($B15="","",SUMIFS(Transactions!$E$6:$E$1000,Transactions!$C$6:$C$1000,$B15,Transactions!$F$6:$F$1000,C$5)) | D15: =IF($B15="","",SUMIFS(Transactions!$E$6:$E$1000,Transactions!$C$6:$C$1000,$B15,Transactions!$F$6:$F$1000,D$5)) | E15: =IF($B15="","",SUMIFS(Transactions!$E$6:$E$1000,Transactions!$C$6:$C$1000,$B15,Transactions!$F$6:$F$1000,E$5)) | F15: =IF($B15="","",SUMIFS(Transactions!$E$6:$E$1000,Transactions!$C$6:$C$1000,$B15,Transactions!$F$6:$F$1000,F$5)) | G15: =IF($B15="","",SUMIFS(Transactions!$E$6:$E$1000,Transactions!$C$6:$C$1000,$B15,Transactions!$F$6:$F$1000,G$5)) | H15: =IF($B15="","",SUMIFS(Transactions!$E$6:$E$1000,Transactions!$C$6:$C$1000,$B15,Transactions!$F$6:$F$1000,H$5)) | I15: =IF($B15="","",SUMIFS(Transactions!$E$6:$E$1000,Transactions!$C$6:$C$1000,$B15,Transactions!$F$6:$F$1000,I$5)) | J15: =IF($B15="","",SUMIFS(Transactions!$E$6:$E$1000,Transactions!$C$6:$C$1000,$B15,Transactions!$F$6:$F$1000,J$5)) | ... N15: =IF($B15="","",SUMIFS(Transactions!$E$6:$E$1000,Transactions!$C$6:$C$1000,$B15,Transactions!$F$6:$F$1000,N$5)) | O15: =IF(B15="","",SUM(C15:N15))
B16: =IF(Setup!B26="","",Setup!B26) | C16: =IF($B16="","",SUMIFS(Transactions!$E$6:$E$1000,Transactions!$C$6:$C$1000,$B16,Transactions!$F$6:$F$1000,C$5)) | D16: =IF($B16="","",SUMIFS(Transactions!$E$6:$E$1000,Transactions!$C$6:$C$1000,$B16,Transactions!$F$6:$F$1000,D$5)) | E16: =IF($B16="","",SUMIFS(Transactions!$E$6:$E$1000,Transactions!$C$6:$C$1000,$B16,Transactions!$F$6:$F$1000,E$5)) | F16: =IF($B16="","",SUMIFS(Transactions!$E$6:$E$1000,Transactions!$C$6:$C$1000,$B16,Transactions!$F$6:$F$1000,F$5)) | G16: =IF($B16="","",SUMIFS(Transactions!$E$6:$E$1000,Transactions!$C$6:$C$1000,$B16,Transactions!$F$6:$F$1000,G$5)) | H16: =IF($B16="","",SUMIFS(Transactions!$E$6:$E$1000,Transactions!$C$6:$C$1000,$B16,Transactions!$F$6:$F$1000,H$5)) | I16: =IF($B16="","",SUMIFS(Transactions!$E$6:$E$1000,Transactions!$C$6:$C$1000,$B16,Transactions!$F$6:$F$1000,I$5)) | J16: =IF($B16="","",SUMIFS(Transactions!$E$6:$E$1000,Transactions!$C$6:$C$1000,$B16,Transactions!$F$6:$F$1000,J$5)) | ... N16: =IF($B16="","",SUMIFS(Transactions!$E$6:$E$1000,Transactions!$C$6:$C$1000,$B16,Transactions!$F$6:$F$1000,N$5)) | O16: =IF(B16="","",SUM(C16:N16))
B17: =IF(Setup!B27="","",Setup!B27) | C17: =IF($B17="","",SUMIFS(Transactions!$E$6:$E$1000,Transactions!$C$6:$C$1000,$B17,Transactions!$F$6:$F$1000,C$5)) | D17: =IF($B17="","",SUMIFS(Transactions!$E$6:$E$1000,Transactions!$C$6:$C$1000,$B17,Transactions!$F$6:$F$1000,D$5)) | E17: =IF($B17="","",SUMIFS(Transactions!$E$6:$E$1000,Transactions!$C$6:$C$1000,$B17,Transactions!$F$6:$F$1000,E$5)) | F17: =IF($B17="","",SUMIFS(Transactions!$E$6:$E$1000,Transactions!$C$6:$C$1000,$B17,Transactions!$F$6:$F$1000,F$5)) | G17: =IF($B17="","",SUMIFS(Transactions!$E$6:$E$1000,Transactions!$C$6:$C$1000,$B17,Transactions!$F$6:$F$1000,G$5)) | H17: =IF($B17="","",SUMIFS(Transactions!$E$6:$E$1000,Transactions!$C$6:$C$1000,$B17,Transactions!$F$6:$F$1000,H$5)) | I17: =IF($B17="","",SUMIFS(Transactions!$E$6:$E$1000,Transactions!$C$6:$C$1000,$B17,Transactions!$F$6:$F$1000,I$5)) | J17: =IF($B17="","",SUMIFS(Transactions!$E$6:$E$1000,Transactions!$C$6:$C$1000,$B17,Transactions!$F$6:$F$1000,J$5)) | ... N17: =IF($B17="","",SUMIFS(Transactions!$E$6:$E$1000,Transactions!$C$6:$C$1000,$B17,Transactions!$F$6:$F$1000,N$5)) | O17: =IF(B17="","",SUM(C17:N17))
... B35: =IF(Setup!B45="","",Setup!B45) | C35: =IF($B35="","",SUMIFS(Transactions!$E$6:$E$1000,Transactions!$C$6:$C$1000,$B35,Transactions!$F$6:$F$1000,C$5)) | D35: =IF($B35="","",SUMIFS(Transactions!$E$6:$E$1000,Transactions!$C$6:$C$1000,$B35,Transactions!$F$6:$F$1000,D$5)) | E35: =IF($B35="","",SUMIFS(Transactions!$E$6:$E$1000,Transactions!$C$6:$C$1000,$B35,Transactions!$F$6:$F$1000,E$5)) | F35: =IF($B35="","",SUMIFS(Transactions!$E$6:$E$1000,Transactions!$C$6:$C$1000,$B35,Transactions!$F$6:$F$1000,F$5)) | G35: =IF($B35="","",SUMIFS(Transactions!$E$6:$E$1000,Transactions!$C$6:$C$1000,$B35,Transactions!$F$6:$F$1000,G$5)) | H35: =IF($B35="","",SUMIFS(Transactions!$E$6:$E$1000,Transactions!$C$6:$C$1000,$B35,Transactions!$F$6:$F$1000,H$5)) | I35: =IF($B35="","",SUMIFS(Transactions!$E$6:$E$1000,Transactions!$C$6:$C$1000,$B35,Transactions!$F$6:$F$1000,I$5)) | J35: =IF($B35="","",SUMIFS(Transactions!$E$6:$E$1000,Transactions!$C$6:$C$1000,$B35,Transactions!$F$6:$F$1000,J$5)) | ... N35: =IF($B35="","",SUMIFS(Transactions!$E$6:$E$1000,Transactions!$C$6:$C$1000,$B35,Transactions!$F$6:$F$1000,N$5)) | O35: =IF(B35="","",SUM(C35:N35))
B36: Total spent | C36: =SUM(C6:C35) | D36: =SUM(D6:D35) | E36: =SUM(E6:E35) | F36: =SUM(F6:F35) | G36: =SUM(G6:G35) | H36: =SUM(H6:H35) | I36: =SUM(I6:I35) | J36: =SUM(J6:J35) | ... O36: =SUM(O6:O35)
B37: Income | C37: =Setup!$D$12 | D37: =Setup!$D$12 | E37: =Setup!$D$12 | F37: =Setup!$D$12 | G37: =Setup!$D$12 | H37: =Setup!$D$12 | I37: =Setup!$D$12 | J37: =Setup!$D$12 | ... N37: =Setup!$D$12 | O37: =Setup!$D$12*12
B38: Left over | C38: =C37-C36 | D38: =D37-D36 | E38: =E37-E36 | F38: =F37-F36 | G38: =G37-G36 | H38: =H37-H36 | I38: =I37-I36 | J38: =J37-J36 | ... O38: =O37-O36

Sheet Debt Payoff
B2: Debt Payoff Tracker
B3: Snowball: smallest balance first
B5: Debt | C5: Starting balance | D5: APR | E5: Min payment | F5: Paid so far | G5: Remaining | H5: Progress
B6: Credit Card | C6: 4200 | D6: 0.229 | E6: 120 | F6: 1800 | G6: =IF(C6="","",C6-F6) | H6: =IF(C6="","",F6/C6)
B7: Car Loan | C7: 11400 | D7: 0.069 | E7: 285 | F7: 1710 | G7: =IF(C7="","",C7-F7) | H7: =IF(C7="","",F7/C7)
B8: Student Loan | C8: 8600 | D8: 0.045 | E8: 110 | F8: 660 | G8: =IF(C8="","",C8-F8) | H8: =IF(C8="","",F8/C8)
G9: =IF(C9="","",C9-F9) | H9: =IF(C9="","",F9/C9)
G10: =IF(C10="","",C10-F10) | H10: =IF(C10="","",F10/C10)
G11: =IF(C11="","",C11-F11) | H11: =IF(C11="","",F11/C11)
G12: =IF(C12="","",C12-F12) | H12: =IF(C12="","",F12/C12)
G13: =IF(C13="","",C13-F13) | H13: =IF(C13="","",F13/C13)
B15: Total | C15: =SUM(C6:C13) | F15: =SUM(F6:F13) | G15: =SUM(G6:G13) | H15: =IFERROR(F15/C15,0)

Sheet Savings Goals
B2: Savings Goals
B3: Watch every goal fill up
B5: Goal | C5: Target | D5: Saved | E5: Still needed | F5: Progress | G5: Target date
B6: Emergency Fund | C6: 10000 | D6: 6400 | E6: =IF(C6="","",MAX(0,C6-D6)) | F6: =IF(C6="","",MIN(1,D6/C6)) | G6: Dec 2027
B7: Vacation | C7: 3000 | D7: 1200 | E7: =IF(C7="","",MAX(0,C7-D7)) | F7: =IF(C7="","",MIN(1,D7/C7)) | G7: Jul 2027
B8: New Laptop | C8: 1500 | D8: 950 | E8: =IF(C8="","",MAX(0,C8-D8)) | F8: =IF(C8="","",MIN(1,D8/C8)) | G8: Sep 2027
B9: Holiday Gifts | C9: 800 | D9: 240 | E9: =IF(C9="","",MAX(0,C9-D9)) | F9: =IF(C9="","",MIN(1,D9/C9)) | G9: Nov 2027
E10: =IF(C10="","",MAX(0,C10-D10)) | F10: =IF(C10="","",MIN(1,D10/C10))
E11: =IF(C11="","",MAX(0,C11-D11)) | F11: =IF(C11="","",MIN(1,D11/C11))
E12: =IF(C12="","",MAX(0,C12-D12)) | F12: =IF(C12="","",MIN(1,D12/C12))
E13: =IF(C13="","",MAX(0,C13-D13)) | F13: =IF(C13="","",MIN(1,D13/C13))
