Workbook
Name IncomeCats: 'Setup'!$B$12:$B$21
Name ExpenseCats: 'Setup'!$E$12:$E$31
Name PlanMonth: 'Setup'!$C$8
Name Cur: 'Setup'!$C$7

Sheet Start Here
B2: Life Planner
B3: Budget • Tasks • Habits • Goals • Meals • Cleaning — Google Sheets & Excel
B6: 1. Setup | C6: Type your name, currency symbol, the month you are planning and your own budget categories. Two minutes, once.
B7: 2. Money Log | C7: The only place you type money. One row per income or expense. Budget, Annual, Savings and Dashboard update themselves.
B8: 3. Budget | C8: Type your planned amount per category. Actual, difference and "safe to spend per day" are calculated for the month chosen in Setup.
B9: 4. Annual | C9: All 12 months side by side, built from the Money Log. Nothing to type.
B10: 5. Savings & Debt | C10: Up to 12 savings goals and 12 debts with live progress bars.
B11: 6. Tasks | C11: 100 tasks with category, due date, priority and status. Open tasks appear on the Dashboard, soonest first.
B12: 7. Habits | C12: 20 habits x 31 days. Type x on the days you did it; streak, total and month score are automatic.
B13: 8. Cleaning | C13: Daily to yearly chores. Type the date you last did it; the next due date and status are calculated.
B14: 9. Goals | C14: 10 goals with why, reward, five dated steps and a progress bar.
B15: 10. Week Plan | C15: Plan your week by the hour, from 6:00 to 22:00.
B16: 11. Meals | C16: Plan breakfast, lunch, dinner and snacks for the week, with a grocery list by aisle.
B17: 12. Calendar | C17: Choose a month: every day shows how many open tasks are due.
... B22: Oakfold | C22: Personal use. Not financial advice.

Sheet Dashboard
B2: Dashboard
B3: =IF('Setup'!C6="","Your month at a glance","Hi "&'Setup'!C6&" — your month at a glance")
B5: =PlanMonth
B6: Income | E6: Expenses | H6: Balance
B7: =Cur&TEXT('Budget'!D42,"#,##0.00") | E7: =Cur&TEXT('Budget'!D43,"#,##0.00") | H7: =IF('Budget'!D44<0,"-",)&Cur&TEXT(ABS('Budget'!D44),"#,##0.00")
B9: Safe to spend / day | C9: =IF('Budget'!D47="","",Cur&TEXT('Budget'!D47,"#,##0.00")) | E9: Next tasks | F9: Due | H9: Habits this month | I9: Score
B10: Total saved | C10: =Cur&TEXT('Savings & Debt'!C36,"#,##0.00") | E10: =IFERROR(INDEX('Tasks'!$B$7:$B$106,MATCH(SMALL('Tasks'!$I$7:$I$106,1),'Tasks'!$I$7:$I$106,0)),"") | F10: =IFERROR(INT(SMALL('Tasks'!$I$7:$I$106,1)),"") | H10: =IF('Habits'!B7="","",'Habits'!B7) | I10: =IF('Habits'!B7="","",'Habits'!AI7)
B11: Debt remaining | C11: =Cur&TEXT('Savings & Debt'!C37,"#,##0.00") | E11: =IFERROR(INDEX('Tasks'!$B$7:$B$106,MATCH(SMALL('Tasks'!$I$7:$I$106,2),'Tasks'!$I$7:$I$106,0)),"") | F11: =IFERROR(INT(SMALL('Tasks'!$I$7:$I$106,2)),"") | H11: =IF('Habits'!B8="","",'Habits'!B8) | I11: =IF('Habits'!B8="","",'Habits'!AI8)
E12: =IFERROR(INDEX('Tasks'!$B$7:$B$106,MATCH(SMALL('Tasks'!$I$7:$I$106,3),'Tasks'!$I$7:$I$106,0)),"") | F12: =IFERROR(INT(SMALL('Tasks'!$I$7:$I$106,3)),"") | H12: =IF('Habits'!B9="","",'Habits'!B9) | I12: =IF('Habits'!B9="","",'Habits'!AI9)
B13: Top spending | C13: Actual | E13: =IFERROR(INDEX('Tasks'!$B$7:$B$106,MATCH(SMALL('Tasks'!$I$7:$I$106,4),'Tasks'!$I$7:$I$106,0)),"") | F13: =IFERROR(INT(SMALL('Tasks'!$I$7:$I$106,4)),"") | H13: =IF('Habits'!B10="","",'Habits'!B10) | I13: =IF('Habits'!B10="","",'Habits'!AI10)
B14: =IFERROR(INDEX('Budget'!$B$21:$B$40,MATCH(LARGE('Budget'!$H$21:$H$40,1),'Budget'!$H$21:$H$40,0)),"") | C14: =IFERROR(INDEX('Budget'!$D$21:$D$40,MATCH(LARGE('Budget'!$H$21:$H$40,1),'Budget'!$H$21:$H$40,0)),"") | E14: =IFERROR(INDEX('Tasks'!$B$7:$B$106,MATCH(SMALL('Tasks'!$I$7:$I$106,5),'Tasks'!$I$7:$I$106,0)),"") | F14: =IFERROR(INT(SMALL('Tasks'!$I$7:$I$106,5)),"") | H14: =IF('Habits'!B11="","",'Habits'!B11) | I14: =IF('Habits'!B11="","",'Habits'!AI11)
B15: =IFERROR(INDEX('Budget'!$B$21:$B$40,MATCH(LARGE('Budget'!$H$21:$H$40,2),'Budget'!$H$21:$H$40,0)),"") | C15: =IFERROR(INDEX('Budget'!$D$21:$D$40,MATCH(LARGE('Budget'!$H$21:$H$40,2),'Budget'!$H$21:$H$40,0)),"") | E15: =IFERROR(INDEX('Tasks'!$B$7:$B$106,MATCH(SMALL('Tasks'!$I$7:$I$106,6),'Tasks'!$I$7:$I$106,0)),"") | F15: =IFERROR(INT(SMALL('Tasks'!$I$7:$I$106,6)),"") | H15: =IF('Habits'!B12="","",'Habits'!B12) | I15: =IF('Habits'!B12="","",'Habits'!AI12)
B16: =IFERROR(INDEX('Budget'!$B$21:$B$40,MATCH(LARGE('Budget'!$H$21:$H$40,3),'Budget'!$H$21:$H$40,0)),"") | C16: =IFERROR(INDEX('Budget'!$D$21:$D$40,MATCH(LARGE('Budget'!$H$21:$H$40,3),'Budget'!$H$21:$H$40,0)),"") | E16: =IFERROR(INDEX('Tasks'!$B$7:$B$106,MATCH(SMALL('Tasks'!$I$7:$I$106,7),'Tasks'!$I$7:$I$106,0)),"") | F16: =IFERROR(INT(SMALL('Tasks'!$I$7:$I$106,7)),"") | H16: =IF('Habits'!B13="","",'Habits'!B13) | I16: =IF('Habits'!B13="","",'Habits'!AI13)
B17: =IFERROR(INDEX('Budget'!$B$21:$B$40,MATCH(LARGE('Budget'!$H$21:$H$40,4),'Budget'!$H$21:$H$40,0)),"") | C17: =IFERROR(INDEX('Budget'!$D$21:$D$40,MATCH(LARGE('Budget'!$H$21:$H$40,4),'Budget'!$H$21:$H$40,0)),"") | E17: =IFERROR(INDEX('Tasks'!$B$7:$B$106,MATCH(SMALL('Tasks'!$I$7:$I$106,8),'Tasks'!$I$7:$I$106,0)),"") | F17: =IFERROR(INT(SMALL('Tasks'!$I$7:$I$106,8)),"") | H17: =IF('Habits'!B14="","",'Habits'!B14) | I17: =IF('Habits'!B14="","",'Habits'!AI14)
B18: =IFERROR(INDEX('Budget'!$B$21:$B$40,MATCH(LARGE('Budget'!$H$21:$H$40,5),'Budget'!$H$21:$H$40,0)),"") | C18: =IFERROR(INDEX('Budget'!$D$21:$D$40,MATCH(LARGE('Budget'!$H$21:$H$40,5),'Budget'!$H$21:$H$40,0)),"")
B20: Meals today | E20: Cleaning due | F20: Status | H20: Savings goals | I20: Progress
B21: Breakfast | C21: =INDEX('Meals'!$C$7:$I$7,WEEKDAY(TODAY(),2)) | E21: {=IFERROR(INDEX('Cleaning'!$B$7:$B$46,SMALL(IF('Cleaning'!$G$7:$G$46<>"Upcoming",IF('Cleaning'!$G$7:$G$46<>"",ROW('Cleaning'!$G$7:$G$46)-6)),1)),"")} | F21: {=IFERROR(INDEX('Cleaning'!$G$7:$G$46,SMALL(IF('Cleaning'!$G$7:$G$46<>"Upcoming",IF('Cleaning'!$G$7:$G$46<>"",ROW('Cleaning'!$G$7:$G$46)-6)),1)),"")} | H21: =IF('Savings & Debt'!B7="","",'Savings & Debt'!B7) | I21: =IF('Savings & Debt'!B7="","",'Savings & Debt'!F7)
B22: Lunch | C22: =INDEX('Meals'!$C$8:$I$8,WEEKDAY(TODAY(),2)) | E22: {=IFERROR(INDEX('Cleaning'!$B$7:$B$46,SMALL(IF('Cleaning'!$G$7:$G$46<>"Upcoming",IF('Cleaning'!$G$7:$G$46<>"",ROW('Cleaning'!$G$7:$G$46)-6)),2)),"")} | F22: {=IFERROR(INDEX('Cleaning'!$G$7:$G$46,SMALL(IF('Cleaning'!$G$7:$G$46<>"Upcoming",IF('Cleaning'!$G$7:$G$46<>"",ROW('Cleaning'!$G$7:$G$46)-6)),2)),"")} | H22: =IF('Savings & Debt'!B8="","",'Savings & Debt'!B8) | I22: =IF('Savings & Debt'!B8="","",'Savings & Debt'!F8)
B23: Dinner | C23: =INDEX('Meals'!$C$9:$I$9,WEEKDAY(TODAY(),2)) | E23: {=IFERROR(INDEX('Cleaning'!$B$7:$B$46,SMALL(IF('Cleaning'!$G$7:$G$46<>"Upcoming",IF('Cleaning'!$G$7:$G$46<>"",ROW('Cleaning'!$G$7:$G$46)-6)),3)),"")} | F23: {=IFERROR(INDEX('Cleaning'!$G$7:$G$46,SMALL(IF('Cleaning'!$G$7:$G$46<>"Upcoming",IF('Cleaning'!$G$7:$G$46<>"",ROW('Cleaning'!$G$7:$G$46)-6)),3)),"")} | H23: =IF('Savings & Debt'!B9="","",'Savings & Debt'!B9) | I23: =IF('Savings & Debt'!B9="","",'Savings & Debt'!F9)
B24: Snacks | C24: =INDEX('Meals'!$C$10:$I$10,WEEKDAY(TODAY(),2)) | E24: {=IFERROR(INDEX('Cleaning'!$B$7:$B$46,SMALL(IF('Cleaning'!$G$7:$G$46<>"Upcoming",IF('Cleaning'!$G$7:$G$46<>"",ROW('Cleaning'!$G$7:$G$46)-6)),4)),"")} | F24: {=IFERROR(INDEX('Cleaning'!$G$7:$G$46,SMALL(IF('Cleaning'!$G$7:$G$46<>"Upcoming",IF('Cleaning'!$G$7:$G$46<>"",ROW('Cleaning'!$G$7:$G$46)-6)),4)),"")} | H24: =IF('Savings & Debt'!B10="","",'Savings & Debt'!B10) | I24: =IF('Savings & Debt'!B10="","",'Savings & Debt'!F10)
E25: {=IFERROR(INDEX('Cleaning'!$B$7:$B$46,SMALL(IF('Cleaning'!$G$7:$G$46<>"Upcoming",IF('Cleaning'!$G$7:$G$46<>"",ROW('Cleaning'!$G$7:$G$46)-6)),5)),"")} | F25: {=IFERROR(INDEX('Cleaning'!$G$7:$G$46,SMALL(IF('Cleaning'!$G$7:$G$46<>"Upcoming",IF('Cleaning'!$G$7:$G$46<>"",ROW('Cleaning'!$G$7:$G$46)-6)),5)),"")} | H25: =IF('Savings & Debt'!B11="","",'Savings & Debt'!B11) | I25: =IF('Savings & Debt'!B11="","",'Savings & Debt'!F11)
E26: {=IFERROR(INDEX('Cleaning'!$B$7:$B$46,SMALL(IF('Cleaning'!$G$7:$G$46<>"Upcoming",IF('Cleaning'!$G$7:$G$46<>"",ROW('Cleaning'!$G$7:$G$46)-6)),6)),"")} | F26: {=IFERROR(INDEX('Cleaning'!$G$7:$G$46,SMALL(IF('Cleaning'!$G$7:$G$46<>"Upcoming",IF('Cleaning'!$G$7:$G$46<>"",ROW('Cleaning'!$G$7:$G$46)-6)),6)),"")} | H26: =IF('Savings & Debt'!B12="","",'Savings & Debt'!B12) | I26: =IF('Savings & Debt'!B12="","",'Savings & Debt'!F12)

Sheet Setup
B2: Setup
B3: Fill the white cells once. Everything else follows.
B6: Your name | C6: Alex
B7: Currency symbol | C7: $
B8: Planning month (first day) | C8: 46296
B9: Year | C9: =YEAR(C8)
B11: Income categories | E11: Expense categories
B12: Salary | E12: Rent / Mortgage
B13: Side income | E13: Utilities
B14: Gifts | E14: Groceries
B15: Refunds | E15: Transport
B16: Other income | E16: Insurance
E17: Phone & Internet
E18: Subscriptions
E19: Eating out
E20: Health
E21: Personal care
E22: Clothing
E23: Kids
E24: Pets
E25: Gifts & Events
E26: Entertainment
E27: Savings transfer
E28: Debt payment
E29: Other
B34: Tip: rename any category; every tab picks up the new name.

Sheet Money Log
B2: Money Log
B3: One row per transaction. Choose Income or Expense, then a category.
B6: Date | C6: Type | D6: Category | E6: Amount | F6: Note | G6: Month
B7: 46235 | C7: Expense | D7: Rent / Mortgage | E7: 1150 | F7: Rent | G7: =IF(B7="","",DATE(YEAR(B7),MONTH(B7),1))
B8: 46235 | C8: Income | D8: Salary | E8: 3250 | F8: Payday | G8: =IF(B8="","",DATE(YEAR(B8),MONTH(B8),1))
B9: 46237 | C9: Expense | D9: Groceries | E9: 127 | F9: Weekly shop | G9: =IF(B9="","",DATE(YEAR(B9),MONTH(B9),1))
B10: 46238 | C10: Expense | D10: Health | E10: 24 | G10: =IF(B10="","",DATE(YEAR(B10),MONTH(B10),1))
B11: 46238 | C11: Expense | D11: Transport | E11: 48 | G11: =IF(B11="","",DATE(YEAR(B11),MONTH(B11),1))
B12: 46239 | C12: Expense | D12: Utilities | E12: 96 | G12: =IF(B12="","",DATE(YEAR(B12),MONTH(B12),1))
B13: 46240 | C13: Expense | D13: Phone & Internet | E13: 65 | G13: =IF(B13="","",DATE(YEAR(B13),MONTH(B13),1))
B14: 46241 | C14: Expense | D14: Pets | E14: 58 | G14: =IF(B14="","",DATE(YEAR(B14),MONTH(B14),1))
B15: 46242 | C15: Expense | D15: Eating out | E15: 46 | G15: =IF(B15="","",DATE(YEAR(B15),MONTH(B15),1))
B16: 46243 | C16: Expense | D16: Insurance | E16: 142 | G16: =IF(B16="","",DATE(YEAR(B16),MONTH(B16),1))
B17: 46244 | C17: Expense | D17: Groceries | E17: 84 | F17: Weekly shop | G17: =IF(B17="","",DATE(YEAR(B17),MONTH(B17),1))
B18: 46245 | C18: Expense | D18: Entertainment | E18: 29 | G18: =IF(B18="","",DATE(YEAR(B18),MONTH(B18),1))
B19: 46245 | C19: Expense | D19: Transport | E19: 35 | G19: =IF(B19="","",DATE(YEAR(B19),MONTH(B19),1))
B20: 46246 | C20: Expense | D20: Subscriptions | E20: 38 | G20: =IF(B20="","",DATE(YEAR(B20),MONTH(B20),1))
B21: 46249 | C21: Income | D21: Side income | E21: 340 | G21: =IF(B21="","",DATE(YEAR(B21),MONTH(B21),1))
B22: 46251 | C22: Expense | D22: Groceries | E22: 84 | F22: Weekly shop | G22: =IF(B22="","",DATE(YEAR(B22),MONTH(B22),1))
B23: 46252 | C23: Expense | D23: Transport | E23: 42 | G23: =IF(B23="","",DATE(YEAR(B23),MONTH(B23),1))
B24: 46254 | C24: Expense | D24: Savings transfer | E24: 300 | F24: Emergency fund | G24: =IF(B24="","",DATE(YEAR(B24),MONTH(B24),1))
B25: 46255 | C25: Expense | D25: Debt payment | E25: 250 | F25: Card payment | G25: =IF(B25="","",DATE(YEAR(B25),MONTH(B25),1))
B26: 46258 | C26: Expense | D26: Groceries | E26: 84 | F26: Weekly shop | G26: =IF(B26="","",DATE(YEAR(B26),MONTH(B26),1))
B27: 46259 | C27: Expense | D27: Transport | E27: 48 | G27: =IF(B27="","",DATE(YEAR(B27),MONTH(B27),1))
B28: 46266 | C28: Expense | D28: Rent / Mortgage | E28: 1150 | F28: Rent | G28: =IF(B28="","",DATE(YEAR(B28),MONTH(B28),1))
B29: 46266 | C29: Income | D29: Salary | E29: 3250 | F29: Payday | G29: =IF(B29="","",DATE(YEAR(B29),MONTH(B29),1))
B30: 46268 | C30: Expense | D30: Groceries | E30: 84 | F30: Weekly shop | G30: =IF(B30="","",DATE(YEAR(B30),MONTH(B30),1))
B31: 46269 | C31: Expense | D31: Health | E31: 24 | G31: =IF(B31="","",DATE(YEAR(B31),MONTH(B31),1))
B32: 46269 | C32: Expense | D32: Transport | E32: 42 | G32: =IF(B32="","",DATE(YEAR(B32),MONTH(B32),1))
B33: 46270 | C33: Expense | D33: Utilities | E33: 96 | G33: =IF(B33="","",DATE(YEAR(B33),MONTH(B33),1))
B34: 46271 | C34: Expense | D34: Phone & Internet | E34: 65 | G34: =IF(B34="","",DATE(YEAR(B34),MONTH(B34),1))
B35: 46272 | C35: Expense | D35: Pets | E35: 58 | G35: =IF(B35="","",DATE(YEAR(B35),MONTH(B35),1))
B36: 46273 | C36: Expense | D36: Eating out | E36: 46 | G36: =IF(B36="","",DATE(YEAR(B36),MONTH(B36),1))
B37: 46274 | C37: Expense | D37: Insurance | E37: 142 | G37: =IF(B37="","",DATE(YEAR(B37),MONTH(B37),1))
B38: 46275 | C38: Expense | D38: Groceries | E38: 127 | F38: Weekly shop | G38: =IF(B38="","",DATE(YEAR(B38),MONTH(B38),1))
B39: 46276 | C39: Expense | D39: Entertainment | E39: 29 | G39: =IF(B39="","",DATE(YEAR(B39),MONTH(B39),1))
B40: 46276 | C40: Expense | D40: Transport | E40: 35 | G40: =IF(B40="","",DATE(YEAR(B40),MONTH(B40),1))
B41: 46277 | C41: Expense | D41: Subscriptions | E41: 38 | G41: =IF(B41="","",DATE(YEAR(B41),MONTH(B41),1))
B42: 46280 | C42: Income | D42: Side income | E42: 280 | G42: =IF(B42="","",DATE(YEAR(B42),MONTH(B42),1))
B43: 46282 | C43: Expense | D43: Groceries | E43: 96 | F43: Weekly shop | G43: =IF(B43="","",DATE(YEAR(B43),MONTH(B43),1))
B44: 46283 | C44: Expense | D44: Transport | E44: 35 | G44: =IF(B44="","",DATE(YEAR(B44),MONTH(B44),1))
B45: 46285 | C45: Expense | D45: Savings transfer | E45: 300 | F45: Emergency fund | G45: =IF(B45="","",DATE(YEAR(B45),MONTH(B45),1))
B46: 46286 | C46: Expense | D46: Debt payment | E46: 250 | F46: Card payment | G46: =IF(B46="","",DATE(YEAR(B46),MONTH(B46),1))
B47: 46289 | C47: Expense | D47: Groceries | E47: 127 | F47: Weekly shop | G47: =IF(B47="","",DATE(YEAR(B47),MONTH(B47),1))
B48: 46290 | C48: Expense | D48: Transport | E48: 35 | G48: =IF(B48="","",DATE(YEAR(B48),MONTH(B48),1))
B49: 46296 | C49: Expense | D49: Rent / Mortgage | E49: 1150 | F49: Rent | G49: =IF(B49="","",DATE(YEAR(B49),MONTH(B49),1))
B50: 46296 | C50: Income | D50: Salary | E50: 3250 | F50: Payday | G50: =IF(B50="","",DATE(YEAR(B50),MONTH(B50),1))
B51: 46298 | C51: Expense | D51: Groceries | E51: 96 | F51: Weekly shop | G51: =IF(B51="","",DATE(YEAR(B51),MONTH(B51),1))
B52: 46299 | C52: Expense | D52: Health | E52: 24 | G52: =IF(B52="","",DATE(YEAR(B52),MONTH(B52),1))
B53: 46299 | C53: Expense | D53: Transport | E53: 48 | G53: =IF(B53="","",DATE(YEAR(B53),MONTH(B53),1))
B54: 46300 | C54: Expense | D54: Utilities | E54: 96 | G54: =IF(B54="","",DATE(YEAR(B54),MONTH(B54),1))
B55: 46301 | C55: Expense | D55: Phone & Internet | E55: 65 | G55: =IF(B55="","",DATE(YEAR(B55),MONTH(B55),1))
B56: 46302 | C56: Expense | D56: Pets | E56: 58 | G56: =IF(B56="","",DATE(YEAR(B56),MONTH(B56),1))
B57: 46303 | C57: Expense | D57: Eating out | E57: 46 | G57: =IF(B57="","",DATE(YEAR(B57),MONTH(B57),1))
B58: 46304 | C58: Expense | D58: Insurance | E58: 142 | G58: =IF(B58="","",DATE(YEAR(B58),MONTH(B58),1))
B59: 46305 | C59: Expense | D59: Groceries | E59: 84 | F59: Weekly shop | G59: =IF(B59="","",DATE(YEAR(B59),MONTH(B59),1))
B60: 46306 | C60: Expense | D60: Entertainment | E60: 29 | G60: =IF(B60="","",DATE(YEAR(B60),MONTH(B60),1))
B61: 46306 | C61: Expense | D61: Transport | E61: 48 | G61: =IF(B61="","",DATE(YEAR(B61),MONTH(B61),1))
B62: 46307 | C62: Expense | D62: Subscriptions | E62: 38 | G62: =IF(B62="","",DATE(YEAR(B62),MONTH(B62),1))
G63: =IF(B63="","",DATE(YEAR(B63),MONTH(B63),1))
G64: =IF(B64="","",DATE(YEAR(B64),MONTH(B64),1))
G65: =IF(B65="","",DATE(YEAR(B65),MONTH(B65),1))
G66: =IF(B66="","",DATE(YEAR(B66),MONTH(B66),1))
G67: =IF(B67="","",DATE(YEAR(B67),MONTH(B67),1))
G68: =IF(B68="","",DATE(YEAR(B68),MONTH(B68),1))
G69: =IF(B69="","",DATE(YEAR(B69),MONTH(B69),1))
G70: =IF(B70="","",DATE(YEAR(B70),MONTH(B70),1))
G71: =IF(B71="","",DATE(YEAR(B71),MONTH(B71),1))
G72: =IF(B72="","",DATE(YEAR(B72),MONTH(B72),1))
G73: =IF(B73="","",DATE(YEAR(B73),MONTH(B73),1))
G74: =IF(B74="","",DATE(YEAR(B74),MONTH(B74),1))
... G506: =IF(B506="","",DATE(YEAR(B506),MONTH(B506),1))

Sheet Budget
B2: Monthly Budget
B3: Month shown = Planning month in Setup. Type planned amounts in the white column.
B6: Month | C6: =PlanMonth
B8: Income | C8: Planned | D8: Actual | E8: Difference | F8: Received
B9: =IF('Setup'!B12="","",'Setup'!B12) | C9: 3250 | D9: =IF(B9="","",SUMIFS('Money Log'!$E$7:$E$506,'Money Log'!$D$7:$D$506,B9,'Money Log'!$C$7:$C$506,"Income",'Money Log'!$G$7:$G$506,PlanMonth)) | E9: =IF(B9="","",D9-N(C9)) | F9: =IF(OR(B9="",N(C9)=0),"",D9/C9)
B10: =IF('Setup'!B13="","",'Setup'!B13) | C10: 350 | D10: =IF(B10="","",SUMIFS('Money Log'!$E$7:$E$506,'Money Log'!$D$7:$D$506,B10,'Money Log'!$C$7:$C$506,"Income",'Money Log'!$G$7:$G$506,PlanMonth)) | E10: =IF(B10="","",D10-N(C10)) | F10: =IF(OR(B10="",N(C10)=0),"",D10/C10)
B11: =IF('Setup'!B14="","",'Setup'!B14) | D11: =IF(B11="","",SUMIFS('Money Log'!$E$7:$E$506,'Money Log'!$D$7:$D$506,B11,'Money Log'!$C$7:$C$506,"Income",'Money Log'!$G$7:$G$506,PlanMonth)) | E11: =IF(B11="","",D11-N(C11)) | F11: =IF(OR(B11="",N(C11)=0),"",D11/C11)
B12: =IF('Setup'!B15="","",'Setup'!B15) | D12: =IF(B12="","",SUMIFS('Money Log'!$E$7:$E$506,'Money Log'!$D$7:$D$506,B12,'Money Log'!$C$7:$C$506,"Income",'Money Log'!$G$7:$G$506,PlanMonth)) | E12: =IF(B12="","",D12-N(C12)) | F12: =IF(OR(B12="",N(C12)=0),"",D12/C12)
B13: =IF('Setup'!B16="","",'Setup'!B16) | D13: =IF(B13="","",SUMIFS('Money Log'!$E$7:$E$506,'Money Log'!$D$7:$D$506,B13,'Money Log'!$C$7:$C$506,"Income",'Money Log'!$G$7:$G$506,PlanMonth)) | E13: =IF(B13="","",D13-N(C13)) | F13: =IF(OR(B13="",N(C13)=0),"",D13/C13)
B14: =IF('Setup'!B17="","",'Setup'!B17) | D14: =IF(B14="","",SUMIFS('Money Log'!$E$7:$E$506,'Money Log'!$D$7:$D$506,B14,'Money Log'!$C$7:$C$506,"Income",'Money Log'!$G$7:$G$506,PlanMonth)) | E14: =IF(B14="","",D14-N(C14)) | F14: =IF(OR(B14="",N(C14)=0),"",D14/C14)
B15: =IF('Setup'!B18="","",'Setup'!B18) | D15: =IF(B15="","",SUMIFS('Money Log'!$E$7:$E$506,'Money Log'!$D$7:$D$506,B15,'Money Log'!$C$7:$C$506,"Income",'Money Log'!$G$7:$G$506,PlanMonth)) | E15: =IF(B15="","",D15-N(C15)) | F15: =IF(OR(B15="",N(C15)=0),"",D15/C15)
B16: =IF('Setup'!B19="","",'Setup'!B19) | D16: =IF(B16="","",SUMIFS('Money Log'!$E$7:$E$506,'Money Log'!$D$7:$D$506,B16,'Money Log'!$C$7:$C$506,"Income",'Money Log'!$G$7:$G$506,PlanMonth)) | E16: =IF(B16="","",D16-N(C16)) | F16: =IF(OR(B16="",N(C16)=0),"",D16/C16)
B17: =IF('Setup'!B20="","",'Setup'!B20) | D17: =IF(B17="","",SUMIFS('Money Log'!$E$7:$E$506,'Money Log'!$D$7:$D$506,B17,'Money Log'!$C$7:$C$506,"Income",'Money Log'!$G$7:$G$506,PlanMonth)) | E17: =IF(B17="","",D17-N(C17)) | F17: =IF(OR(B17="",N(C17)=0),"",D17/C17)
B18: =IF('Setup'!B21="","",'Setup'!B21) | D18: =IF(B18="","",SUMIFS('Money Log'!$E$7:$E$506,'Money Log'!$D$7:$D$506,B18,'Money Log'!$C$7:$C$506,"Income",'Money Log'!$G$7:$G$506,PlanMonth)) | E18: =IF(B18="","",D18-N(C18)) | F18: =IF(OR(B18="",N(C18)=0),"",D18/C18)
B20: Expenses | C20: Planned | D20: Actual | E20: Left | F20: Used
B21: =IF('Setup'!E12="","",'Setup'!E12) | C21: 1150 | D21: =IF(B21="","",SUMIFS('Money Log'!$E$7:$E$506,'Money Log'!$D$7:$D$506,B21,'Money Log'!$C$7:$C$506,"Expense",'Money Log'!$G$7:$G$506,PlanMonth)) | E21: =IF(B21="","",N(C21)-D21) | F21: =IF(OR(B21="",N(C21)=0),"",D21/C21) | H21: =IF(OR(B21="",N(D21)=0),"",D21+ROW()/1000000)
B22: =IF('Setup'!E13="","",'Setup'!E13) | C22: 120 | D22: =IF(B22="","",SUMIFS('Money Log'!$E$7:$E$506,'Money Log'!$D$7:$D$506,B22,'Money Log'!$C$7:$C$506,"Expense",'Money Log'!$G$7:$G$506,PlanMonth)) | E22: =IF(B22="","",N(C22)-D22) | F22: =IF(OR(B22="",N(C22)=0),"",D22/C22) | H22: =IF(OR(B22="",N(D22)=0),"",D22+ROW()/1000000)
B23: =IF('Setup'!E14="","",'Setup'!E14) | C23: 450 | D23: =IF(B23="","",SUMIFS('Money Log'!$E$7:$E$506,'Money Log'!$D$7:$D$506,B23,'Money Log'!$C$7:$C$506,"Expense",'Money Log'!$G$7:$G$506,PlanMonth)) | E23: =IF(B23="","",N(C23)-D23) | F23: =IF(OR(B23="",N(C23)=0),"",D23/C23) | H23: =IF(OR(B23="",N(D23)=0),"",D23+ROW()/1000000)
B24: =IF('Setup'!E15="","",'Setup'!E15) | C24: 180 | D24: =IF(B24="","",SUMIFS('Money Log'!$E$7:$E$506,'Money Log'!$D$7:$D$506,B24,'Money Log'!$C$7:$C$506,"Expense",'Money Log'!$G$7:$G$506,PlanMonth)) | E24: =IF(B24="","",N(C24)-D24) | F24: =IF(OR(B24="",N(C24)=0),"",D24/C24) | H24: =IF(OR(B24="",N(D24)=0),"",D24+ROW()/1000000)
B25: =IF('Setup'!E16="","",'Setup'!E16) | C25: 142 | D25: =IF(B25="","",SUMIFS('Money Log'!$E$7:$E$506,'Money Log'!$D$7:$D$506,B25,'Money Log'!$C$7:$C$506,"Expense",'Money Log'!$G$7:$G$506,PlanMonth)) | E25: =IF(B25="","",N(C25)-D25) | F25: =IF(OR(B25="",N(C25)=0),"",D25/C25) | H25: =IF(OR(B25="",N(D25)=0),"",D25+ROW()/1000000)
B26: =IF('Setup'!E17="","",'Setup'!E17) | C26: 65 | D26: =IF(B26="","",SUMIFS('Money Log'!$E$7:$E$506,'Money Log'!$D$7:$D$506,B26,'Money Log'!$C$7:$C$506,"Expense",'Money Log'!$G$7:$G$506,PlanMonth)) | E26: =IF(B26="","",N(C26)-D26) | F26: =IF(OR(B26="",N(C26)=0),"",D26/C26) | H26: =IF(OR(B26="",N(D26)=0),"",D26+ROW()/1000000)
B27: =IF('Setup'!E18="","",'Setup'!E18) | C27: 40 | D27: =IF(B27="","",SUMIFS('Money Log'!$E$7:$E$506,'Money Log'!$D$7:$D$506,B27,'Money Log'!$C$7:$C$506,"Expense",'Money Log'!$G$7:$G$506,PlanMonth)) | E27: =IF(B27="","",N(C27)-D27) | F27: =IF(OR(B27="",N(C27)=0),"",D27/C27) | H27: =IF(OR(B27="",N(D27)=0),"",D27+ROW()/1000000)
B28: =IF('Setup'!E19="","",'Setup'!E19) | C28: 80 | D28: =IF(B28="","",SUMIFS('Money Log'!$E$7:$E$506,'Money Log'!$D$7:$D$506,B28,'Money Log'!$C$7:$C$506,"Expense",'Money Log'!$G$7:$G$506,PlanMonth)) | E28: =IF(B28="","",N(C28)-D28) | F28: =IF(OR(B28="",N(C28)=0),"",D28/C28) | H28: =IF(OR(B28="",N(D28)=0),"",D28+ROW()/1000000)
B29: =IF('Setup'!E20="","",'Setup'!E20) | C29: 40 | D29: =IF(B29="","",SUMIFS('Money Log'!$E$7:$E$506,'Money Log'!$D$7:$D$506,B29,'Money Log'!$C$7:$C$506,"Expense",'Money Log'!$G$7:$G$506,PlanMonth)) | E29: =IF(B29="","",N(C29)-D29) | F29: =IF(OR(B29="",N(C29)=0),"",D29/C29) | H29: =IF(OR(B29="",N(D29)=0),"",D29+ROW()/1000000)
B30: =IF('Setup'!E21="","",'Setup'!E21) | C30: 30 | D30: =IF(B30="","",SUMIFS('Money Log'!$E$7:$E$506,'Money Log'!$D$7:$D$506,B30,'Money Log'!$C$7:$C$506,"Expense",'Money Log'!$G$7:$G$506,PlanMonth)) | E30: =IF(B30="","",N(C30)-D30) | F30: =IF(OR(B30="",N(C30)=0),"",D30/C30) | H30: =IF(OR(B30="",N(D30)=0),"",D30+ROW()/1000000)
B31: =IF('Setup'!E22="","",'Setup'!E22) | C31: 40 | D31: =IF(B31="","",SUMIFS('Money Log'!$E$7:$E$506,'Money Log'!$D$7:$D$506,B31,'Money Log'!$C$7:$C$506,"Expense",'Money Log'!$G$7:$G$506,PlanMonth)) | E31: =IF(B31="","",N(C31)-D31) | F31: =IF(OR(B31="",N(C31)=0),"",D31/C31) | H31: =IF(OR(B31="",N(D31)=0),"",D31+ROW()/1000000)
B32: =IF('Setup'!E23="","",'Setup'!E23) | D32: =IF(B32="","",SUMIFS('Money Log'!$E$7:$E$506,'Money Log'!$D$7:$D$506,B32,'Money Log'!$C$7:$C$506,"Expense",'Money Log'!$G$7:$G$506,PlanMonth)) | E32: =IF(B32="","",N(C32)-D32) | F32: =IF(OR(B32="",N(C32)=0),"",D32/C32) | H32: =IF(OR(B32="",N(D32)=0),"",D32+ROW()/1000000)
B33: =IF('Setup'!E24="","",'Setup'!E24) | C33: 60 | D33: =IF(B33="","",SUMIFS('Money Log'!$E$7:$E$506,'Money Log'!$D$7:$D$506,B33,'Money Log'!$C$7:$C$506,"Expense",'Money Log'!$G$7:$G$506,PlanMonth)) | E33: =IF(B33="","",N(C33)-D33) | F33: =IF(OR(B33="",N(C33)=0),"",D33/C33) | H33: =IF(OR(B33="",N(D33)=0),"",D33+ROW()/1000000)
B34: =IF('Setup'!E25="","",'Setup'!E25) | C34: 50 | D34: =IF(B34="","",SUMIFS('Money Log'!$E$7:$E$506,'Money Log'!$D$7:$D$506,B34,'Money Log'!$C$7:$C$506,"Expense",'Money Log'!$G$7:$G$506,PlanMonth)) | E34: =IF(B34="","",N(C34)-D34) | F34: =IF(OR(B34="",N(C34)=0),"",D34/C34) | H34: =IF(OR(B34="",N(D34)=0),"",D34+ROW()/1000000)
B35: =IF('Setup'!E26="","",'Setup'!E26) | C35: 40 | D35: =IF(B35="","",SUMIFS('Money Log'!$E$7:$E$506,'Money Log'!$D$7:$D$506,B35,'Money Log'!$C$7:$C$506,"Expense",'Money Log'!$G$7:$G$506,PlanMonth)) | E35: =IF(B35="","",N(C35)-D35) | F35: =IF(OR(B35="",N(C35)=0),"",D35/C35) | H35: =IF(OR(B35="",N(D35)=0),"",D35+ROW()/1000000)
B36: =IF('Setup'!E27="","",'Setup'!E27) | C36: 300 | D36: =IF(B36="","",SUMIFS('Money Log'!$E$7:$E$506,'Money Log'!$D$7:$D$506,B36,'Money Log'!$C$7:$C$506,"Expense",'Money Log'!$G$7:$G$506,PlanMonth)) | E36: =IF(B36="","",N(C36)-D36) | F36: =IF(OR(B36="",N(C36)=0),"",D36/C36) | H36: =IF(OR(B36="",N(D36)=0),"",D36+ROW()/1000000)
B37: =IF('Setup'!E28="","",'Setup'!E28) | C37: 250 | D37: =IF(B37="","",SUMIFS('Money Log'!$E$7:$E$506,'Money Log'!$D$7:$D$506,B37,'Money Log'!$C$7:$C$506,"Expense",'Money Log'!$G$7:$G$506,PlanMonth)) | E37: =IF(B37="","",N(C37)-D37) | F37: =IF(OR(B37="",N(C37)=0),"",D37/C37) | H37: =IF(OR(B37="",N(D37)=0),"",D37+ROW()/1000000)
B38: =IF('Setup'!E29="","",'Setup'!E29) | C38: 50 | D38: =IF(B38="","",SUMIFS('Money Log'!$E$7:$E$506,'Money Log'!$D$7:$D$506,B38,'Money Log'!$C$7:$C$506,"Expense",'Money Log'!$G$7:$G$506,PlanMonth)) | E38: =IF(B38="","",N(C38)-D38) | F38: =IF(OR(B38="",N(C38)=0),"",D38/C38) | H38: =IF(OR(B38="",N(D38)=0),"",D38+ROW()/1000000)
B39: =IF('Setup'!E30="","",'Setup'!E30) | D39: =IF(B39="","",SUMIFS('Money Log'!$E$7:$E$506,'Money Log'!$D$7:$D$506,B39,'Money Log'!$C$7:$C$506,"Expense",'Money Log'!$G$7:$G$506,PlanMonth)) | E39: =IF(B39="","",N(C39)-D39) | F39: =IF(OR(B39="",N(C39)=0),"",D39/C39) | H39: =IF(OR(B39="",N(D39)=0),"",D39+ROW()/1000000)
B40: =IF('Setup'!E31="","",'Setup'!E31) | D40: =IF(B40="","",SUMIFS('Money Log'!$E$7:$E$506,'Money Log'!$D$7:$D$506,B40,'Money Log'!$C$7:$C$506,"Expense",'Money Log'!$G$7:$G$506,PlanMonth)) | E40: =IF(B40="","",N(C40)-D40) | F40: =IF(OR(B40="",N(C40)=0),"",D40/C40) | H40: =IF(OR(B40="",N(D40)=0),"",D40+ROW()/1000000)
B42: Total income | D42: =SUM(D9:D18)
B43: Total expenses | D43: =SUM(D21:D40)
B44: Balance | D44: =D42-D43
B45: Planned left to spend | D45: =SUM(C21:C40)-D43
B46: Days left this month | D46: =IF(MONTH(TODAY())=MONTH(PlanMonth),DAY(EOMONTH(PlanMonth,0))-DAY(TODAY())+1,"")
B47: Safe to spend per day | D47: =IF(N(D46)=0,"",MAX(0,D45)/D46)

Sheet Annual
B2: Annual Overview
B3: Twelve months from the Money Log for the year in Setup. Nothing to type.
C5: =DATE('Setup'!$C$9,1,1) | D5: =DATE('Setup'!$C$9,2,1) | E5: =DATE('Setup'!$C$9,3,1) | F5: =DATE('Setup'!$C$9,4,1) | G5: =DATE('Setup'!$C$9,5,1) | H5: =DATE('Setup'!$C$9,6,1) | I5: =DATE('Setup'!$C$9,7,1) | J5: =DATE('Setup'!$C$9,8,1) | K5: =DATE('Setup'!$C$9,9,1) | L5: =DATE('Setup'!$C$9,10,1) | M5: =DATE('Setup'!$C$9,11,1) | N5: =DATE('Setup'!$C$9,12,1)
B6: Category | C6: Jan | D6: Feb | E6: Mar | F6: Apr | G6: May | H6: Jun | I6: Jul | J6: Aug | K6: Sep | L6: Oct | M6: Nov | N6: Dec | O6: Year
B7: INCOME
B8: =IF('Setup'!B12="","",'Setup'!B12) | C8: =IF($B8="","",SUMIFS('Money Log'!$E$7:$E$506,'Money Log'!$D$7:$D$506,$B8,'Money Log'!$C$7:$C$506,"Income",'Money Log'!$G$7:$G$506,C$5)) | D8: =IF($B8="","",SUMIFS('Money Log'!$E$7:$E$506,'Money Log'!$D$7:$D$506,$B8,'Money Log'!$C$7:$C$506,"Income",'Money Log'!$G$7:$G$506,D$5)) | E8: =IF($B8="","",SUMIFS('Money Log'!$E$7:$E$506,'Money Log'!$D$7:$D$506,$B8,'Money Log'!$C$7:$C$506,"Income",'Money Log'!$G$7:$G$506,E$5)) | F8: =IF($B8="","",SUMIFS('Money Log'!$E$7:$E$506,'Money Log'!$D$7:$D$506,$B8,'Money Log'!$C$7:$C$506,"Income",'Money Log'!$G$7:$G$506,F$5)) | G8: =IF($B8="","",SUMIFS('Money Log'!$E$7:$E$506,'Money Log'!$D$7:$D$506,$B8,'Money Log'!$C$7:$C$506,"Income",'Money Log'!$G$7:$G$506,G$5)) | H8: =IF($B8="","",SUMIFS('Money Log'!$E$7:$E$506,'Money Log'!$D$7:$D$506,$B8,'Money Log'!$C$7:$C$506,"Income",'Money Log'!$G$7:$G$506,H$5)) | I8: =IF($B8="","",SUMIFS('Money Log'!$E$7:$E$506,'Money Log'!$D$7:$D$506,$B8,'Money Log'!$C$7:$C$506,"Income",'Money Log'!$G$7:$G$506,I$5)) | J8: =IF($B8="","",SUMIFS('Money Log'!$E$7:$E$506,'Money Log'!$D$7:$D$506,$B8,'Money Log'!$C$7:$C$506,"Income",'Money Log'!$G$7:$G$506,J$5)) | ... N8: =IF($B8="","",SUMIFS('Money Log'!$E$7:$E$506,'Money Log'!$D$7:$D$506,$B8,'Money Log'!$C$7:$C$506,"Income",'Money Log'!$G$7:$G$506,N$5)) | O8: =IF($B8="","",SUM(C8:N8))
B9: =IF('Setup'!B13="","",'Setup'!B13) | C9: =IF($B9="","",SUMIFS('Money Log'!$E$7:$E$506,'Money Log'!$D$7:$D$506,$B9,'Money Log'!$C$7:$C$506,"Income",'Money Log'!$G$7:$G$506,C$5)) | D9: =IF($B9="","",SUMIFS('Money Log'!$E$7:$E$506,'Money Log'!$D$7:$D$506,$B9,'Money Log'!$C$7:$C$506,"Income",'Money Log'!$G$7:$G$506,D$5)) | E9: =IF($B9="","",SUMIFS('Money Log'!$E$7:$E$506,'Money Log'!$D$7:$D$506,$B9,'Money Log'!$C$7:$C$506,"Income",'Money Log'!$G$7:$G$506,E$5)) | F9: =IF($B9="","",SUMIFS('Money Log'!$E$7:$E$506,'Money Log'!$D$7:$D$506,$B9,'Money Log'!$C$7:$C$506,"Income",'Money Log'!$G$7:$G$506,F$5)) | G9: =IF($B9="","",SUMIFS('Money Log'!$E$7:$E$506,'Money Log'!$D$7:$D$506,$B9,'Money Log'!$C$7:$C$506,"Income",'Money Log'!$G$7:$G$506,G$5)) | H9: =IF($B9="","",SUMIFS('Money Log'!$E$7:$E$506,'Money Log'!$D$7:$D$506,$B9,'Money Log'!$C$7:$C$506,"Income",'Money Log'!$G$7:$G$506,H$5)) | I9: =IF($B9="","",SUMIFS('Money Log'!$E$7:$E$506,'Money Log'!$D$7:$D$506,$B9,'Money Log'!$C$7:$C$506,"Income",'Money Log'!$G$7:$G$506,I$5)) | J9: =IF($B9="","",SUMIFS('Money Log'!$E$7:$E$506,'Money Log'!$D$7:$D$506,$B9,'Money Log'!$C$7:$C$506,"Income",'Money Log'!$G$7:$G$506,J$5)) | ... N9: =IF($B9="","",SUMIFS('Money Log'!$E$7:$E$506,'Money Log'!$D$7:$D$506,$B9,'Money Log'!$C$7:$C$506,"Income",'Money Log'!$G$7:$G$506,N$5)) | O9: =IF($B9="","",SUM(C9:N9))
B10: =IF('Setup'!B14="","",'Setup'!B14) | C10: =IF($B10="","",SUMIFS('Money Log'!$E$7:$E$506,'Money Log'!$D$7:$D$506,$B10,'Money Log'!$C$7:$C$506,"Income",'Money Log'!$G$7:$G$506,C$5)) | D10: =IF($B10="","",SUMIFS('Money Log'!$E$7:$E$506,'Money Log'!$D$7:$D$506,$B10,'Money Log'!$C$7:$C$506,"Income",'Money Log'!$G$7:$G$506,D$5)) | E10: =IF($B10="","",SUMIFS('Money Log'!$E$7:$E$506,'Money Log'!$D$7:$D$506,$B10,'Money Log'!$C$7:$C$506,"Income",'Money Log'!$G$7:$G$506,E$5)) | F10: =IF($B10="","",SUMIFS('Money Log'!$E$7:$E$506,'Money Log'!$D$7:$D$506,$B10,'Money Log'!$C$7:$C$506,"Income",'Money Log'!$G$7:$G$506,F$5)) | G10: =IF($B10="","",SUMIFS('Money Log'!$E$7:$E$506,'Money Log'!$D$7:$D$506,$B10,'Money Log'!$C$7:$C$506,"Income",'Money Log'!$G$7:$G$506,G$5)) | H10: =IF($B10="","",SUMIFS('Money Log'!$E$7:$E$506,'Money Log'!$D$7:$D$506,$B10,'Money Log'!$C$7:$C$506,"Income",'Money Log'!$G$7:$G$506,H$5)) | I10: =IF($B10="","",SUMIFS('Money Log'!$E$7:$E$506,'Money Log'!$D$7:$D$506,$B10,'Money Log'!$C$7:$C$506,"Income",'Money Log'!$G$7:$G$506,I$5)) | J10: =IF($B10="","",SUMIFS('Money Log'!$E$7:$E$506,'Money Log'!$D$7:$D$506,$B10,'Money Log'!$C$7:$C$506,"Income",'Money Log'!$G$7:$G$506,J$5)) | ... N10: =IF($B10="","",SUMIFS('Money Log'!$E$7:$E$506,'Money Log'!$D$7:$D$506,$B10,'Money Log'!$C$7:$C$506,"Income",'Money Log'!$G$7:$G$506,N$5)) | O10: =IF($B10="","",SUM(C10:N10))
B11: =IF('Setup'!B15="","",'Setup'!B15) | C11: =IF($B11="","",SUMIFS('Money Log'!$E$7:$E$506,'Money Log'!$D$7:$D$506,$B11,'Money Log'!$C$7:$C$506,"Income",'Money Log'!$G$7:$G$506,C$5)) | D11: =IF($B11="","",SUMIFS('Money Log'!$E$7:$E$506,'Money Log'!$D$7:$D$506,$B11,'Money Log'!$C$7:$C$506,"Income",'Money Log'!$G$7:$G$506,D$5)) | E11: =IF($B11="","",SUMIFS('Money Log'!$E$7:$E$506,'Money Log'!$D$7:$D$506,$B11,'Money Log'!$C$7:$C$506,"Income",'Money Log'!$G$7:$G$506,E$5)) | F11: =IF($B11="","",SUMIFS('Money Log'!$E$7:$E$506,'Money Log'!$D$7:$D$506,$B11,'Money Log'!$C$7:$C$506,"Income",'Money Log'!$G$7:$G$506,F$5)) | G11: =IF($B11="","",SUMIFS('Money Log'!$E$7:$E$506,'Money Log'!$D$7:$D$506,$B11,'Money Log'!$C$7:$C$506,"Income",'Money Log'!$G$7:$G$506,G$5)) | H11: =IF($B11="","",SUMIFS('Money Log'!$E$7:$E$506,'Money Log'!$D$7:$D$506,$B11,'Money Log'!$C$7:$C$506,"Income",'Money Log'!$G$7:$G$506,H$5)) | I11: =IF($B11="","",SUMIFS('Money Log'!$E$7:$E$506,'Money Log'!$D$7:$D$506,$B11,'Money Log'!$C$7:$C$506,"Income",'Money Log'!$G$7:$G$506,I$5)) | J11: =IF($B11="","",SUMIFS('Money Log'!$E$7:$E$506,'Money Log'!$D$7:$D$506,$B11,'Money Log'!$C$7:$C$506,"Income",'Money Log'!$G$7:$G$506,J$5)) | ... N11: =IF($B11="","",SUMIFS('Money Log'!$E$7:$E$506,'Money Log'!$D$7:$D$506,$B11,'Money Log'!$C$7:$C$506,"Income",'Money Log'!$G$7:$G$506,N$5)) | O11: =IF($B11="","",SUM(C11:N11))
B12: =IF('Setup'!B16="","",'Setup'!B16) | C12: =IF($B12="","",SUMIFS('Money Log'!$E$7:$E$506,'Money Log'!$D$7:$D$506,$B12,'Money Log'!$C$7:$C$506,"Income",'Money Log'!$G$7:$G$506,C$5)) | D12: =IF($B12="","",SUMIFS('Money Log'!$E$7:$E$506,'Money Log'!$D$7:$D$506,$B12,'Money Log'!$C$7:$C$506,"Income",'Money Log'!$G$7:$G$506,D$5)) | E12: =IF($B12="","",SUMIFS('Money Log'!$E$7:$E$506,'Money Log'!$D$7:$D$506,$B12,'Money Log'!$C$7:$C$506,"Income",'Money Log'!$G$7:$G$506,E$5)) | F12: =IF($B12="","",SUMIFS('Money Log'!$E$7:$E$506,'Money Log'!$D$7:$D$506,$B12,'Money Log'!$C$7:$C$506,"Income",'Money Log'!$G$7:$G$506,F$5)) | G12: =IF($B12="","",SUMIFS('Money Log'!$E$7:$E$506,'Money Log'!$D$7:$D$506,$B12,'Money Log'!$C$7:$C$506,"Income",'Money Log'!$G$7:$G$506,G$5)) | H12: =IF($B12="","",SUMIFS('Money Log'!$E$7:$E$506,'Money Log'!$D$7:$D$506,$B12,'Money Log'!$C$7:$C$506,"Income",'Money Log'!$G$7:$G$506,H$5)) | I12: =IF($B12="","",SUMIFS('Money Log'!$E$7:$E$506,'Money Log'!$D$7:$D$506,$B12,'Money Log'!$C$7:$C$506,"Income",'Money Log'!$G$7:$G$506,I$5)) | J12: =IF($B12="","",SUMIFS('Money Log'!$E$7:$E$506,'Money Log'!$D$7:$D$506,$B12,'Money Log'!$C$7:$C$506,"Income",'Money Log'!$G$7:$G$506,J$5)) | ... N12: =IF($B12="","",SUMIFS('Money Log'!$E$7:$E$506,'Money Log'!$D$7:$D$506,$B12,'Money Log'!$C$7:$C$506,"Income",'Money Log'!$G$7:$G$506,N$5)) | O12: =IF($B12="","",SUM(C12:N12))
B13: =IF('Setup'!B17="","",'Setup'!B17) | C13: =IF($B13="","",SUMIFS('Money Log'!$E$7:$E$506,'Money Log'!$D$7:$D$506,$B13,'Money Log'!$C$7:$C$506,"Income",'Money Log'!$G$7:$G$506,C$5)) | D13: =IF($B13="","",SUMIFS('Money Log'!$E$7:$E$506,'Money Log'!$D$7:$D$506,$B13,'Money Log'!$C$7:$C$506,"Income",'Money Log'!$G$7:$G$506,D$5)) | E13: =IF($B13="","",SUMIFS('Money Log'!$E$7:$E$506,'Money Log'!$D$7:$D$506,$B13,'Money Log'!$C$7:$C$506,"Income",'Money Log'!$G$7:$G$506,E$5)) | F13: =IF($B13="","",SUMIFS('Money Log'!$E$7:$E$506,'Money Log'!$D$7:$D$506,$B13,'Money Log'!$C$7:$C$506,"Income",'Money Log'!$G$7:$G$506,F$5)) | G13: =IF($B13="","",SUMIFS('Money Log'!$E$7:$E$506,'Money Log'!$D$7:$D$506,$B13,'Money Log'!$C$7:$C$506,"Income",'Money Log'!$G$7:$G$506,G$5)) | H13: =IF($B13="","",SUMIFS('Money Log'!$E$7:$E$506,'Money Log'!$D$7:$D$506,$B13,'Money Log'!$C$7:$C$506,"Income",'Money Log'!$G$7:$G$506,H$5)) | I13: =IF($B13="","",SUMIFS('Money Log'!$E$7:$E$506,'Money Log'!$D$7:$D$506,$B13,'Money Log'!$C$7:$C$506,"Income",'Money Log'!$G$7:$G$506,I$5)) | J13: =IF($B13="","",SUMIFS('Money Log'!$E$7:$E$506,'Money Log'!$D$7:$D$506,$B13,'Money Log'!$C$7:$C$506,"Income",'Money Log'!$G$7:$G$506,J$5)) | ... N13: =IF($B13="","",SUMIFS('Money Log'!$E$7:$E$506,'Money Log'!$D$7:$D$506,$B13,'Money Log'!$C$7:$C$506,"Income",'Money Log'!$G$7:$G$506,N$5)) | O13: =IF($B13="","",SUM(C13:N13))
B14: =IF('Setup'!B18="","",'Setup'!B18) | C14: =IF($B14="","",SUMIFS('Money Log'!$E$7:$E$506,'Money Log'!$D$7:$D$506,$B14,'Money Log'!$C$7:$C$506,"Income",'Money Log'!$G$7:$G$506,C$5)) | D14: =IF($B14="","",SUMIFS('Money Log'!$E$7:$E$506,'Money Log'!$D$7:$D$506,$B14,'Money Log'!$C$7:$C$506,"Income",'Money Log'!$G$7:$G$506,D$5)) | E14: =IF($B14="","",SUMIFS('Money Log'!$E$7:$E$506,'Money Log'!$D$7:$D$506,$B14,'Money Log'!$C$7:$C$506,"Income",'Money Log'!$G$7:$G$506,E$5)) | F14: =IF($B14="","",SUMIFS('Money Log'!$E$7:$E$506,'Money Log'!$D$7:$D$506,$B14,'Money Log'!$C$7:$C$506,"Income",'Money Log'!$G$7:$G$506,F$5)) | G14: =IF($B14="","",SUMIFS('Money Log'!$E$7:$E$506,'Money Log'!$D$7:$D$506,$B14,'Money Log'!$C$7:$C$506,"Income",'Money Log'!$G$7:$G$506,G$5)) | H14: =IF($B14="","",SUMIFS('Money Log'!$E$7:$E$506,'Money Log'!$D$7:$D$506,$B14,'Money Log'!$C$7:$C$506,"Income",'Money Log'!$G$7:$G$506,H$5)) | I14: =IF($B14="","",SUMIFS('Money Log'!$E$7:$E$506,'Money Log'!$D$7:$D$506,$B14,'Money Log'!$C$7:$C$506,"Income",'Money Log'!$G$7:$G$506,I$5)) | J14: =IF($B14="","",SUMIFS('Money Log'!$E$7:$E$506,'Money Log'!$D$7:$D$506,$B14,'Money Log'!$C$7:$C$506,"Income",'Money Log'!$G$7:$G$506,J$5)) | ... N14: =IF($B14="","",SUMIFS('Money Log'!$E$7:$E$506,'Money Log'!$D$7:$D$506,$B14,'Money Log'!$C$7:$C$506,"Income",'Money Log'!$G$7:$G$506,N$5)) | O14: =IF($B14="","",SUM(C14:N14))
B15: =IF('Setup'!B19="","",'Setup'!B19) | C15: =IF($B15="","",SUMIFS('Money Log'!$E$7:$E$506,'Money Log'!$D$7:$D$506,$B15,'Money Log'!$C$7:$C$506,"Income",'Money Log'!$G$7:$G$506,C$5)) | D15: =IF($B15="","",SUMIFS('Money Log'!$E$7:$E$506,'Money Log'!$D$7:$D$506,$B15,'Money Log'!$C$7:$C$506,"Income",'Money Log'!$G$7:$G$506,D$5)) | E15: =IF($B15="","",SUMIFS('Money Log'!$E$7:$E$506,'Money Log'!$D$7:$D$506,$B15,'Money Log'!$C$7:$C$506,"Income",'Money Log'!$G$7:$G$506,E$5)) | F15: =IF($B15="","",SUMIFS('Money Log'!$E$7:$E$506,'Money Log'!$D$7:$D$506,$B15,'Money Log'!$C$7:$C$506,"Income",'Money Log'!$G$7:$G$506,F$5)) | G15: =IF($B15="","",SUMIFS('Money Log'!$E$7:$E$506,'Money Log'!$D$7:$D$506,$B15,'Money Log'!$C$7:$C$506,"Income",'Money Log'!$G$7:$G$506,G$5)) | H15: =IF($B15="","",SUMIFS('Money Log'!$E$7:$E$506,'Money Log'!$D$7:$D$506,$B15,'Money Log'!$C$7:$C$506,"Income",'Money Log'!$G$7:$G$506,H$5)) | I15: =IF($B15="","",SUMIFS('Money Log'!$E$7:$E$506,'Money Log'!$D$7:$D$506,$B15,'Money Log'!$C$7:$C$506,"Income",'Money Log'!$G$7:$G$506,I$5)) | J15: =IF($B15="","",SUMIFS('Money Log'!$E$7:$E$506,'Money Log'!$D$7:$D$506,$B15,'Money Log'!$C$7:$C$506,"Income",'Money Log'!$G$7:$G$506,J$5)) | ... N15: =IF($B15="","",SUMIFS('Money Log'!$E$7:$E$506,'Money Log'!$D$7:$D$506,$B15,'Money Log'!$C$7:$C$506,"Income",'Money Log'!$G$7:$G$506,N$5)) | O15: =IF($B15="","",SUM(C15:N15))
B16: =IF('Setup'!B20="","",'Setup'!B20) | C16: =IF($B16="","",SUMIFS('Money Log'!$E$7:$E$506,'Money Log'!$D$7:$D$506,$B16,'Money Log'!$C$7:$C$506,"Income",'Money Log'!$G$7:$G$506,C$5)) | D16: =IF($B16="","",SUMIFS('Money Log'!$E$7:$E$506,'Money Log'!$D$7:$D$506,$B16,'Money Log'!$C$7:$C$506,"Income",'Money Log'!$G$7:$G$506,D$5)) | E16: =IF($B16="","",SUMIFS('Money Log'!$E$7:$E$506,'Money Log'!$D$7:$D$506,$B16,'Money Log'!$C$7:$C$506,"Income",'Money Log'!$G$7:$G$506,E$5)) | F16: =IF($B16="","",SUMIFS('Money Log'!$E$7:$E$506,'Money Log'!$D$7:$D$506,$B16,'Money Log'!$C$7:$C$506,"Income",'Money Log'!$G$7:$G$506,F$5)) | G16: =IF($B16="","",SUMIFS('Money Log'!$E$7:$E$506,'Money Log'!$D$7:$D$506,$B16,'Money Log'!$C$7:$C$506,"Income",'Money Log'!$G$7:$G$506,G$5)) | H16: =IF($B16="","",SUMIFS('Money Log'!$E$7:$E$506,'Money Log'!$D$7:$D$506,$B16,'Money Log'!$C$7:$C$506,"Income",'Money Log'!$G$7:$G$506,H$5)) | I16: =IF($B16="","",SUMIFS('Money Log'!$E$7:$E$506,'Money Log'!$D$7:$D$506,$B16,'Money Log'!$C$7:$C$506,"Income",'Money Log'!$G$7:$G$506,I$5)) | J16: =IF($B16="","",SUMIFS('Money Log'!$E$7:$E$506,'Money Log'!$D$7:$D$506,$B16,'Money Log'!$C$7:$C$506,"Income",'Money Log'!$G$7:$G$506,J$5)) | ... N16: =IF($B16="","",SUMIFS('Money Log'!$E$7:$E$506,'Money Log'!$D$7:$D$506,$B16,'Money Log'!$C$7:$C$506,"Income",'Money Log'!$G$7:$G$506,N$5)) | O16: =IF($B16="","",SUM(C16:N16))
B17: =IF('Setup'!B21="","",'Setup'!B21) | C17: =IF($B17="","",SUMIFS('Money Log'!$E$7:$E$506,'Money Log'!$D$7:$D$506,$B17,'Money Log'!$C$7:$C$506,"Income",'Money Log'!$G$7:$G$506,C$5)) | D17: =IF($B17="","",SUMIFS('Money Log'!$E$7:$E$506,'Money Log'!$D$7:$D$506,$B17,'Money Log'!$C$7:$C$506,"Income",'Money Log'!$G$7:$G$506,D$5)) | E17: =IF($B17="","",SUMIFS('Money Log'!$E$7:$E$506,'Money Log'!$D$7:$D$506,$B17,'Money Log'!$C$7:$C$506,"Income",'Money Log'!$G$7:$G$506,E$5)) | F17: =IF($B17="","",SUMIFS('Money Log'!$E$7:$E$506,'Money Log'!$D$7:$D$506,$B17,'Money Log'!$C$7:$C$506,"Income",'Money Log'!$G$7:$G$506,F$5)) | G17: =IF($B17="","",SUMIFS('Money Log'!$E$7:$E$506,'Money Log'!$D$7:$D$506,$B17,'Money Log'!$C$7:$C$506,"Income",'Money Log'!$G$7:$G$506,G$5)) | H17: =IF($B17="","",SUMIFS('Money Log'!$E$7:$E$506,'Money Log'!$D$7:$D$506,$B17,'Money Log'!$C$7:$C$506,"Income",'Money Log'!$G$7:$G$506,H$5)) | I17: =IF($B17="","",SUMIFS('Money Log'!$E$7:$E$506,'Money Log'!$D$7:$D$506,$B17,'Money Log'!$C$7:$C$506,"Income",'Money Log'!$G$7:$G$506,I$5)) | J17: =IF($B17="","",SUMIFS('Money Log'!$E$7:$E$506,'Money Log'!$D$7:$D$506,$B17,'Money Log'!$C$7:$C$506,"Income",'Money Log'!$G$7:$G$506,J$5)) | ... N17: =IF($B17="","",SUMIFS('Money Log'!$E$7:$E$506,'Money Log'!$D$7:$D$506,$B17,'Money Log'!$C$7:$C$506,"Income",'Money Log'!$G$7:$G$506,N$5)) | O17: =IF($B17="","",SUM(C17:N17))
B18: Total income | C18: =SUM(C8:C17) | D18: =SUM(D8:D17) | E18: =SUM(E8:E17) | F18: =SUM(F8:F17) | G18: =SUM(G8:G17) | H18: =SUM(H8:H17) | I18: =SUM(I8:I17) | J18: =SUM(J8:J17) | ... O18: =SUM(O8:O17)
B20: EXPENSES
B21: =IF('Setup'!E12="","",'Setup'!E12) | C21: =IF($B21="","",SUMIFS('Money Log'!$E$7:$E$506,'Money Log'!$D$7:$D$506,$B21,'Money Log'!$C$7:$C$506,"Expense",'Money Log'!$G$7:$G$506,C$5)) | D21: =IF($B21="","",SUMIFS('Money Log'!$E$7:$E$506,'Money Log'!$D$7:$D$506,$B21,'Money Log'!$C$7:$C$506,"Expense",'Money Log'!$G$7:$G$506,D$5)) | E21: =IF($B21="","",SUMIFS('Money Log'!$E$7:$E$506,'Money Log'!$D$7:$D$506,$B21,'Money Log'!$C$7:$C$506,"Expense",'Money Log'!$G$7:$G$506,E$5)) | F21: =IF($B21="","",SUMIFS('Money Log'!$E$7:$E$506,'Money Log'!$D$7:$D$506,$B21,'Money Log'!$C$7:$C$506,"Expense",'Money Log'!$G$7:$G$506,F$5)) | G21: =IF($B21="","",SUMIFS('Money Log'!$E$7:$E$506,'Money Log'!$D$7:$D$506,$B21,'Money Log'!$C$7:$C$506,"Expense",'Money Log'!$G$7:$G$506,G$5)) | H21: =IF($B21="","",SUMIFS('Money Log'!$E$7:$E$506,'Money Log'!$D$7:$D$506,$B21,'Money Log'!$C$7:$C$506,"Expense",'Money Log'!$G$7:$G$506,H$5)) | I21: =IF($B21="","",SUMIFS('Money Log'!$E$7:$E$506,'Money Log'!$D$7:$D$506,$B21,'Money Log'!$C$7:$C$506,"Expense",'Money Log'!$G$7:$G$506,I$5)) | J21: =IF($B21="","",SUMIFS('Money Log'!$E$7:$E$506,'Money Log'!$D$7:$D$506,$B21,'Money Log'!$C$7:$C$506,"Expense",'Money Log'!$G$7:$G$506,J$5)) | ... N21: =IF($B21="","",SUMIFS('Money Log'!$E$7:$E$506,'Money Log'!$D$7:$D$506,$B21,'Money Log'!$C$7:$C$506,"Expense",'Money Log'!$G$7:$G$506,N$5)) | O21: =IF($B21="","",SUM(C21:N21))
B22: =IF('Setup'!E13="","",'Setup'!E13) | C22: =IF($B22="","",SUMIFS('Money Log'!$E$7:$E$506,'Money Log'!$D$7:$D$506,$B22,'Money Log'!$C$7:$C$506,"Expense",'Money Log'!$G$7:$G$506,C$5)) | D22: =IF($B22="","",SUMIFS('Money Log'!$E$7:$E$506,'Money Log'!$D$7:$D$506,$B22,'Money Log'!$C$7:$C$506,"Expense",'Money Log'!$G$7:$G$506,D$5)) | E22: =IF($B22="","",SUMIFS('Money Log'!$E$7:$E$506,'Money Log'!$D$7:$D$506,$B22,'Money Log'!$C$7:$C$506,"Expense",'Money Log'!$G$7:$G$506,E$5)) | F22: =IF($B22="","",SUMIFS('Money Log'!$E$7:$E$506,'Money Log'!$D$7:$D$506,$B22,'Money Log'!$C$7:$C$506,"Expense",'Money Log'!$G$7:$G$506,F$5)) | G22: =IF($B22="","",SUMIFS('Money Log'!$E$7:$E$506,'Money Log'!$D$7:$D$506,$B22,'Money Log'!$C$7:$C$506,"Expense",'Money Log'!$G$7:$G$506,G$5)) | H22: =IF($B22="","",SUMIFS('Money Log'!$E$7:$E$506,'Money Log'!$D$7:$D$506,$B22,'Money Log'!$C$7:$C$506,"Expense",'Money Log'!$G$7:$G$506,H$5)) | I22: =IF($B22="","",SUMIFS('Money Log'!$E$7:$E$506,'Money Log'!$D$7:$D$506,$B22,'Money Log'!$C$7:$C$506,"Expense",'Money Log'!$G$7:$G$506,I$5)) | J22: =IF($B22="","",SUMIFS('Money Log'!$E$7:$E$506,'Money Log'!$D$7:$D$506,$B22,'Money Log'!$C$7:$C$506,"Expense",'Money Log'!$G$7:$G$506,J$5)) | ... N22: =IF($B22="","",SUMIFS('Money Log'!$E$7:$E$506,'Money Log'!$D$7:$D$506,$B22,'Money Log'!$C$7:$C$506,"Expense",'Money Log'!$G$7:$G$506,N$5)) | O22: =IF($B22="","",SUM(C22:N22))
B23: =IF('Setup'!E14="","",'Setup'!E14) | C23: =IF($B23="","",SUMIFS('Money Log'!$E$7:$E$506,'Money Log'!$D$7:$D$506,$B23,'Money Log'!$C$7:$C$506,"Expense",'Money Log'!$G$7:$G$506,C$5)) | D23: =IF($B23="","",SUMIFS('Money Log'!$E$7:$E$506,'Money Log'!$D$7:$D$506,$B23,'Money Log'!$C$7:$C$506,"Expense",'Money Log'!$G$7:$G$506,D$5)) | E23: =IF($B23="","",SUMIFS('Money Log'!$E$7:$E$506,'Money Log'!$D$7:$D$506,$B23,'Money Log'!$C$7:$C$506,"Expense",'Money Log'!$G$7:$G$506,E$5)) | F23: =IF($B23="","",SUMIFS('Money Log'!$E$7:$E$506,'Money Log'!$D$7:$D$506,$B23,'Money Log'!$C$7:$C$506,"Expense",'Money Log'!$G$7:$G$506,F$5)) | G23: =IF($B23="","",SUMIFS('Money Log'!$E$7:$E$506,'Money Log'!$D$7:$D$506,$B23,'Money Log'!$C$7:$C$506,"Expense",'Money Log'!$G$7:$G$506,G$5)) | H23: =IF($B23="","",SUMIFS('Money Log'!$E$7:$E$506,'Money Log'!$D$7:$D$506,$B23,'Money Log'!$C$7:$C$506,"Expense",'Money Log'!$G$7:$G$506,H$5)) | I23: =IF($B23="","",SUMIFS('Money Log'!$E$7:$E$506,'Money Log'!$D$7:$D$506,$B23,'Money Log'!$C$7:$C$506,"Expense",'Money Log'!$G$7:$G$506,I$5)) | J23: =IF($B23="","",SUMIFS('Money Log'!$E$7:$E$506,'Money Log'!$D$7:$D$506,$B23,'Money Log'!$C$7:$C$506,"Expense",'Money Log'!$G$7:$G$506,J$5)) | ... N23: =IF($B23="","",SUMIFS('Money Log'!$E$7:$E$506,'Money Log'!$D$7:$D$506,$B23,'Money Log'!$C$7:$C$506,"Expense",'Money Log'!$G$7:$G$506,N$5)) | O23: =IF($B23="","",SUM(C23:N23))
B24: =IF('Setup'!E15="","",'Setup'!E15) | C24: =IF($B24="","",SUMIFS('Money Log'!$E$7:$E$506,'Money Log'!$D$7:$D$506,$B24,'Money Log'!$C$7:$C$506,"Expense",'Money Log'!$G$7:$G$506,C$5)) | D24: =IF($B24="","",SUMIFS('Money Log'!$E$7:$E$506,'Money Log'!$D$7:$D$506,$B24,'Money Log'!$C$7:$C$506,"Expense",'Money Log'!$G$7:$G$506,D$5)) | E24: =IF($B24="","",SUMIFS('Money Log'!$E$7:$E$506,'Money Log'!$D$7:$D$506,$B24,'Money Log'!$C$7:$C$506,"Expense",'Money Log'!$G$7:$G$506,E$5)) | F24: =IF($B24="","",SUMIFS('Money Log'!$E$7:$E$506,'Money Log'!$D$7:$D$506,$B24,'Money Log'!$C$7:$C$506,"Expense",'Money Log'!$G$7:$G$506,F$5)) | G24: =IF($B24="","",SUMIFS('Money Log'!$E$7:$E$506,'Money Log'!$D$7:$D$506,$B24,'Money Log'!$C$7:$C$506,"Expense",'Money Log'!$G$7:$G$506,G$5)) | H24: =IF($B24="","",SUMIFS('Money Log'!$E$7:$E$506,'Money Log'!$D$7:$D$506,$B24,'Money Log'!$C$7:$C$506,"Expense",'Money Log'!$G$7:$G$506,H$5)) | I24: =IF($B24="","",SUMIFS('Money Log'!$E$7:$E$506,'Money Log'!$D$7:$D$506,$B24,'Money Log'!$C$7:$C$506,"Expense",'Money Log'!$G$7:$G$506,I$5)) | J24: =IF($B24="","",SUMIFS('Money Log'!$E$7:$E$506,'Money Log'!$D$7:$D$506,$B24,'Money Log'!$C$7:$C$506,"Expense",'Money Log'!$G$7:$G$506,J$5)) | ... N24: =IF($B24="","",SUMIFS('Money Log'!$E$7:$E$506,'Money Log'!$D$7:$D$506,$B24,'Money Log'!$C$7:$C$506,"Expense",'Money Log'!$G$7:$G$506,N$5)) | O24: =IF($B24="","",SUM(C24:N24))
B25: =IF('Setup'!E16="","",'Setup'!E16) | C25: =IF($B25="","",SUMIFS('Money Log'!$E$7:$E$506,'Money Log'!$D$7:$D$506,$B25,'Money Log'!$C$7:$C$506,"Expense",'Money Log'!$G$7:$G$506,C$5)) | D25: =IF($B25="","",SUMIFS('Money Log'!$E$7:$E$506,'Money Log'!$D$7:$D$506,$B25,'Money Log'!$C$7:$C$506,"Expense",'Money Log'!$G$7:$G$506,D$5)) | E25: =IF($B25="","",SUMIFS('Money Log'!$E$7:$E$506,'Money Log'!$D$7:$D$506,$B25,'Money Log'!$C$7:$C$506,"Expense",'Money Log'!$G$7:$G$506,E$5)) | F25: =IF($B25="","",SUMIFS('Money Log'!$E$7:$E$506,'Money Log'!$D$7:$D$506,$B25,'Money Log'!$C$7:$C$506,"Expense",'Money Log'!$G$7:$G$506,F$5)) | G25: =IF($B25="","",SUMIFS('Money Log'!$E$7:$E$506,'Money Log'!$D$7:$D$506,$B25,'Money Log'!$C$7:$C$506,"Expense",'Money Log'!$G$7:$G$506,G$5)) | H25: =IF($B25="","",SUMIFS('Money Log'!$E$7:$E$506,'Money Log'!$D$7:$D$506,$B25,'Money Log'!$C$7:$C$506,"Expense",'Money Log'!$G$7:$G$506,H$5)) | I25: =IF($B25="","",SUMIFS('Money Log'!$E$7:$E$506,'Money Log'!$D$7:$D$506,$B25,'Money Log'!$C$7:$C$506,"Expense",'Money Log'!$G$7:$G$506,I$5)) | J25: =IF($B25="","",SUMIFS('Money Log'!$E$7:$E$506,'Money Log'!$D$7:$D$506,$B25,'Money Log'!$C$7:$C$506,"Expense",'Money Log'!$G$7:$G$506,J$5)) | ... N25: =IF($B25="","",SUMIFS('Money Log'!$E$7:$E$506,'Money Log'!$D$7:$D$506,$B25,'Money Log'!$C$7:$C$506,"Expense",'Money Log'!$G$7:$G$506,N$5)) | O25: =IF($B25="","",SUM(C25:N25))
B26: =IF('Setup'!E17="","",'Setup'!E17) | C26: =IF($B26="","",SUMIFS('Money Log'!$E$7:$E$506,'Money Log'!$D$7:$D$506,$B26,'Money Log'!$C$7:$C$506,"Expense",'Money Log'!$G$7:$G$506,C$5)) | D26: =IF($B26="","",SUMIFS('Money Log'!$E$7:$E$506,'Money Log'!$D$7:$D$506,$B26,'Money Log'!$C$7:$C$506,"Expense",'Money Log'!$G$7:$G$506,D$5)) | E26: =IF($B26="","",SUMIFS('Money Log'!$E$7:$E$506,'Money Log'!$D$7:$D$506,$B26,'Money Log'!$C$7:$C$506,"Expense",'Money Log'!$G$7:$G$506,E$5)) | F26: =IF($B26="","",SUMIFS('Money Log'!$E$7:$E$506,'Money Log'!$D$7:$D$506,$B26,'Money Log'!$C$7:$C$506,"Expense",'Money Log'!$G$7:$G$506,F$5)) | G26: =IF($B26="","",SUMIFS('Money Log'!$E$7:$E$506,'Money Log'!$D$7:$D$506,$B26,'Money Log'!$C$7:$C$506,"Expense",'Money Log'!$G$7:$G$506,G$5)) | H26: =IF($B26="","",SUMIFS('Money Log'!$E$7:$E$506,'Money Log'!$D$7:$D$506,$B26,'Money Log'!$C$7:$C$506,"Expense",'Money Log'!$G$7:$G$506,H$5)) | I26: =IF($B26="","",SUMIFS('Money Log'!$E$7:$E$506,'Money Log'!$D$7:$D$506,$B26,'Money Log'!$C$7:$C$506,"Expense",'Money Log'!$G$7:$G$506,I$5)) | J26: =IF($B26="","",SUMIFS('Money Log'!$E$7:$E$506,'Money Log'!$D$7:$D$506,$B26,'Money Log'!$C$7:$C$506,"Expense",'Money Log'!$G$7:$G$506,J$5)) | ... N26: =IF($B26="","",SUMIFS('Money Log'!$E$7:$E$506,'Money Log'!$D$7:$D$506,$B26,'Money Log'!$C$7:$C$506,"Expense",'Money Log'!$G$7:$G$506,N$5)) | O26: =IF($B26="","",SUM(C26:N26))
B27: =IF('Setup'!E18="","",'Setup'!E18) | C27: =IF($B27="","",SUMIFS('Money Log'!$E$7:$E$506,'Money Log'!$D$7:$D$506,$B27,'Money Log'!$C$7:$C$506,"Expense",'Money Log'!$G$7:$G$506,C$5)) | D27: =IF($B27="","",SUMIFS('Money Log'!$E$7:$E$506,'Money Log'!$D$7:$D$506,$B27,'Money Log'!$C$7:$C$506,"Expense",'Money Log'!$G$7:$G$506,D$5)) | E27: =IF($B27="","",SUMIFS('Money Log'!$E$7:$E$506,'Money Log'!$D$7:$D$506,$B27,'Money Log'!$C$7:$C$506,"Expense",'Money Log'!$G$7:$G$506,E$5)) | F27: =IF($B27="","",SUMIFS('Money Log'!$E$7:$E$506,'Money Log'!$D$7:$D$506,$B27,'Money Log'!$C$7:$C$506,"Expense",'Money Log'!$G$7:$G$506,F$5)) | G27: =IF($B27="","",SUMIFS('Money Log'!$E$7:$E$506,'Money Log'!$D$7:$D$506,$B27,'Money Log'!$C$7:$C$506,"Expense",'Money Log'!$G$7:$G$506,G$5)) | H27: =IF($B27="","",SUMIFS('Money Log'!$E$7:$E$506,'Money Log'!$D$7:$D$506,$B27,'Money Log'!$C$7:$C$506,"Expense",'Money Log'!$G$7:$G$506,H$5)) | I27: =IF($B27="","",SUMIFS('Money Log'!$E$7:$E$506,'Money Log'!$D$7:$D$506,$B27,'Money Log'!$C$7:$C$506,"Expense",'Money Log'!$G$7:$G$506,I$5)) | J27: =IF($B27="","",SUMIFS('Money Log'!$E$7:$E$506,'Money Log'!$D$7:$D$506,$B27,'Money Log'!$C$7:$C$506,"Expense",'Money Log'!$G$7:$G$506,J$5)) | ... N27: =IF($B27="","",SUMIFS('Money Log'!$E$7:$E$506,'Money Log'!$D$7:$D$506,$B27,'Money Log'!$C$7:$C$506,"Expense",'Money Log'!$G$7:$G$506,N$5)) | O27: =IF($B27="","",SUM(C27:N27))
B28: =IF('Setup'!E19="","",'Setup'!E19) | C28: =IF($B28="","",SUMIFS('Money Log'!$E$7:$E$506,'Money Log'!$D$7:$D$506,$B28,'Money Log'!$C$7:$C$506,"Expense",'Money Log'!$G$7:$G$506,C$5)) | D28: =IF($B28="","",SUMIFS('Money Log'!$E$7:$E$506,'Money Log'!$D$7:$D$506,$B28,'Money Log'!$C$7:$C$506,"Expense",'Money Log'!$G$7:$G$506,D$5)) | E28: =IF($B28="","",SUMIFS('Money Log'!$E$7:$E$506,'Money Log'!$D$7:$D$506,$B28,'Money Log'!$C$7:$C$506,"Expense",'Money Log'!$G$7:$G$506,E$5)) | F28: =IF($B28="","",SUMIFS('Money Log'!$E$7:$E$506,'Money Log'!$D$7:$D$506,$B28,'Money Log'!$C$7:$C$506,"Expense",'Money Log'!$G$7:$G$506,F$5)) | G28: =IF($B28="","",SUMIFS('Money Log'!$E$7:$E$506,'Money Log'!$D$7:$D$506,$B28,'Money Log'!$C$7:$C$506,"Expense",'Money Log'!$G$7:$G$506,G$5)) | H28: =IF($B28="","",SUMIFS('Money Log'!$E$7:$E$506,'Money Log'!$D$7:$D$506,$B28,'Money Log'!$C$7:$C$506,"Expense",'Money Log'!$G$7:$G$506,H$5)) | I28: =IF($B28="","",SUMIFS('Money Log'!$E$7:$E$506,'Money Log'!$D$7:$D$506,$B28,'Money Log'!$C$7:$C$506,"Expense",'Money Log'!$G$7:$G$506,I$5)) | J28: =IF($B28="","",SUMIFS('Money Log'!$E$7:$E$506,'Money Log'!$D$7:$D$506,$B28,'Money Log'!$C$7:$C$506,"Expense",'Money Log'!$G$7:$G$506,J$5)) | ... N28: =IF($B28="","",SUMIFS('Money Log'!$E$7:$E$506,'Money Log'!$D$7:$D$506,$B28,'Money Log'!$C$7:$C$506,"Expense",'Money Log'!$G$7:$G$506,N$5)) | O28: =IF($B28="","",SUM(C28:N28))
B29: =IF('Setup'!E20="","",'Setup'!E20) | C29: =IF($B29="","",SUMIFS('Money Log'!$E$7:$E$506,'Money Log'!$D$7:$D$506,$B29,'Money Log'!$C$7:$C$506,"Expense",'Money Log'!$G$7:$G$506,C$5)) | D29: =IF($B29="","",SUMIFS('Money Log'!$E$7:$E$506,'Money Log'!$D$7:$D$506,$B29,'Money Log'!$C$7:$C$506,"Expense",'Money Log'!$G$7:$G$506,D$5)) | E29: =IF($B29="","",SUMIFS('Money Log'!$E$7:$E$506,'Money Log'!$D$7:$D$506,$B29,'Money Log'!$C$7:$C$506,"Expense",'Money Log'!$G$7:$G$506,E$5)) | F29: =IF($B29="","",SUMIFS('Money Log'!$E$7:$E$506,'Money Log'!$D$7:$D$506,$B29,'Money Log'!$C$7:$C$506,"Expense",'Money Log'!$G$7:$G$506,F$5)) | G29: =IF($B29="","",SUMIFS('Money Log'!$E$7:$E$506,'Money Log'!$D$7:$D$506,$B29,'Money Log'!$C$7:$C$506,"Expense",'Money Log'!$G$7:$G$506,G$5)) | H29: =IF($B29="","",SUMIFS('Money Log'!$E$7:$E$506,'Money Log'!$D$7:$D$506,$B29,'Money Log'!$C$7:$C$506,"Expense",'Money Log'!$G$7:$G$506,H$5)) | I29: =IF($B29="","",SUMIFS('Money Log'!$E$7:$E$506,'Money Log'!$D$7:$D$506,$B29,'Money Log'!$C$7:$C$506,"Expense",'Money Log'!$G$7:$G$506,I$5)) | J29: =IF($B29="","",SUMIFS('Money Log'!$E$7:$E$506,'Money Log'!$D$7:$D$506,$B29,'Money Log'!$C$7:$C$506,"Expense",'Money Log'!$G$7:$G$506,J$5)) | ... N29: =IF($B29="","",SUMIFS('Money Log'!$E$7:$E$506,'Money Log'!$D$7:$D$506,$B29,'Money Log'!$C$7:$C$506,"Expense",'Money Log'!$G$7:$G$506,N$5)) | O29: =IF($B29="","",SUM(C29:N29))
B30: =IF('Setup'!E21="","",'Setup'!E21) | C30: =IF($B30="","",SUMIFS('Money Log'!$E$7:$E$506,'Money Log'!$D$7:$D$506,$B30,'Money Log'!$C$7:$C$506,"Expense",'Money Log'!$G$7:$G$506,C$5)) | D30: =IF($B30="","",SUMIFS('Money Log'!$E$7:$E$506,'Money Log'!$D$7:$D$506,$B30,'Money Log'!$C$7:$C$506,"Expense",'Money Log'!$G$7:$G$506,D$5)) | E30: =IF($B30="","",SUMIFS('Money Log'!$E$7:$E$506,'Money Log'!$D$7:$D$506,$B30,'Money Log'!$C$7:$C$506,"Expense",'Money Log'!$G$7:$G$506,E$5)) | F30: =IF($B30="","",SUMIFS('Money Log'!$E$7:$E$506,'Money Log'!$D$7:$D$506,$B30,'Money Log'!$C$7:$C$506,"Expense",'Money Log'!$G$7:$G$506,F$5)) | G30: =IF($B30="","",SUMIFS('Money Log'!$E$7:$E$506,'Money Log'!$D$7:$D$506,$B30,'Money Log'!$C$7:$C$506,"Expense",'Money Log'!$G$7:$G$506,G$5)) | H30: =IF($B30="","",SUMIFS('Money Log'!$E$7:$E$506,'Money Log'!$D$7:$D$506,$B30,'Money Log'!$C$7:$C$506,"Expense",'Money Log'!$G$7:$G$506,H$5)) | I30: =IF($B30="","",SUMIFS('Money Log'!$E$7:$E$506,'Money Log'!$D$7:$D$506,$B30,'Money Log'!$C$7:$C$506,"Expense",'Money Log'!$G$7:$G$506,I$5)) | J30: =IF($B30="","",SUMIFS('Money Log'!$E$7:$E$506,'Money Log'!$D$7:$D$506,$B30,'Money Log'!$C$7:$C$506,"Expense",'Money Log'!$G$7:$G$506,J$5)) | ... N30: =IF($B30="","",SUMIFS('Money Log'!$E$7:$E$506,'Money Log'!$D$7:$D$506,$B30,'Money Log'!$C$7:$C$506,"Expense",'Money Log'!$G$7:$G$506,N$5)) | O30: =IF($B30="","",SUM(C30:N30))
B31: =IF('Setup'!E22="","",'Setup'!E22) | C31: =IF($B31="","",SUMIFS('Money Log'!$E$7:$E$506,'Money Log'!$D$7:$D$506,$B31,'Money Log'!$C$7:$C$506,"Expense",'Money Log'!$G$7:$G$506,C$5)) | D31: =IF($B31="","",SUMIFS('Money Log'!$E$7:$E$506,'Money Log'!$D$7:$D$506,$B31,'Money Log'!$C$7:$C$506,"Expense",'Money Log'!$G$7:$G$506,D$5)) | E31: =IF($B31="","",SUMIFS('Money Log'!$E$7:$E$506,'Money Log'!$D$7:$D$506,$B31,'Money Log'!$C$7:$C$506,"Expense",'Money Log'!$G$7:$G$506,E$5)) | F31: =IF($B31="","",SUMIFS('Money Log'!$E$7:$E$506,'Money Log'!$D$7:$D$506,$B31,'Money Log'!$C$7:$C$506,"Expense",'Money Log'!$G$7:$G$506,F$5)) | G31: =IF($B31="","",SUMIFS('Money Log'!$E$7:$E$506,'Money Log'!$D$7:$D$506,$B31,'Money Log'!$C$7:$C$506,"Expense",'Money Log'!$G$7:$G$506,G$5)) | H31: =IF($B31="","",SUMIFS('Money Log'!$E$7:$E$506,'Money Log'!$D$7:$D$506,$B31,'Money Log'!$C$7:$C$506,"Expense",'Money Log'!$G$7:$G$506,H$5)) | I31: =IF($B31="","",SUMIFS('Money Log'!$E$7:$E$506,'Money Log'!$D$7:$D$506,$B31,'Money Log'!$C$7:$C$506,"Expense",'Money Log'!$G$7:$G$506,I$5)) | J31: =IF($B31="","",SUMIFS('Money Log'!$E$7:$E$506,'Money Log'!$D$7:$D$506,$B31,'Money Log'!$C$7:$C$506,"Expense",'Money Log'!$G$7:$G$506,J$5)) | ... N31: =IF($B31="","",SUMIFS('Money Log'!$E$7:$E$506,'Money Log'!$D$7:$D$506,$B31,'Money Log'!$C$7:$C$506,"Expense",'Money Log'!$G$7:$G$506,N$5)) | O31: =IF($B31="","",SUM(C31:N31))
B32: =IF('Setup'!E23="","",'Setup'!E23) | C32: =IF($B32="","",SUMIFS('Money Log'!$E$7:$E$506,'Money Log'!$D$7:$D$506,$B32,'Money Log'!$C$7:$C$506,"Expense",'Money Log'!$G$7:$G$506,C$5)) | D32: =IF($B32="","",SUMIFS('Money Log'!$E$7:$E$506,'Money Log'!$D$7:$D$506,$B32,'Money Log'!$C$7:$C$506,"Expense",'Money Log'!$G$7:$G$506,D$5)) | E32: =IF($B32="","",SUMIFS('Money Log'!$E$7:$E$506,'Money Log'!$D$7:$D$506,$B32,'Money Log'!$C$7:$C$506,"Expense",'Money Log'!$G$7:$G$506,E$5)) | F32: =IF($B32="","",SUMIFS('Money Log'!$E$7:$E$506,'Money Log'!$D$7:$D$506,$B32,'Money Log'!$C$7:$C$506,"Expense",'Money Log'!$G$7:$G$506,F$5)) | G32: =IF($B32="","",SUMIFS('Money Log'!$E$7:$E$506,'Money Log'!$D$7:$D$506,$B32,'Money Log'!$C$7:$C$506,"Expense",'Money Log'!$G$7:$G$506,G$5)) | H32: =IF($B32="","",SUMIFS('Money Log'!$E$7:$E$506,'Money Log'!$D$7:$D$506,$B32,'Money Log'!$C$7:$C$506,"Expense",'Money Log'!$G$7:$G$506,H$5)) | I32: =IF($B32="","",SUMIFS('Money Log'!$E$7:$E$506,'Money Log'!$D$7:$D$506,$B32,'Money Log'!$C$7:$C$506,"Expense",'Money Log'!$G$7:$G$506,I$5)) | J32: =IF($B32="","",SUMIFS('Money Log'!$E$7:$E$506,'Money Log'!$D$7:$D$506,$B32,'Money Log'!$C$7:$C$506,"Expense",'Money Log'!$G$7:$G$506,J$5)) | ... N32: =IF($B32="","",SUMIFS('Money Log'!$E$7:$E$506,'Money Log'!$D$7:$D$506,$B32,'Money Log'!$C$7:$C$506,"Expense",'Money Log'!$G$7:$G$506,N$5)) | O32: =IF($B32="","",SUM(C32:N32))
... B40: =IF('Setup'!E31="","",'Setup'!E31) | C40: =IF($B40="","",SUMIFS('Money Log'!$E$7:$E$506,'Money Log'!$D$7:$D$506,$B40,'Money Log'!$C$7:$C$506,"Expense",'Money Log'!$G$7:$G$506,C$5)) | D40: =IF($B40="","",SUMIFS('Money Log'!$E$7:$E$506,'Money Log'!$D$7:$D$506,$B40,'Money Log'!$C$7:$C$506,"Expense",'Money Log'!$G$7:$G$506,D$5)) | E40: =IF($B40="","",SUMIFS('Money Log'!$E$7:$E$506,'Money Log'!$D$7:$D$506,$B40,'Money Log'!$C$7:$C$506,"Expense",'Money Log'!$G$7:$G$506,E$5)) | F40: =IF($B40="","",SUMIFS('Money Log'!$E$7:$E$506,'Money Log'!$D$7:$D$506,$B40,'Money Log'!$C$7:$C$506,"Expense",'Money Log'!$G$7:$G$506,F$5)) | G40: =IF($B40="","",SUMIFS('Money Log'!$E$7:$E$506,'Money Log'!$D$7:$D$506,$B40,'Money Log'!$C$7:$C$506,"Expense",'Money Log'!$G$7:$G$506,G$5)) | H40: =IF($B40="","",SUMIFS('Money Log'!$E$7:$E$506,'Money Log'!$D$7:$D$506,$B40,'Money Log'!$C$7:$C$506,"Expense",'Money Log'!$G$7:$G$506,H$5)) | I40: =IF($B40="","",SUMIFS('Money Log'!$E$7:$E$506,'Money Log'!$D$7:$D$506,$B40,'Money Log'!$C$7:$C$506,"Expense",'Money Log'!$G$7:$G$506,I$5)) | J40: =IF($B40="","",SUMIFS('Money Log'!$E$7:$E$506,'Money Log'!$D$7:$D$506,$B40,'Money Log'!$C$7:$C$506,"Expense",'Money Log'!$G$7:$G$506,J$5)) | ... N40: =IF($B40="","",SUMIFS('Money Log'!$E$7:$E$506,'Money Log'!$D$7:$D$506,$B40,'Money Log'!$C$7:$C$506,"Expense",'Money Log'!$G$7:$G$506,N$5)) | O40: =IF($B40="","",SUM(C40:N40))
B41: Total expense | C41: =SUM(C21:C40) | D41: =SUM(D21:D40) | E41: =SUM(E21:E40) | F41: =SUM(F21:F40) | G41: =SUM(G21:G40) | H41: =SUM(H21:H40) | I41: =SUM(I21:I40) | J41: =SUM(J21:J40) | ... O41: =SUM(O21:O40)
B43: Net (income − expenses) | C43: =C18-C41 | D43: =D18-D41 | E43: =E18-E41 | F43: =F18-F41 | G43: =G18-G41 | H43: =H18-H41 | I43: =I18-I41 | J43: =J18-J41 | ... O43: =O18-O41

Sheet Savings & Debt
B2: Savings & Debt
B3: Type targets, balances and amounts saved or paid. Progress fills itself.
B6: Savings goal | C6: Target | D6: Saved | E6: Still needed | F6: Progress | G6: Target date
B7: Emergency fund | C7: 5000 | D7: 2100 | E7: =IF(B7="","",MAX(0,N(C7)-N(D7))) | F7: =IF(OR(B7="",N(C7)=0),"",MIN(1,N(D7)/C7)) | G7: 46568
B8: Vacation | C8: 1800 | D8: 650 | E8: =IF(B8="","",MAX(0,N(C8)-N(D8))) | F8: =IF(OR(B8="",N(C8)=0),"",MIN(1,N(D8)/C8)) | G8: 46569
B9: New laptop | C9: 1200 | D9: 900 | E9: =IF(B9="","",MAX(0,N(C9)-N(D9))) | F9: =IF(OR(B9="",N(C9)=0),"",MIN(1,N(D9)/C9)) | G9: 46418
B10: Car repairs | C10: 800 | D10: 240 | E10: =IF(B10="","",MAX(0,N(C10)-N(D10))) | F10: =IF(OR(B10="",N(C10)=0),"",MIN(1,N(D10)/C10))
E11: =IF(B11="","",MAX(0,N(C11)-N(D11))) | F11: =IF(OR(B11="",N(C11)=0),"",MIN(1,N(D11)/C11))
E12: =IF(B12="","",MAX(0,N(C12)-N(D12))) | F12: =IF(OR(B12="",N(C12)=0),"",MIN(1,N(D12)/C12))
E13: =IF(B13="","",MAX(0,N(C13)-N(D13))) | F13: =IF(OR(B13="",N(C13)=0),"",MIN(1,N(D13)/C13))
E14: =IF(B14="","",MAX(0,N(C14)-N(D14))) | F14: =IF(OR(B14="",N(C14)=0),"",MIN(1,N(D14)/C14))
E15: =IF(B15="","",MAX(0,N(C15)-N(D15))) | F15: =IF(OR(B15="",N(C15)=0),"",MIN(1,N(D15)/C15))
E16: =IF(B16="","",MAX(0,N(C16)-N(D16))) | F16: =IF(OR(B16="",N(C16)=0),"",MIN(1,N(D16)/C16))
E17: =IF(B17="","",MAX(0,N(C17)-N(D17))) | F17: =IF(OR(B17="",N(C17)=0),"",MIN(1,N(D17)/C17))
E18: =IF(B18="","",MAX(0,N(C18)-N(D18))) | F18: =IF(OR(B18="",N(C18)=0),"",MIN(1,N(D18)/C18))
B21: Debt | C21: Starting balance | D21: Paid so far | E21: Remaining | F21: Paid off | G21: Min. payment
B22: Credit card | C22: 3200 | D22: 1150 | E22: =IF(B22="","",MAX(0,N(C22)-N(D22))) | F22: =IF(OR(B22="",N(C22)=0),"",MIN(1,N(D22)/C22)) | G22: 90
B23: Car loan | C23: 9800 | D23: 2600 | E23: =IF(B23="","",MAX(0,N(C23)-N(D23))) | F23: =IF(OR(B23="",N(C23)=0),"",MIN(1,N(D23)/C23)) | G23: 245
B24: Student loan | C24: 14500 | D24: 1800 | E24: =IF(B24="","",MAX(0,N(C24)-N(D24))) | F24: =IF(OR(B24="",N(C24)=0),"",MIN(1,N(D24)/C24)) | G24: 160
E25: =IF(B25="","",MAX(0,N(C25)-N(D25))) | F25: =IF(OR(B25="",N(C25)=0),"",MIN(1,N(D25)/C25))
E26: =IF(B26="","",MAX(0,N(C26)-N(D26))) | F26: =IF(OR(B26="",N(C26)=0),"",MIN(1,N(D26)/C26))
E27: =IF(B27="","",MAX(0,N(C27)-N(D27))) | F27: =IF(OR(B27="",N(C27)=0),"",MIN(1,N(D27)/C27))
E28: =IF(B28="","",MAX(0,N(C28)-N(D28))) | F28: =IF(OR(B28="",N(C28)=0),"",MIN(1,N(D28)/C28))
E29: =IF(B29="","",MAX(0,N(C29)-N(D29))) | F29: =IF(OR(B29="",N(C29)=0),"",MIN(1,N(D29)/C29))
E30: =IF(B30="","",MAX(0,N(C30)-N(D30))) | F30: =IF(OR(B30="",N(C30)=0),"",MIN(1,N(D30)/C30))
E31: =IF(B31="","",MAX(0,N(C31)-N(D31))) | F31: =IF(OR(B31="",N(C31)=0),"",MIN(1,N(D31)/C31))
E32: =IF(B32="","",MAX(0,N(C32)-N(D32))) | F32: =IF(OR(B32="",N(C32)=0),"",MIN(1,N(D32)/C32))
E33: =IF(B33="","",MAX(0,N(C33)-N(D33))) | F33: =IF(OR(B33="",N(C33)=0),"",MIN(1,N(D33)/C33))
B36: Total saved | C36: =SUM(D7:D18)
B37: Total debt remaining | C37: =SUM(E22:E33)
B38: Monthly minimum payments | C38: =SUM(G22:G33)

Sheet Tasks
B2: Task List
B3: Type a task, pick a category, a due date and a priority. Mark it Done when finished.
B6: Task | C6: Category | D6: Due date | E6: Priority | F6: Status | G6: Days left
B7: Pay car insurance | C7: Money | D7: 46309 | E7: High | F7: To do | G7: =IF(OR(B7="",D7="",F7="Done"),"",D7-TODAY()) | I7: =IF(OR(B7="",D7="",F7="Done"),"",D7+ROW()/100000)
B8: Book dentist check-up | C8: Health | D8: 46312 | E8: Medium | F8: To do | G8: =IF(OR(B8="",D8="",F8="Done"),"",D8-TODAY()) | I8: =IF(OR(B8="",D8="",F8="Done"),"",D8+ROW()/100000)
B9: Renew passport | C9: Personal | D9: 46325 | E9: Medium | F9: In progress | G9: =IF(OR(B9="",D9="",F9="Done"),"",D9-TODAY()) | I9: =IF(OR(B9="",D9="",F9="Done"),"",D9+ROW()/100000)
B10: Order school photos | C10: Family | D10: 46310 | E10: Low | F10: To do | G10: =IF(OR(B10="",D10="",F10="Done"),"",D10-TODAY()) | I10: =IF(OR(B10="",D10="",F10="Done"),"",D10+ROW()/100000)
B11: Send quarterly report | C11: Work | D11: 46308 | E11: High | F11: In progress | G11: =IF(OR(B11="",D11="",F11="Done"),"",D11-TODAY()) | I11: =IF(OR(B11="",D11="",F11="Done"),"",D11+ROW()/100000)
B12: Return online order | C12: Errands | D12: 46306 | E12: Medium | F12: To do | G12: =IF(OR(B12="",D12="",F12="Done"),"",D12-TODAY()) | I12: =IF(OR(B12="",D12="",F12="Done"),"",D12+ROW()/100000)
B13: Clear out garage | C13: Home | D13: 46319 | E13: Low | F13: To do | G13: =IF(OR(B13="",D13="",F13="Done"),"",D13-TODAY()) | I13: =IF(OR(B13="",D13="",F13="Done"),"",D13+ROW()/100000)
B14: Call the bank about fees | C14: Money | D14: 46311 | E14: Medium | F14: To do | G14: =IF(OR(B14="",D14="",F14="Done"),"",D14-TODAY()) | I14: =IF(OR(B14="",D14="",F14="Done"),"",D14+ROW()/100000)
B15: Plan weekend trip | C15: Family | D15: 46316 | E15: Low | F15: To do | G15: =IF(OR(B15="",D15="",F15="Done"),"",D15-TODAY()) | I15: =IF(OR(B15="",D15="",F15="Done"),"",D15+ROW()/100000)
B16: Change smoke alarm batteries | C16: Home | D16: 46304 | E16: High | F16: Done | G16: =IF(OR(B16="",D16="",F16="Done"),"",D16-TODAY()) | I16: =IF(OR(B16="",D16="",F16="Done"),"",D16+ROW()/100000)
G17: =IF(OR(B17="",D17="",F17="Done"),"",D17-TODAY()) | I17: =IF(OR(B17="",D17="",F17="Done"),"",D17+ROW()/100000)
G18: =IF(OR(B18="",D18="",F18="Done"),"",D18-TODAY()) | I18: =IF(OR(B18="",D18="",F18="Done"),"",D18+ROW()/100000)
G19: =IF(OR(B19="",D19="",F19="Done"),"",D19-TODAY()) | I19: =IF(OR(B19="",D19="",F19="Done"),"",D19+ROW()/100000)
G20: =IF(OR(B20="",D20="",F20="Done"),"",D20-TODAY()) | I20: =IF(OR(B20="",D20="",F20="Done"),"",D20+ROW()/100000)
G21: =IF(OR(B21="",D21="",F21="Done"),"",D21-TODAY()) | I21: =IF(OR(B21="",D21="",F21="Done"),"",D21+ROW()/100000)
G22: =IF(OR(B22="",D22="",F22="Done"),"",D22-TODAY()) | I22: =IF(OR(B22="",D22="",F22="Done"),"",D22+ROW()/100000)
G23: =IF(OR(B23="",D23="",F23="Done"),"",D23-TODAY()) | I23: =IF(OR(B23="",D23="",F23="Done"),"",D23+ROW()/100000)
G24: =IF(OR(B24="",D24="",F24="Done"),"",D24-TODAY()) | I24: =IF(OR(B24="",D24="",F24="Done"),"",D24+ROW()/100000)
G25: =IF(OR(B25="",D25="",F25="Done"),"",D25-TODAY()) | I25: =IF(OR(B25="",D25="",F25="Done"),"",D25+ROW()/100000)
G26: =IF(OR(B26="",D26="",F26="Done"),"",D26-TODAY()) | I26: =IF(OR(B26="",D26="",F26="Done"),"",D26+ROW()/100000)
G27: =IF(OR(B27="",D27="",F27="Done"),"",D27-TODAY()) | I27: =IF(OR(B27="",D27="",F27="Done"),"",D27+ROW()/100000)
G28: =IF(OR(B28="",D28="",F28="Done"),"",D28-TODAY()) | I28: =IF(OR(B28="",D28="",F28="Done"),"",D28+ROW()/100000)
... G106: =IF(OR(B106="",D106="",F106="Done"),"",D106-TODAY()) | I106: =IF(OR(B106="",D106="",F106="Done"),"",D106+ROW()/100000)

Sheet Habits
B2: Habit Tracker
B3: Type x on each day you did the habit. Month shown = Planning month in Setup.
B6: Habit | C6: =IF(1>DAY(EOMONTH(PlanMonth,0)),"",1) | D6: =IF(2>DAY(EOMONTH(PlanMonth,0)),"",2) | E6: =IF(3>DAY(EOMONTH(PlanMonth,0)),"",3) | F6: =IF(4>DAY(EOMONTH(PlanMonth,0)),"",4) | G6: =IF(5>DAY(EOMONTH(PlanMonth,0)),"",5) | H6: =IF(6>DAY(EOMONTH(PlanMonth,0)),"",6) | I6: =IF(7>DAY(EOMONTH(PlanMonth,0)),"",7) | J6: =IF(8>DAY(EOMONTH(PlanMonth,0)),"",8) | K6: =IF(9>DAY(EOMONTH(PlanMonth,0)),"",9) | L6: =IF(10>DAY(EOMONTH(PlanMonth,0)),"",10) | M6: =IF(11>DAY(EOMONTH(PlanMonth,0)),"",11) | N6: =IF(12>DAY(EOMONTH(PlanMonth,0)),"",12) | O6: =IF(13>DAY(EOMONTH(PlanMonth,0)),"",13) | P6: =IF(14>DAY(EOMONTH(PlanMonth,0)),"",14) | Q6: =IF(15>DAY(EOMONTH(PlanMonth,0)),"",15) | R6: =IF(16>DAY(EOMONTH(PlanMonth,0)),"",16) | S6: =IF(17>DAY(EOMONTH(PlanMonth,0)),"",17) | T6: =IF(18>DAY(EOMONTH(PlanMonth,0)),"",18) | U6: =IF(19>DAY(EOMONTH(PlanMonth,0)),"",19) | V6: =IF(20>DAY(EOMONTH(PlanMonth,0)),"",20) | W6: =IF(21>DAY(EOMONTH(PlanMonth,0)),"",21) | X6: =IF(22>DAY(EOMONTH(PlanMonth,0)),"",22) | Y6: =IF(23>DAY(EOMONTH(PlanMonth,0)),"",23) | Z6: =IF(24>DAY(EOMONTH(PlanMonth,0)),"",24) | AA6: =IF(25>DAY(EOMONTH(PlanMonth,0)),"",25) | AB6: =IF(26>DAY(EOMONTH(PlanMonth,0)),"",26) | AC6: =IF(27>DAY(EOMONTH(PlanMonth,0)),"",27) | AD6: =IF(28>DAY(EOMONTH(PlanMonth,0)),"",28) | AE6: =IF(29>DAY(EOMONTH(PlanMonth,0)),"",29) | AF6: =IF(30>DAY(EOMONTH(PlanMonth,0)),"",30) | AG6: =IF(31>DAY(EOMONTH(PlanMonth,0)),"",31) | AH6: Done | AI6: Score | AJ6: Streak
B7: Drink 2 L of water | C7: x | D7: x | E7: x | F7: x | G7: x | H7: x | I7: x | J7: x | K7: x | L7: x | M7: x | AH7: =IF(B7="","",COUNTIF(C7:AG7,"x")) | AI7: =IF(B7="","",AH7/MAX(1,IF(MONTH(TODAY())=MONTH(PlanMonth),DAY(TODAY()),DAY(EOMONTH(PlanMonth,0))))) | AJ7: {=IF(B7="","",IFERROR(IF(MONTH(TODAY())=MONTH(PlanMonth),DAY(TODAY()),DAY(EOMONTH(PlanMonth,0)))-MAX(IF(OFFSET(C7,0,0,1,IF(MONTH(TODAY())=MONTH(PlanMonth),DAY(TODAY()),DAY(EOMONTH(PlanMonth,0))))<>"x",COLUMN(OFFSET(C7,0,0,1,IF(MONTH(TODAY())=MONTH(PlanMonth),DAY(TODAY()),DAY(EOMONTH(PlanMonth,0)))))-COLUMN(C7)+1,0)),0))}
B8: Walk 8,000 steps | C8: x | D8: x | E8: x | F8: x | G8: x | H8: x | I8: x | J8: x | L8: x | AH8: =IF(B8="","",COUNTIF(C8:AG8,"x")) | AI8: =IF(B8="","",AH8/MAX(1,IF(MONTH(TODAY())=MONTH(PlanMonth),DAY(TODAY()),DAY(EOMONTH(PlanMonth,0))))) | AJ8: {=IF(B8="","",IFERROR(IF(MONTH(TODAY())=MONTH(PlanMonth),DAY(TODAY()),DAY(EOMONTH(PlanMonth,0)))-MAX(IF(OFFSET(C8,0,0,1,IF(MONTH(TODAY())=MONTH(PlanMonth),DAY(TODAY()),DAY(EOMONTH(PlanMonth,0))))<>"x",COLUMN(OFFSET(C8,0,0,1,IF(MONTH(TODAY())=MONTH(PlanMonth),DAY(TODAY()),DAY(EOMONTH(PlanMonth,0)))))-COLUMN(C8)+1,0)),0))}
B9: Read 20 minutes | C9: x | D9: x | E9: x | G9: x | H9: x | I9: x | J9: x | K9: x | L9: x | M9: x | AH9: =IF(B9="","",COUNTIF(C9:AG9,"x")) | AI9: =IF(B9="","",AH9/MAX(1,IF(MONTH(TODAY())=MONTH(PlanMonth),DAY(TODAY()),DAY(EOMONTH(PlanMonth,0))))) | AJ9: {=IF(B9="","",IFERROR(IF(MONTH(TODAY())=MONTH(PlanMonth),DAY(TODAY()),DAY(EOMONTH(PlanMonth,0)))-MAX(IF(OFFSET(C9,0,0,1,IF(MONTH(TODAY())=MONTH(PlanMonth),DAY(TODAY()),DAY(EOMONTH(PlanMonth,0))))<>"x",COLUMN(OFFSET(C9,0,0,1,IF(MONTH(TODAY())=MONTH(PlanMonth),DAY(TODAY()),DAY(EOMONTH(PlanMonth,0)))))-COLUMN(C9)+1,0)),0))}
B10: No phone after 22:00 | C10: x | D10: x | E10: x | G10: x | I10: x | J10: x | M10: x | AH10: =IF(B10="","",COUNTIF(C10:AG10,"x")) | AI10: =IF(B10="","",AH10/MAX(1,IF(MONTH(TODAY())=MONTH(PlanMonth),DAY(TODAY()),DAY(EOMONTH(PlanMonth,0))))) | AJ10: {=IF(B10="","",IFERROR(IF(MONTH(TODAY())=MONTH(PlanMonth),DAY(TODAY()),DAY(EOMONTH(PlanMonth,0)))-MAX(IF(OFFSET(C10,0,0,1,IF(MONTH(TODAY())=MONTH(PlanMonth),DAY(TODAY()),DAY(EOMONTH(PlanMonth,0))))<>"x",COLUMN(OFFSET(C10,0,0,1,IF(MONTH(TODAY())=MONTH(PlanMonth),DAY(TODAY()),DAY(EOMONTH(PlanMonth,0)))))-COLUMN(C10)+1,0)),0))}
B11: Stretch / yoga | C11: x | D11: x | F11: x | G11: x | H11: x | I11: x | J11: x | L11: x | M11: x | AH11: =IF(B11="","",COUNTIF(C11:AG11,"x")) | AI11: =IF(B11="","",AH11/MAX(1,IF(MONTH(TODAY())=MONTH(PlanMonth),DAY(TODAY()),DAY(EOMONTH(PlanMonth,0))))) | AJ11: {=IF(B11="","",IFERROR(IF(MONTH(TODAY())=MONTH(PlanMonth),DAY(TODAY()),DAY(EOMONTH(PlanMonth,0)))-MAX(IF(OFFSET(C11,0,0,1,IF(MONTH(TODAY())=MONTH(PlanMonth),DAY(TODAY()),DAY(EOMONTH(PlanMonth,0))))<>"x",COLUMN(OFFSET(C11,0,0,1,IF(MONTH(TODAY())=MONTH(PlanMonth),DAY(TODAY()),DAY(EOMONTH(PlanMonth,0)))))-COLUMN(C11)+1,0)),0))}
B12: Make the bed | C12: x | D12: x | E12: x | G12: x | I12: x | J12: x | K12: x | L12: x | M12: x | AH12: =IF(B12="","",COUNTIF(C12:AG12,"x")) | AI12: =IF(B12="","",AH12/MAX(1,IF(MONTH(TODAY())=MONTH(PlanMonth),DAY(TODAY()),DAY(EOMONTH(PlanMonth,0))))) | AJ12: {=IF(B12="","",IFERROR(IF(MONTH(TODAY())=MONTH(PlanMonth),DAY(TODAY()),DAY(EOMONTH(PlanMonth,0)))-MAX(IF(OFFSET(C12,0,0,1,IF(MONTH(TODAY())=MONTH(PlanMonth),DAY(TODAY()),DAY(EOMONTH(PlanMonth,0))))<>"x",COLUMN(OFFSET(C12,0,0,1,IF(MONTH(TODAY())=MONTH(PlanMonth),DAY(TODAY()),DAY(EOMONTH(PlanMonth,0)))))-COLUMN(C12)+1,0)),0))}
B13: Cook at home | D13: x | F13: x | G13: x | H13: x | I13: x | J13: x | K13: x | L13: x | M13: x | AH13: =IF(B13="","",COUNTIF(C13:AG13,"x")) | AI13: =IF(B13="","",AH13/MAX(1,IF(MONTH(TODAY())=MONTH(PlanMonth),DAY(TODAY()),DAY(EOMONTH(PlanMonth,0))))) | AJ13: {=IF(B13="","",IFERROR(IF(MONTH(TODAY())=MONTH(PlanMonth),DAY(TODAY()),DAY(EOMONTH(PlanMonth,0)))-MAX(IF(OFFSET(C13,0,0,1,IF(MONTH(TODAY())=MONTH(PlanMonth),DAY(TODAY()),DAY(EOMONTH(PlanMonth,0))))<>"x",COLUMN(OFFSET(C13,0,0,1,IF(MONTH(TODAY())=MONTH(PlanMonth),DAY(TODAY()),DAY(EOMONTH(PlanMonth,0)))))-COLUMN(C13)+1,0)),0))}
B14: Journal | D14: x | E14: x | F14: x | G14: x | H14: x | I14: x | J14: x | L14: x | M14: x | AH14: =IF(B14="","",COUNTIF(C14:AG14,"x")) | AI14: =IF(B14="","",AH14/MAX(1,IF(MONTH(TODAY())=MONTH(PlanMonth),DAY(TODAY()),DAY(EOMONTH(PlanMonth,0))))) | AJ14: {=IF(B14="","",IFERROR(IF(MONTH(TODAY())=MONTH(PlanMonth),DAY(TODAY()),DAY(EOMONTH(PlanMonth,0)))-MAX(IF(OFFSET(C14,0,0,1,IF(MONTH(TODAY())=MONTH(PlanMonth),DAY(TODAY()),DAY(EOMONTH(PlanMonth,0))))<>"x",COLUMN(OFFSET(C14,0,0,1,IF(MONTH(TODAY())=MONTH(PlanMonth),DAY(TODAY()),DAY(EOMONTH(PlanMonth,0)))))-COLUMN(C14)+1,0)),0))}
B15: Take vitamins | C15: x | D15: x | E15: x | F15: x | G15: x | J15: x | L15: x | AH15: =IF(B15="","",COUNTIF(C15:AG15,"x")) | AI15: =IF(B15="","",AH15/MAX(1,IF(MONTH(TODAY())=MONTH(PlanMonth),DAY(TODAY()),DAY(EOMONTH(PlanMonth,0))))) | AJ15: {=IF(B15="","",IFERROR(IF(MONTH(TODAY())=MONTH(PlanMonth),DAY(TODAY()),DAY(EOMONTH(PlanMonth,0)))-MAX(IF(OFFSET(C15,0,0,1,IF(MONTH(TODAY())=MONTH(PlanMonth),DAY(TODAY()),DAY(EOMONTH(PlanMonth,0))))<>"x",COLUMN(OFFSET(C15,0,0,1,IF(MONTH(TODAY())=MONTH(PlanMonth),DAY(TODAY()),DAY(EOMONTH(PlanMonth,0)))))-COLUMN(C15)+1,0)),0))}
B16: Tidy for 10 minutes | D16: x | E16: x | F16: x | G16: x | H16: x | I16: x | J16: x | L16: x | M16: x | AH16: =IF(B16="","",COUNTIF(C16:AG16,"x")) | AI16: =IF(B16="","",AH16/MAX(1,IF(MONTH(TODAY())=MONTH(PlanMonth),DAY(TODAY()),DAY(EOMONTH(PlanMonth,0))))) | AJ16: {=IF(B16="","",IFERROR(IF(MONTH(TODAY())=MONTH(PlanMonth),DAY(TODAY()),DAY(EOMONTH(PlanMonth,0)))-MAX(IF(OFFSET(C16,0,0,1,IF(MONTH(TODAY())=MONTH(PlanMonth),DAY(TODAY()),DAY(EOMONTH(PlanMonth,0))))<>"x",COLUMN(OFFSET(C16,0,0,1,IF(MONTH(TODAY())=MONTH(PlanMonth),DAY(TODAY()),DAY(EOMONTH(PlanMonth,0)))))-COLUMN(C16)+1,0)),0))}
B17: No spend day | C17: x | D17: x | E17: x | F17: x | H17: x | I17: x | J17: x | K17: x | L17: x | AH17: =IF(B17="","",COUNTIF(C17:AG17,"x")) | AI17: =IF(B17="","",AH17/MAX(1,IF(MONTH(TODAY())=MONTH(PlanMonth),DAY(TODAY()),DAY(EOMONTH(PlanMonth,0))))) | AJ17: {=IF(B17="","",IFERROR(IF(MONTH(TODAY())=MONTH(PlanMonth),DAY(TODAY()),DAY(EOMONTH(PlanMonth,0)))-MAX(IF(OFFSET(C17,0,0,1,IF(MONTH(TODAY())=MONTH(PlanMonth),DAY(TODAY()),DAY(EOMONTH(PlanMonth,0))))<>"x",COLUMN(OFFSET(C17,0,0,1,IF(MONTH(TODAY())=MONTH(PlanMonth),DAY(TODAY()),DAY(EOMONTH(PlanMonth,0)))))-COLUMN(C17)+1,0)),0))}
B18: Sleep by 23:00 | C18: x | D18: x | E18: x | F18: x | H18: x | I18: x | J18: x | M18: x | AH18: =IF(B18="","",COUNTIF(C18:AG18,"x")) | AI18: =IF(B18="","",AH18/MAX(1,IF(MONTH(TODAY())=MONTH(PlanMonth),DAY(TODAY()),DAY(EOMONTH(PlanMonth,0))))) | AJ18: {=IF(B18="","",IFERROR(IF(MONTH(TODAY())=MONTH(PlanMonth),DAY(TODAY()),DAY(EOMONTH(PlanMonth,0)))-MAX(IF(OFFSET(C18,0,0,1,IF(MONTH(TODAY())=MONTH(PlanMonth),DAY(TODAY()),DAY(EOMONTH(PlanMonth,0))))<>"x",COLUMN(OFFSET(C18,0,0,1,IF(MONTH(TODAY())=MONTH(PlanMonth),DAY(TODAY()),DAY(EOMONTH(PlanMonth,0)))))-COLUMN(C18)+1,0)),0))}
AH19: =IF(B19="","",COUNTIF(C19:AG19,"x")) | AI19: =IF(B19="","",AH19/MAX(1,IF(MONTH(TODAY())=MONTH(PlanMonth),DAY(TODAY()),DAY(EOMONTH(PlanMonth,0))))) | AJ19: {=IF(B19="","",IFERROR(IF(MONTH(TODAY())=MONTH(PlanMonth),DAY(TODAY()),DAY(EOMONTH(PlanMonth,0)))-MAX(IF(OFFSET(C19,0,0,1,IF(MONTH(TODAY())=MONTH(PlanMonth),DAY(TODAY()),DAY(EOMONTH(PlanMonth,0))))<>"x",COLUMN(OFFSET(C19,0,0,1,IF(MONTH(TODAY())=MONTH(PlanMonth),DAY(TODAY()),DAY(EOMONTH(PlanMonth,0)))))-COLUMN(C19)+1,0)),0))}
AH20: =IF(B20="","",COUNTIF(C20:AG20,"x")) | AI20: =IF(B20="","",AH20/MAX(1,IF(MONTH(TODAY())=MONTH(PlanMonth),DAY(TODAY()),DAY(EOMONTH(PlanMonth,0))))) | AJ20: {=IF(B20="","",IFERROR(IF(MONTH(TODAY())=MONTH(PlanMonth),DAY(TODAY()),DAY(EOMONTH(PlanMonth,0)))-MAX(IF(OFFSET(C20,0,0,1,IF(MONTH(TODAY())=MONTH(PlanMonth),DAY(TODAY()),DAY(EOMONTH(PlanMonth,0))))<>"x",COLUMN(OFFSET(C20,0,0,1,IF(MONTH(TODAY())=MONTH(PlanMonth),DAY(TODAY()),DAY(EOMONTH(PlanMonth,0)))))-COLUMN(C20)+1,0)),0))}
AH21: =IF(B21="","",COUNTIF(C21:AG21,"x")) | AI21: =IF(B21="","",AH21/MAX(1,IF(MONTH(TODAY())=MONTH(PlanMonth),DAY(TODAY()),DAY(EOMONTH(PlanMonth,0))))) | AJ21: {=IF(B21="","",IFERROR(IF(MONTH(TODAY())=MONTH(PlanMonth),DAY(TODAY()),DAY(EOMONTH(PlanMonth,0)))-MAX(IF(OFFSET(C21,0,0,1,IF(MONTH(TODAY())=MONTH(PlanMonth),DAY(TODAY()),DAY(EOMONTH(PlanMonth,0))))<>"x",COLUMN(OFFSET(C21,0,0,1,IF(MONTH(TODAY())=MONTH(PlanMonth),DAY(TODAY()),DAY(EOMONTH(PlanMonth,0)))))-COLUMN(C21)+1,0)),0))}
AH22: =IF(B22="","",COUNTIF(C22:AG22,"x")) | AI22: =IF(B22="","",AH22/MAX(1,IF(MONTH(TODAY())=MONTH(PlanMonth),DAY(TODAY()),DAY(EOMONTH(PlanMonth,0))))) | AJ22: {=IF(B22="","",IFERROR(IF(MONTH(TODAY())=MONTH(PlanMonth),DAY(TODAY()),DAY(EOMONTH(PlanMonth,0)))-MAX(IF(OFFSET(C22,0,0,1,IF(MONTH(TODAY())=MONTH(PlanMonth),DAY(TODAY()),DAY(EOMONTH(PlanMonth,0))))<>"x",COLUMN(OFFSET(C22,0,0,1,IF(MONTH(TODAY())=MONTH(PlanMonth),DAY(TODAY()),DAY(EOMONTH(PlanMonth,0)))))-COLUMN(C22)+1,0)),0))}
AH23: =IF(B23="","",COUNTIF(C23:AG23,"x")) | AI23: =IF(B23="","",AH23/MAX(1,IF(MONTH(TODAY())=MONTH(PlanMonth),DAY(TODAY()),DAY(EOMONTH(PlanMonth,0))))) | AJ23: {=IF(B23="","",IFERROR(IF(MONTH(TODAY())=MONTH(PlanMonth),DAY(TODAY()),DAY(EOMONTH(PlanMonth,0)))-MAX(IF(OFFSET(C23,0,0,1,IF(MONTH(TODAY())=MONTH(PlanMonth),DAY(TODAY()),DAY(EOMONTH(PlanMonth,0))))<>"x",COLUMN(OFFSET(C23,0,0,1,IF(MONTH(TODAY())=MONTH(PlanMonth),DAY(TODAY()),DAY(EOMONTH(PlanMonth,0)))))-COLUMN(C23)+1,0)),0))}
AH24: =IF(B24="","",COUNTIF(C24:AG24,"x")) | AI24: =IF(B24="","",AH24/MAX(1,IF(MONTH(TODAY())=MONTH(PlanMonth),DAY(TODAY()),DAY(EOMONTH(PlanMonth,0))))) | AJ24: {=IF(B24="","",IFERROR(IF(MONTH(TODAY())=MONTH(PlanMonth),DAY(TODAY()),DAY(EOMONTH(PlanMonth,0)))-MAX(IF(OFFSET(C24,0,0,1,IF(MONTH(TODAY())=MONTH(PlanMonth),DAY(TODAY()),DAY(EOMONTH(PlanMonth,0))))<>"x",COLUMN(OFFSET(C24,0,0,1,IF(MONTH(TODAY())=MONTH(PlanMonth),DAY(TODAY()),DAY(EOMONTH(PlanMonth,0)))))-COLUMN(C24)+1,0)),0))}
AH25: =IF(B25="","",COUNTIF(C25:AG25,"x")) | AI25: =IF(B25="","",AH25/MAX(1,IF(MONTH(TODAY())=MONTH(PlanMonth),DAY(TODAY()),DAY(EOMONTH(PlanMonth,0))))) | AJ25: {=IF(B25="","",IFERROR(IF(MONTH(TODAY())=MONTH(PlanMonth),DAY(TODAY()),DAY(EOMONTH(PlanMonth,0)))-MAX(IF(OFFSET(C25,0,0,1,IF(MONTH(TODAY())=MONTH(PlanMonth),DAY(TODAY()),DAY(EOMONTH(PlanMonth,0))))<>"x",COLUMN(OFFSET(C25,0,0,1,IF(MONTH(TODAY())=MONTH(PlanMonth),DAY(TODAY()),DAY(EOMONTH(PlanMonth,0)))))-COLUMN(C25)+1,0)),0))}
AH26: =IF(B26="","",COUNTIF(C26:AG26,"x")) | AI26: =IF(B26="","",AH26/MAX(1,IF(MONTH(TODAY())=MONTH(PlanMonth),DAY(TODAY()),DAY(EOMONTH(PlanMonth,0))))) | AJ26: {=IF(B26="","",IFERROR(IF(MONTH(TODAY())=MONTH(PlanMonth),DAY(TODAY()),DAY(EOMONTH(PlanMonth,0)))-MAX(IF(OFFSET(C26,0,0,1,IF(MONTH(TODAY())=MONTH(PlanMonth),DAY(TODAY()),DAY(EOMONTH(PlanMonth,0))))<>"x",COLUMN(OFFSET(C26,0,0,1,IF(MONTH(TODAY())=MONTH(PlanMonth),DAY(TODAY()),DAY(EOMONTH(PlanMonth,0)))))-COLUMN(C26)+1,0)),0))}

Sheet Cleaning
B2: Cleaning Schedule
B3: Type the date you last did each chore. Next due date and status update themselves.
B6: Chore | C6: Frequency | D6: Room | E6: Last done | F6: Next due | G6: Status
B7: Wipe kitchen counters | C7: Daily | D7: Kitchen | E7: 46307 | F7: =IF(OR(B7="",C7=""),"",IF(E7="",TODAY(),E7+IF(C7="Daily",1,IF(C7="Weekly",7,IF(C7="Every 2 weeks",14,IF(C7="Monthly",30,IF(C7="Quarterly",91,IF(C7="Half-yearly",182,365)))))))) | G7: =IF(F7="","",IF(F7<TODAY(),"Overdue",IF(F7=TODAY(),"Today","Upcoming")))
B8: Load / empty dishwasher | C8: Daily | D8: Kitchen | E8: 46307 | F8: =IF(OR(B8="",C8=""),"",IF(E8="",TODAY(),E8+IF(C8="Daily",1,IF(C8="Weekly",7,IF(C8="Every 2 weeks",14,IF(C8="Monthly",30,IF(C8="Quarterly",91,IF(C8="Half-yearly",182,365)))))))) | G8: =IF(F8="","",IF(F8<TODAY(),"Overdue",IF(F8=TODAY(),"Today","Upcoming")))
B9: Quick bathroom wipe | C9: Daily | D9: Bathroom | E9: 46306 | F9: =IF(OR(B9="",C9=""),"",IF(E9="",TODAY(),E9+IF(C9="Daily",1,IF(C9="Weekly",7,IF(C9="Every 2 weeks",14,IF(C9="Monthly",30,IF(C9="Quarterly",91,IF(C9="Half-yearly",182,365)))))))) | G9: =IF(F9="","",IF(F9<TODAY(),"Overdue",IF(F9=TODAY(),"Today","Upcoming")))
B10: Vacuum floors | C10: Weekly | D10: Whole home | E10: 46303 | F10: =IF(OR(B10="",C10=""),"",IF(E10="",TODAY(),E10+IF(C10="Daily",1,IF(C10="Weekly",7,IF(C10="Every 2 weeks",14,IF(C10="Monthly",30,IF(C10="Quarterly",91,IF(C10="Half-yearly",182,365)))))))) | G10: =IF(F10="","",IF(F10<TODAY(),"Overdue",IF(F10=TODAY(),"Today","Upcoming")))
B11: Change bed sheets | C11: Weekly | D11: Bedroom | E11: 46299 | F11: =IF(OR(B11="",C11=""),"",IF(E11="",TODAY(),E11+IF(C11="Daily",1,IF(C11="Weekly",7,IF(C11="Every 2 weeks",14,IF(C11="Monthly",30,IF(C11="Quarterly",91,IF(C11="Half-yearly",182,365)))))))) | G11: =IF(F11="","",IF(F11<TODAY(),"Overdue",IF(F11=TODAY(),"Today","Upcoming")))
B12: Clean toilets | C12: Weekly | D12: Bathroom | E12: 46301 | F12: =IF(OR(B12="",C12=""),"",IF(E12="",TODAY(),E12+IF(C12="Daily",1,IF(C12="Weekly",7,IF(C12="Every 2 weeks",14,IF(C12="Monthly",30,IF(C12="Quarterly",91,IF(C12="Half-yearly",182,365)))))))) | G12: =IF(F12="","",IF(F12<TODAY(),"Overdue",IF(F12=TODAY(),"Today","Upcoming")))
B13: Mop floors | C13: Weekly | D13: Whole home | E13: 46302 | F13: =IF(OR(B13="",C13=""),"",IF(E13="",TODAY(),E13+IF(C13="Daily",1,IF(C13="Weekly",7,IF(C13="Every 2 weeks",14,IF(C13="Monthly",30,IF(C13="Quarterly",91,IF(C13="Half-yearly",182,365)))))))) | G13: =IF(F13="","",IF(F13<TODAY(),"Overdue",IF(F13=TODAY(),"Today","Upcoming")))
B14: Clean out fridge | C14: Weekly | D14: Kitchen | E14: 46298 | F14: =IF(OR(B14="",C14=""),"",IF(E14="",TODAY(),E14+IF(C14="Daily",1,IF(C14="Weekly",7,IF(C14="Every 2 weeks",14,IF(C14="Monthly",30,IF(C14="Quarterly",91,IF(C14="Half-yearly",182,365)))))))) | G14: =IF(F14="","",IF(F14<TODAY(),"Overdue",IF(F14=TODAY(),"Today","Upcoming")))
B15: Dust surfaces | C15: Weekly | D15: Living room | E15: 46304 | F15: =IF(OR(B15="",C15=""),"",IF(E15="",TODAY(),E15+IF(C15="Daily",1,IF(C15="Weekly",7,IF(C15="Every 2 weeks",14,IF(C15="Monthly",30,IF(C15="Quarterly",91,IF(C15="Half-yearly",182,365)))))))) | G15: =IF(F15="","",IF(F15<TODAY(),"Overdue",IF(F15=TODAY(),"Today","Upcoming")))
B16: Clean oven | C16: Monthly | D16: Kitchen | E16: 46267 | F16: =IF(OR(B16="",C16=""),"",IF(E16="",TODAY(),E16+IF(C16="Daily",1,IF(C16="Weekly",7,IF(C16="Every 2 weeks",14,IF(C16="Monthly",30,IF(C16="Quarterly",91,IF(C16="Half-yearly",182,365)))))))) | G16: =IF(F16="","",IF(F16<TODAY(),"Overdue",IF(F16=TODAY(),"Today","Upcoming")))
B17: Wash windows inside | C17: Monthly | D17: Whole home | E17: 46287 | F17: =IF(OR(B17="",C17=""),"",IF(E17="",TODAY(),E17+IF(C17="Daily",1,IF(C17="Weekly",7,IF(C17="Every 2 weeks",14,IF(C17="Monthly",30,IF(C17="Quarterly",91,IF(C17="Half-yearly",182,365)))))))) | G17: =IF(F17="","",IF(F17<TODAY(),"Overdue",IF(F17=TODAY(),"Today","Upcoming")))
B18: Descale kettle | C18: Monthly | D18: Kitchen | E18: 46292 | F18: =IF(OR(B18="",C18=""),"",IF(E18="",TODAY(),E18+IF(C18="Daily",1,IF(C18="Weekly",7,IF(C18="Every 2 weeks",14,IF(C18="Monthly",30,IF(C18="Quarterly",91,IF(C18="Half-yearly",182,365)))))))) | G18: =IF(F18="","",IF(F18<TODAY(),"Overdue",IF(F18=TODAY(),"Today","Upcoming")))
... B22: Clear gutters | C22: Yearly | D22: Outside | E22: 46007 | F22: =IF(OR(B22="",C22=""),"",IF(E22="",TODAY(),E22+IF(C22="Daily",1,IF(C22="Weekly",7,IF(C22="Every 2 weeks",14,IF(C22="Monthly",30,IF(C22="Quarterly",91,IF(C22="Half-yearly",182,365)))))))) | G22: =IF(F22="","",IF(F22<TODAY(),"Overdue",IF(F22=TODAY(),"Today","Upcoming")))
F23: =IF(OR(B23="",C23=""),"",IF(E23="",TODAY(),E23+IF(C23="Daily",1,IF(C23="Weekly",7,IF(C23="Every 2 weeks",14,IF(C23="Monthly",30,IF(C23="Quarterly",91,IF(C23="Half-yearly",182,365)))))))) | G23: =IF(F23="","",IF(F23<TODAY(),"Overdue",IF(F23=TODAY(),"Today","Upcoming")))
F24: =IF(OR(B24="",C24=""),"",IF(E24="",TODAY(),E24+IF(C24="Daily",1,IF(C24="Weekly",7,IF(C24="Every 2 weeks",14,IF(C24="Monthly",30,IF(C24="Quarterly",91,IF(C24="Half-yearly",182,365)))))))) | G24: =IF(F24="","",IF(F24<TODAY(),"Overdue",IF(F24=TODAY(),"Today","Upcoming")))
F25: =IF(OR(B25="",C25=""),"",IF(E25="",TODAY(),E25+IF(C25="Daily",1,IF(C25="Weekly",7,IF(C25="Every 2 weeks",14,IF(C25="Monthly",30,IF(C25="Quarterly",91,IF(C25="Half-yearly",182,365)))))))) | G25: =IF(F25="","",IF(F25<TODAY(),"Overdue",IF(F25=TODAY(),"Today","Upcoming")))
F26: =IF(OR(B26="",C26=""),"",IF(E26="",TODAY(),E26+IF(C26="Daily",1,IF(C26="Weekly",7,IF(C26="Every 2 weeks",14,IF(C26="Monthly",30,IF(C26="Quarterly",91,IF(C26="Half-yearly",182,365)))))))) | G26: =IF(F26="","",IF(F26<TODAY(),"Overdue",IF(F26=TODAY(),"Today","Upcoming")))
F27: =IF(OR(B27="",C27=""),"",IF(E27="",TODAY(),E27+IF(C27="Daily",1,IF(C27="Weekly",7,IF(C27="Every 2 weeks",14,IF(C27="Monthly",30,IF(C27="Quarterly",91,IF(C27="Half-yearly",182,365)))))))) | G27: =IF(F27="","",IF(F27<TODAY(),"Overdue",IF(F27=TODAY(),"Today","Upcoming")))
F28: =IF(OR(B28="",C28=""),"",IF(E28="",TODAY(),E28+IF(C28="Daily",1,IF(C28="Weekly",7,IF(C28="Every 2 weeks",14,IF(C28="Monthly",30,IF(C28="Quarterly",91,IF(C28="Half-yearly",182,365)))))))) | G28: =IF(F28="","",IF(F28<TODAY(),"Overdue",IF(F28=TODAY(),"Today","Upcoming")))
F29: =IF(OR(B29="",C29=""),"",IF(E29="",TODAY(),E29+IF(C29="Daily",1,IF(C29="Weekly",7,IF(C29="Every 2 weeks",14,IF(C29="Monthly",30,IF(C29="Quarterly",91,IF(C29="Half-yearly",182,365)))))))) | G29: =IF(F29="","",IF(F29<TODAY(),"Overdue",IF(F29=TODAY(),"Today","Upcoming")))
F30: =IF(OR(B30="",C30=""),"",IF(E30="",TODAY(),E30+IF(C30="Daily",1,IF(C30="Weekly",7,IF(C30="Every 2 weeks",14,IF(C30="Monthly",30,IF(C30="Quarterly",91,IF(C30="Half-yearly",182,365)))))))) | G30: =IF(F30="","",IF(F30<TODAY(),"Overdue",IF(F30=TODAY(),"Today","Upcoming")))
F31: =IF(OR(B31="",C31=""),"",IF(E31="",TODAY(),E31+IF(C31="Daily",1,IF(C31="Weekly",7,IF(C31="Every 2 weeks",14,IF(C31="Monthly",30,IF(C31="Quarterly",91,IF(C31="Half-yearly",182,365)))))))) | G31: =IF(F31="","",IF(F31<TODAY(),"Overdue",IF(F31=TODAY(),"Today","Upcoming")))
F32: =IF(OR(B32="",C32=""),"",IF(E32="",TODAY(),E32+IF(C32="Daily",1,IF(C32="Weekly",7,IF(C32="Every 2 weeks",14,IF(C32="Monthly",30,IF(C32="Quarterly",91,IF(C32="Half-yearly",182,365)))))))) | G32: =IF(F32="","",IF(F32<TODAY(),"Overdue",IF(F32=TODAY(),"Today","Upcoming")))
F33: =IF(OR(B33="",C33=""),"",IF(E33="",TODAY(),E33+IF(C33="Daily",1,IF(C33="Weekly",7,IF(C33="Every 2 weeks",14,IF(C33="Monthly",30,IF(C33="Quarterly",91,IF(C33="Half-yearly",182,365)))))))) | G33: =IF(F33="","",IF(F33<TODAY(),"Overdue",IF(F33=TODAY(),"Today","Upcoming")))
F34: =IF(OR(B34="",C34=""),"",IF(E34="",TODAY(),E34+IF(C34="Daily",1,IF(C34="Weekly",7,IF(C34="Every 2 weeks",14,IF(C34="Monthly",30,IF(C34="Quarterly",91,IF(C34="Half-yearly",182,365)))))))) | G34: =IF(F34="","",IF(F34<TODAY(),"Overdue",IF(F34=TODAY(),"Today","Upcoming")))
... F46: =IF(OR(B46="",C46=""),"",IF(E46="",TODAY(),E46+IF(C46="Daily",1,IF(C46="Weekly",7,IF(C46="Every 2 weeks",14,IF(C46="Monthly",30,IF(C46="Quarterly",91,IF(C46="Half-yearly",182,365)))))))) | G46: =IF(F46="","",IF(F46<TODAY(),"Overdue",IF(F46=TODAY(),"Today","Upcoming")))

Sheet Goals
B2: Goal Tracker
B3: Ten goals. For each: why it matters, five dated steps, and a reward. Tick steps with x.
B6: Goal | C6: Why it matters | D6: Deadline | E6: Done | F6: Progress
B7: Run a 10K | C7: Feel fit and proud | D7: 46537 | F7: =IF(B7="","",COUNTIF(E8:E12,"x")/5)
B8: Step 1 | C8: Buy running shoes | D8: 46297 | E8: x
B9: Step 2 | C9: Run 3K without stopping | D9: 46327 | E9: x
B10: Step 3 | C10: Run 5K | D10: 46357
B11: Step 4 | C11: Run 8K | D11: 46387
B12: Step 5 | C12: Race day | D12: 46417
B13: Reward | C13: New running watch
B15: Goal | C15: Why it matters | D15: Deadline | E15: Done | F15: Progress
B16: Save $5,000 emergency fund | C16: Stop worrying about surprise bills | D16: 46568 | F16: =IF(B16="","",COUNTIF(E17:E21,"x")/5)
B17: Step 1 | C17: Open savings account | D17: 46297 | E17: x
B18: Step 2 | C18: Automate $300 a month | D18: 46327
B19: Step 3 | C19: Reach $2,500 | D19: 46357
B20: Step 4 | C20: Reach $4,000 | D20: 46387
B21: Step 5 | C21: Reach $5,000 | D21: 46417
B22: Reward | C22: Weekend away
B24: Goal | C24: Why it matters | D24: Deadline | E24: Done | F24: Progress
F25: =IF(B25="","",COUNTIF(E26:E30,"x")/5)
B26: Step 1
B27: Step 2
B28: Step 3
B29: Step 4
B30: Step 5
B31: Reward
B33: Goal | C33: Why it matters | D33: Deadline | E33: Done | F33: Progress
F34: =IF(B34="","",COUNTIF(E35:E39,"x")/5)
B35: Step 1
B36: Step 2
B37: Step 3
B38: Step 4
B39: Step 5
B40: Reward
B42: Goal | C42: Why it matters | D42: Deadline | E42: Done | F42: Progress
F43: =IF(B43="","",COUNTIF(E44:E48,"x")/5)
B44: Step 1
B45: Step 2
B46: Step 3
B47: Step 4
B48: Step 5
B49: Reward
B51: Goal | C51: Why it matters | D51: Deadline | E51: Done | F51: Progress
F52: =IF(B52="","",COUNTIF(E53:E57,"x")/5)
B53: Step 1
B54: Step 2
B55: Step 3
B56: Step 4
B57: Step 5
B58: Reward
B60: Goal | C60: Why it matters | D60: Deadline | E60: Done | F60: Progress
F61: =IF(B61="","",COUNTIF(E62:E66,"x")/5)
B62: Step 1
B63: Step 2
B64: Step 3
B65: Step 4
B66: Step 5
B67: Reward
B69: Goal | C69: Why it matters | D69: Deadline | E69: Done | F69: Progress
F70: =IF(B70="","",COUNTIF(E71:E75,"x")/5)
B71: Step 1
B72: Step 2
B73: Step 3
B74: Step 4
B75: Step 5
B76: Reward
B78: Goal | C78: Why it matters | D78: Deadline | E78: Done | F78: Progress
F79: =IF(B79="","",COUNTIF(E80:E84,"x")/5)
B80: Step 1
B81: Step 2
B82: Step 3
B83: Step 4
B84: Step 5
B85: Reward
B87: Goal | C87: Why it matters | D87: Deadline | E87: Done | F87: Progress
F88: =IF(B88="","",COUNTIF(E89:E93,"x")/5)
B89: Step 1
B90: Step 2
B91: Step 3
B92: Step 4
B93: Step 5
B94: Reward

Sheet Week Plan
B2: Weekly Planner
B3: Plan your week by the hour. Type the Monday date once.
B5: Week of | C5: =TODAY()-WEEKDAY(TODAY(),3)
B6: Time | C6: Monday | D6: Tuesday | E6: Wednesday | F6: Thursday | G6: Friday | H6: Saturday | I6: Sunday
C7: =$C$5+0 | D7: =$C$5+1 | E7: =$C$5+2 | F7: =$C$5+3 | G7: =$C$5+4 | H7: =$C$5+5 | I7: =$C$5+6
B8: 06:00
B9: 07:00 | C9: Gym
B10: 08:00
B11: 09:00 | C11: Team meeting | F11: Report due | I11: Long run
B12: 10:00 | H12: Kids swim class
B13: 11:00
B14: 12:00 | D14: Lunch with Sam
B15: 13:00
B16: 14:00
B17: 15:00
B18: 16:00 | I18: Plan next week
B19: 17:00 | G19: Groceries
B20: 18:00 | E20: Meal prep
B21: 19:00
B22: 20:00
B23: 21:00
B24: 22:00
B27: Top 3 this week
B32: Notes

Sheet Meals
B2: Meal Planner & Grocery List
B3: Plan the week, then list what to buy by aisle. Tick items with x as you shop.
C6: Monday | D6: Tuesday | E6: Wednesday | F6: Thursday | G6: Friday | H6: Saturday | I6: Sunday
B7: Breakfast | C7: Oats & berries | D7: Yogurt & granola | E7: Eggs on toast | F7: Oats & berries | G7: Smoothie | H7: Pancakes | I7: Eggs & avocado
B8: Lunch | C8: Chicken wrap | D8: Pasta leftovers | E8: Tuna salad | F8: Soup & bread | G8: Grain bowl | H8: Picnic | I8: Roast leftovers
B9: Dinner | C9: Veggie stir-fry | D9: Spaghetti bolognese | E9: Fish tacos | F9: Chicken curry | G9: Homemade pizza | H9: Burgers | I9: Sunday roast
B10: Snacks | C10: Apple & nuts | D10: Hummus & carrots | E10: Banana | F10: Cheese & crackers | G10: Popcorn | H10: Fruit salad | I10: Dark chocolate
B13: Grocery list
B14: Aisle | C14: Produce | D14: Meat & Fish | E14: Dairy & Eggs | F14: Bakery | G14: Pantry | H14: Frozen | I14: Household
C15: Berries | D15: Chicken thighs | E15: Eggs (12) | F15: Whole wheat bread | G15: Oats | H15: Peas | I15: Dish soap
C16: Carrots | D16: Ground beef | E16: Greek yogurt | F16: Tortilla wraps | G16: Spaghetti | H16: Pizza bases | I16: Trash bags
C17: Avocados | D17: White fish | E17: Cheddar | G17: Curry paste
C18: Onions | G18: Canned tomatoes
C19: Spinach

Sheet Calendar
B2: Monthly Calendar
B3: Month = Planning month in Setup. Each day counts tasks due (Tasks tab).
B5: =PlanMonth
B6: Mon | C6: Tue | D6: Wed | E6: Thu | F6: Fri | G6: Sat | H6: Sun
B7: =IF(MONTH(PlanMonth-WEEKDAY(PlanMonth,3)+0)<>MONTH(PlanMonth),"",PlanMonth-WEEKDAY(PlanMonth,3)+0) | C7: =IF(MONTH(PlanMonth-WEEKDAY(PlanMonth,3)+1)<>MONTH(PlanMonth),"",PlanMonth-WEEKDAY(PlanMonth,3)+1) | D7: =IF(MONTH(PlanMonth-WEEKDAY(PlanMonth,3)+2)<>MONTH(PlanMonth),"",PlanMonth-WEEKDAY(PlanMonth,3)+2) | E7: =IF(MONTH(PlanMonth-WEEKDAY(PlanMonth,3)+3)<>MONTH(PlanMonth),"",PlanMonth-WEEKDAY(PlanMonth,3)+3) | F7: =IF(MONTH(PlanMonth-WEEKDAY(PlanMonth,3)+4)<>MONTH(PlanMonth),"",PlanMonth-WEEKDAY(PlanMonth,3)+4) | G7: =IF(MONTH(PlanMonth-WEEKDAY(PlanMonth,3)+5)<>MONTH(PlanMonth),"",PlanMonth-WEEKDAY(PlanMonth,3)+5) | H7: =IF(MONTH(PlanMonth-WEEKDAY(PlanMonth,3)+6)<>MONTH(PlanMonth),"",PlanMonth-WEEKDAY(PlanMonth,3)+6)
B8: =IF(B7="","",IF(COUNTIFS('Tasks'!$D$7:$D$106,B7,'Tasks'!$F$7:$F$106,"<>Done")=0,"",COUNTIFS('Tasks'!$D$7:$D$106,B7,'Tasks'!$F$7:$F$106,"<>Done")&" due")) | C8: =IF(C7="","",IF(COUNTIFS('Tasks'!$D$7:$D$106,C7,'Tasks'!$F$7:$F$106,"<>Done")=0,"",COUNTIFS('Tasks'!$D$7:$D$106,C7,'Tasks'!$F$7:$F$106,"<>Done")&" due")) | D8: =IF(D7="","",IF(COUNTIFS('Tasks'!$D$7:$D$106,D7,'Tasks'!$F$7:$F$106,"<>Done")=0,"",COUNTIFS('Tasks'!$D$7:$D$106,D7,'Tasks'!$F$7:$F$106,"<>Done")&" due")) | E8: =IF(E7="","",IF(COUNTIFS('Tasks'!$D$7:$D$106,E7,'Tasks'!$F$7:$F$106,"<>Done")=0,"",COUNTIFS('Tasks'!$D$7:$D$106,E7,'Tasks'!$F$7:$F$106,"<>Done")&" due")) | F8: =IF(F7="","",IF(COUNTIFS('Tasks'!$D$7:$D$106,F7,'Tasks'!$F$7:$F$106,"<>Done")=0,"",COUNTIFS('Tasks'!$D$7:$D$106,F7,'Tasks'!$F$7:$F$106,"<>Done")&" due")) | G8: =IF(G7="","",IF(COUNTIFS('Tasks'!$D$7:$D$106,G7,'Tasks'!$F$7:$F$106,"<>Done")=0,"",COUNTIFS('Tasks'!$D$7:$D$106,G7,'Tasks'!$F$7:$F$106,"<>Done")&" due")) | H8: =IF(H7="","",IF(COUNTIFS('Tasks'!$D$7:$D$106,H7,'Tasks'!$F$7:$F$106,"<>Done")=0,"",COUNTIFS('Tasks'!$D$7:$D$106,H7,'Tasks'!$F$7:$F$106,"<>Done")&" due"))
B9: =IF(MONTH(PlanMonth-WEEKDAY(PlanMonth,3)+7)<>MONTH(PlanMonth),"",PlanMonth-WEEKDAY(PlanMonth,3)+7) | C9: =IF(MONTH(PlanMonth-WEEKDAY(PlanMonth,3)+8)<>MONTH(PlanMonth),"",PlanMonth-WEEKDAY(PlanMonth,3)+8) | D9: =IF(MONTH(PlanMonth-WEEKDAY(PlanMonth,3)+9)<>MONTH(PlanMonth),"",PlanMonth-WEEKDAY(PlanMonth,3)+9) | E9: =IF(MONTH(PlanMonth-WEEKDAY(PlanMonth,3)+10)<>MONTH(PlanMonth),"",PlanMonth-WEEKDAY(PlanMonth,3)+10) | F9: =IF(MONTH(PlanMonth-WEEKDAY(PlanMonth,3)+11)<>MONTH(PlanMonth),"",PlanMonth-WEEKDAY(PlanMonth,3)+11) | G9: =IF(MONTH(PlanMonth-WEEKDAY(PlanMonth,3)+12)<>MONTH(PlanMonth),"",PlanMonth-WEEKDAY(PlanMonth,3)+12) | H9: =IF(MONTH(PlanMonth-WEEKDAY(PlanMonth,3)+13)<>MONTH(PlanMonth),"",PlanMonth-WEEKDAY(PlanMonth,3)+13)
B10: =IF(B9="","",IF(COUNTIFS('Tasks'!$D$7:$D$106,B9,'Tasks'!$F$7:$F$106,"<>Done")=0,"",COUNTIFS('Tasks'!$D$7:$D$106,B9,'Tasks'!$F$7:$F$106,"<>Done")&" due")) | C10: =IF(C9="","",IF(COUNTIFS('Tasks'!$D$7:$D$106,C9,'Tasks'!$F$7:$F$106,"<>Done")=0,"",COUNTIFS('Tasks'!$D$7:$D$106,C9,'Tasks'!$F$7:$F$106,"<>Done")&" due")) | D10: =IF(D9="","",IF(COUNTIFS('Tasks'!$D$7:$D$106,D9,'Tasks'!$F$7:$F$106,"<>Done")=0,"",COUNTIFS('Tasks'!$D$7:$D$106,D9,'Tasks'!$F$7:$F$106,"<>Done")&" due")) | E10: =IF(E9="","",IF(COUNTIFS('Tasks'!$D$7:$D$106,E9,'Tasks'!$F$7:$F$106,"<>Done")=0,"",COUNTIFS('Tasks'!$D$7:$D$106,E9,'Tasks'!$F$7:$F$106,"<>Done")&" due")) | F10: =IF(F9="","",IF(COUNTIFS('Tasks'!$D$7:$D$106,F9,'Tasks'!$F$7:$F$106,"<>Done")=0,"",COUNTIFS('Tasks'!$D$7:$D$106,F9,'Tasks'!$F$7:$F$106,"<>Done")&" due")) | G10: =IF(G9="","",IF(COUNTIFS('Tasks'!$D$7:$D$106,G9,'Tasks'!$F$7:$F$106,"<>Done")=0,"",COUNTIFS('Tasks'!$D$7:$D$106,G9,'Tasks'!$F$7:$F$106,"<>Done")&" due")) | H10: =IF(H9="","",IF(COUNTIFS('Tasks'!$D$7:$D$106,H9,'Tasks'!$F$7:$F$106,"<>Done")=0,"",COUNTIFS('Tasks'!$D$7:$D$106,H9,'Tasks'!$F$7:$F$106,"<>Done")&" due"))
B11: =IF(MONTH(PlanMonth-WEEKDAY(PlanMonth,3)+14)<>MONTH(PlanMonth),"",PlanMonth-WEEKDAY(PlanMonth,3)+14) | C11: =IF(MONTH(PlanMonth-WEEKDAY(PlanMonth,3)+15)<>MONTH(PlanMonth),"",PlanMonth-WEEKDAY(PlanMonth,3)+15) | D11: =IF(MONTH(PlanMonth-WEEKDAY(PlanMonth,3)+16)<>MONTH(PlanMonth),"",PlanMonth-WEEKDAY(PlanMonth,3)+16) | E11: =IF(MONTH(PlanMonth-WEEKDAY(PlanMonth,3)+17)<>MONTH(PlanMonth),"",PlanMonth-WEEKDAY(PlanMonth,3)+17) | F11: =IF(MONTH(PlanMonth-WEEKDAY(PlanMonth,3)+18)<>MONTH(PlanMonth),"",PlanMonth-WEEKDAY(PlanMonth,3)+18) | G11: =IF(MONTH(PlanMonth-WEEKDAY(PlanMonth,3)+19)<>MONTH(PlanMonth),"",PlanMonth-WEEKDAY(PlanMonth,3)+19) | H11: =IF(MONTH(PlanMonth-WEEKDAY(PlanMonth,3)+20)<>MONTH(PlanMonth),"",PlanMonth-WEEKDAY(PlanMonth,3)+20)
B12: =IF(B11="","",IF(COUNTIFS('Tasks'!$D$7:$D$106,B11,'Tasks'!$F$7:$F$106,"<>Done")=0,"",COUNTIFS('Tasks'!$D$7:$D$106,B11,'Tasks'!$F$7:$F$106,"<>Done")&" due")) | C12: =IF(C11="","",IF(COUNTIFS('Tasks'!$D$7:$D$106,C11,'Tasks'!$F$7:$F$106,"<>Done")=0,"",COUNTIFS('Tasks'!$D$7:$D$106,C11,'Tasks'!$F$7:$F$106,"<>Done")&" due")) | D12: =IF(D11="","",IF(COUNTIFS('Tasks'!$D$7:$D$106,D11,'Tasks'!$F$7:$F$106,"<>Done")=0,"",COUNTIFS('Tasks'!$D$7:$D$106,D11,'Tasks'!$F$7:$F$106,"<>Done")&" due")) | E12: =IF(E11="","",IF(COUNTIFS('Tasks'!$D$7:$D$106,E11,'Tasks'!$F$7:$F$106,"<>Done")=0,"",COUNTIFS('Tasks'!$D$7:$D$106,E11,'Tasks'!$F$7:$F$106,"<>Done")&" due")) | F12: =IF(F11="","",IF(COUNTIFS('Tasks'!$D$7:$D$106,F11,'Tasks'!$F$7:$F$106,"<>Done")=0,"",COUNTIFS('Tasks'!$D$7:$D$106,F11,'Tasks'!$F$7:$F$106,"<>Done")&" due")) | G12: =IF(G11="","",IF(COUNTIFS('Tasks'!$D$7:$D$106,G11,'Tasks'!$F$7:$F$106,"<>Done")=0,"",COUNTIFS('Tasks'!$D$7:$D$106,G11,'Tasks'!$F$7:$F$106,"<>Done")&" due")) | H12: =IF(H11="","",IF(COUNTIFS('Tasks'!$D$7:$D$106,H11,'Tasks'!$F$7:$F$106,"<>Done")=0,"",COUNTIFS('Tasks'!$D$7:$D$106,H11,'Tasks'!$F$7:$F$106,"<>Done")&" due"))
B13: =IF(MONTH(PlanMonth-WEEKDAY(PlanMonth,3)+21)<>MONTH(PlanMonth),"",PlanMonth-WEEKDAY(PlanMonth,3)+21) | C13: =IF(MONTH(PlanMonth-WEEKDAY(PlanMonth,3)+22)<>MONTH(PlanMonth),"",PlanMonth-WEEKDAY(PlanMonth,3)+22) | D13: =IF(MONTH(PlanMonth-WEEKDAY(PlanMonth,3)+23)<>MONTH(PlanMonth),"",PlanMonth-WEEKDAY(PlanMonth,3)+23) | E13: =IF(MONTH(PlanMonth-WEEKDAY(PlanMonth,3)+24)<>MONTH(PlanMonth),"",PlanMonth-WEEKDAY(PlanMonth,3)+24) | F13: =IF(MONTH(PlanMonth-WEEKDAY(PlanMonth,3)+25)<>MONTH(PlanMonth),"",PlanMonth-WEEKDAY(PlanMonth,3)+25) | G13: =IF(MONTH(PlanMonth-WEEKDAY(PlanMonth,3)+26)<>MONTH(PlanMonth),"",PlanMonth-WEEKDAY(PlanMonth,3)+26) | H13: =IF(MONTH(PlanMonth-WEEKDAY(PlanMonth,3)+27)<>MONTH(PlanMonth),"",PlanMonth-WEEKDAY(PlanMonth,3)+27)
B14: =IF(B13="","",IF(COUNTIFS('Tasks'!$D$7:$D$106,B13,'Tasks'!$F$7:$F$106,"<>Done")=0,"",COUNTIFS('Tasks'!$D$7:$D$106,B13,'Tasks'!$F$7:$F$106,"<>Done")&" due")) | C14: =IF(C13="","",IF(COUNTIFS('Tasks'!$D$7:$D$106,C13,'Tasks'!$F$7:$F$106,"<>Done")=0,"",COUNTIFS('Tasks'!$D$7:$D$106,C13,'Tasks'!$F$7:$F$106,"<>Done")&" due")) | D14: =IF(D13="","",IF(COUNTIFS('Tasks'!$D$7:$D$106,D13,'Tasks'!$F$7:$F$106,"<>Done")=0,"",COUNTIFS('Tasks'!$D$7:$D$106,D13,'Tasks'!$F$7:$F$106,"<>Done")&" due")) | E14: =IF(E13="","",IF(COUNTIFS('Tasks'!$D$7:$D$106,E13,'Tasks'!$F$7:$F$106,"<>Done")=0,"",COUNTIFS('Tasks'!$D$7:$D$106,E13,'Tasks'!$F$7:$F$106,"<>Done")&" due")) | F14: =IF(F13="","",IF(COUNTIFS('Tasks'!$D$7:$D$106,F13,'Tasks'!$F$7:$F$106,"<>Done")=0,"",COUNTIFS('Tasks'!$D$7:$D$106,F13,'Tasks'!$F$7:$F$106,"<>Done")&" due")) | G14: =IF(G13="","",IF(COUNTIFS('Tasks'!$D$7:$D$106,G13,'Tasks'!$F$7:$F$106,"<>Done")=0,"",COUNTIFS('Tasks'!$D$7:$D$106,G13,'Tasks'!$F$7:$F$106,"<>Done")&" due")) | H14: =IF(H13="","",IF(COUNTIFS('Tasks'!$D$7:$D$106,H13,'Tasks'!$F$7:$F$106,"<>Done")=0,"",COUNTIFS('Tasks'!$D$7:$D$106,H13,'Tasks'!$F$7:$F$106,"<>Done")&" due"))
B15: =IF(MONTH(PlanMonth-WEEKDAY(PlanMonth,3)+28)<>MONTH(PlanMonth),"",PlanMonth-WEEKDAY(PlanMonth,3)+28) | C15: =IF(MONTH(PlanMonth-WEEKDAY(PlanMonth,3)+29)<>MONTH(PlanMonth),"",PlanMonth-WEEKDAY(PlanMonth,3)+29) | D15: =IF(MONTH(PlanMonth-WEEKDAY(PlanMonth,3)+30)<>MONTH(PlanMonth),"",PlanMonth-WEEKDAY(PlanMonth,3)+30) | E15: =IF(MONTH(PlanMonth-WEEKDAY(PlanMonth,3)+31)<>MONTH(PlanMonth),"",PlanMonth-WEEKDAY(PlanMonth,3)+31) | F15: =IF(MONTH(PlanMonth-WEEKDAY(PlanMonth,3)+32)<>MONTH(PlanMonth),"",PlanMonth-WEEKDAY(PlanMonth,3)+32) | G15: =IF(MONTH(PlanMonth-WEEKDAY(PlanMonth,3)+33)<>MONTH(PlanMonth),"",PlanMonth-WEEKDAY(PlanMonth,3)+33) | H15: =IF(MONTH(PlanMonth-WEEKDAY(PlanMonth,3)+34)<>MONTH(PlanMonth),"",PlanMonth-WEEKDAY(PlanMonth,3)+34)
B16: =IF(B15="","",IF(COUNTIFS('Tasks'!$D$7:$D$106,B15,'Tasks'!$F$7:$F$106,"<>Done")=0,"",COUNTIFS('Tasks'!$D$7:$D$106,B15,'Tasks'!$F$7:$F$106,"<>Done")&" due")) | C16: =IF(C15="","",IF(COUNTIFS('Tasks'!$D$7:$D$106,C15,'Tasks'!$F$7:$F$106,"<>Done")=0,"",COUNTIFS('Tasks'!$D$7:$D$106,C15,'Tasks'!$F$7:$F$106,"<>Done")&" due")) | D16: =IF(D15="","",IF(COUNTIFS('Tasks'!$D$7:$D$106,D15,'Tasks'!$F$7:$F$106,"<>Done")=0,"",COUNTIFS('Tasks'!$D$7:$D$106,D15,'Tasks'!$F$7:$F$106,"<>Done")&" due")) | E16: =IF(E15="","",IF(COUNTIFS('Tasks'!$D$7:$D$106,E15,'Tasks'!$F$7:$F$106,"<>Done")=0,"",COUNTIFS('Tasks'!$D$7:$D$106,E15,'Tasks'!$F$7:$F$106,"<>Done")&" due")) | F16: =IF(F15="","",IF(COUNTIFS('Tasks'!$D$7:$D$106,F15,'Tasks'!$F$7:$F$106,"<>Done")=0,"",COUNTIFS('Tasks'!$D$7:$D$106,F15,'Tasks'!$F$7:$F$106,"<>Done")&" due")) | G16: =IF(G15="","",IF(COUNTIFS('Tasks'!$D$7:$D$106,G15,'Tasks'!$F$7:$F$106,"<>Done")=0,"",COUNTIFS('Tasks'!$D$7:$D$106,G15,'Tasks'!$F$7:$F$106,"<>Done")&" due")) | H16: =IF(H15="","",IF(COUNTIFS('Tasks'!$D$7:$D$106,H15,'Tasks'!$F$7:$F$106,"<>Done")=0,"",COUNTIFS('Tasks'!$D$7:$D$106,H15,'Tasks'!$F$7:$F$106,"<>Done")&" due"))
B17: =IF(MONTH(PlanMonth-WEEKDAY(PlanMonth,3)+35)<>MONTH(PlanMonth),"",PlanMonth-WEEKDAY(PlanMonth,3)+35) | C17: =IF(MONTH(PlanMonth-WEEKDAY(PlanMonth,3)+36)<>MONTH(PlanMonth),"",PlanMonth-WEEKDAY(PlanMonth,3)+36) | D17: =IF(MONTH(PlanMonth-WEEKDAY(PlanMonth,3)+37)<>MONTH(PlanMonth),"",PlanMonth-WEEKDAY(PlanMonth,3)+37) | E17: =IF(MONTH(PlanMonth-WEEKDAY(PlanMonth,3)+38)<>MONTH(PlanMonth),"",PlanMonth-WEEKDAY(PlanMonth,3)+38) | F17: =IF(MONTH(PlanMonth-WEEKDAY(PlanMonth,3)+39)<>MONTH(PlanMonth),"",PlanMonth-WEEKDAY(PlanMonth,3)+39) | G17: =IF(MONTH(PlanMonth-WEEKDAY(PlanMonth,3)+40)<>MONTH(PlanMonth),"",PlanMonth-WEEKDAY(PlanMonth,3)+40) | H17: =IF(MONTH(PlanMonth-WEEKDAY(PlanMonth,3)+41)<>MONTH(PlanMonth),"",PlanMonth-WEEKDAY(PlanMonth,3)+41)
B18: =IF(B17="","",IF(COUNTIFS('Tasks'!$D$7:$D$106,B17,'Tasks'!$F$7:$F$106,"<>Done")=0,"",COUNTIFS('Tasks'!$D$7:$D$106,B17,'Tasks'!$F$7:$F$106,"<>Done")&" due")) | C18: =IF(C17="","",IF(COUNTIFS('Tasks'!$D$7:$D$106,C17,'Tasks'!$F$7:$F$106,"<>Done")=0,"",COUNTIFS('Tasks'!$D$7:$D$106,C17,'Tasks'!$F$7:$F$106,"<>Done")&" due")) | D18: =IF(D17="","",IF(COUNTIFS('Tasks'!$D$7:$D$106,D17,'Tasks'!$F$7:$F$106,"<>Done")=0,"",COUNTIFS('Tasks'!$D$7:$D$106,D17,'Tasks'!$F$7:$F$106,"<>Done")&" due")) | E18: =IF(E17="","",IF(COUNTIFS('Tasks'!$D$7:$D$106,E17,'Tasks'!$F$7:$F$106,"<>Done")=0,"",COUNTIFS('Tasks'!$D$7:$D$106,E17,'Tasks'!$F$7:$F$106,"<>Done")&" due")) | F18: =IF(F17="","",IF(COUNTIFS('Tasks'!$D$7:$D$106,F17,'Tasks'!$F$7:$F$106,"<>Done")=0,"",COUNTIFS('Tasks'!$D$7:$D$106,F17,'Tasks'!$F$7:$F$106,"<>Done")&" due")) | G18: =IF(G17="","",IF(COUNTIFS('Tasks'!$D$7:$D$106,G17,'Tasks'!$F$7:$F$106,"<>Done")=0,"",COUNTIFS('Tasks'!$D$7:$D$106,G17,'Tasks'!$F$7:$F$106,"<>Done")&" due")) | H18: =IF(H17="","",IF(COUNTIFS('Tasks'!$D$7:$D$106,H17,'Tasks'!$F$7:$F$106,"<>Done")=0,"",COUNTIFS('Tasks'!$D$7:$D$106,H17,'Tasks'!$F$7:$F$106,"<>Done")&" due"))
